Workbook

Sheet Master Data All
A1: Timestamp | B1: Tanggal Pengajuan | C1: Nama Pemohon Kredit | D1: Nomor Telepon Pemohon Kredit | E1: Pekerjaan Pemohon Kredit | F1: Penghasilan Bulanan Pemohon Kredit | G1: Apakah ada NPWP | H1: Total limit yang didapatkan | I1: Status pengajuan | J1: Kendala saat pengajuan | K1: Upload bukti pengajuan | L1: Area | M1: Tipe HP VIVO yang diambil konsumen | N1: Sator Area Kupang | O1: Sator Area Sumba | P1: Nama Promotor | Q1: Nama Promotor | R1: Nama Promotor | S1: Nama Promotor | T1: Nama Promotor | U1: Nama Promotor | V1: Nama Promotor | W1: Nama Promotor | X1: Nama Promotor | Y1: Column 25 | Z1: Column 26 | AA1: Column 27
A2: 45897.586 | C2: TRIYUANI REINNAMAH | D2: +62 856-8309-785 | E2: SELES | F2: 2JT | G2: Tidak ada | H2: 0 | I2: Reject | J2: - | K2: https://drive.google.com/open?id=1v-cfYDTQqA-R55g32y0mMpJ2Xden8dLJ | L2: Kupang Kota | Q2: DEMARISTI S H FENI
A3: 45897.593 | C3: Adeltrudis hoar | D3: +62 812-5358-4502 | E3: Wiraswasta | F3: 4500000 | G3: Tidak ada | H3: 7.000.000 | I3: Acc | J3: Tidak ada | K3: https://drive.google.com/open?id=1EEnKnPzj4BU5jvvOVf4vlRw3IDTngY6j | L3: Kupang Kota | M3: Y400 | Q3: EMPI FRANGKI LIEM
A4: 45897.594 | C4: Imelda febriana magdalena lelik | D4: +62 857-3874-4175 | E4: Wiraswasta | F4: 4 | G4: Tidak ada | H4: 4.300.000 | I4: Reject | J4: Tidak ada | K4: https://drive.google.com/open?id=1bd8ocKNWbiY1qE9xEiaaeCRMM5-RAEM1 | L4: Kupang Kota | Q4: EMPI FRANGKI LIEM
A5: 45897.606 | C5: Pricsa Fita Chandra Ayu Defretes | D5: +62 877-1590-0008 | E5: Pegawai Swasta | F5: 8-9jt | G5: Ada | H5: - | I5: Reject | J5: - | K5: https://drive.google.com/open?id=1KMM1glijqISnf_J2s7Chw-PKVClwBDzo | L5: Kupang Kota | Q5: YOHANA NOVIANA MARIANA GAA
A6: 45897.639 | C6: Romana Pati | D6: 081230387876 | E6: Pegawai Swasta | F6: 3.500.000 | G6: Tidak ada | H6: Tidak Ada | I6: Reject | J6: Tidak Ada | K6: https://drive.google.com/open?id=1Umo2LS8svJPAB-3fFIgZVewcMcwe4OY8 | L6: Kupang Kota | Q6: PATRIANI MENGI ULY
A7: 45897.649 | C7: Derison lot saluk | D7: 085959344060 | E7: Pemilik pangkas rambut | F7: 3.500.000 | G7: Tidak ada | H7: Tidak ada | I7: Reject | J7: Tidak ada | K7: https://drive.google.com/open?id=1If_zKQvOp5junZ0JAq22Ln94GqwOTGvG | L7: Kupang Kota | Q7: NOVANTRY RUTHANIA NAFFIE
A8: 45897.651 | C8: Melani sara betty | D8: 081998343074 | E8: Online shop butik | F8: 2.500.000 | G8: Tidak ada | H8: Tidak ada | I8: Reject | J8: Tidak dapat limite | K8: https://drive.google.com/open?id=1wDAR-QAoBMP1AFr8tN4HQP_snrdSDpFY | L8: Kupang Kota | Q8: NOVANTRY RUTHANIA NAFFIE
A9: 45897.652 | C9: Novita Mea Ikun Pires | D9: 081236833055 | E9: Pegawai Swasta | F9: 3-4jt | G9: Tidak ada | H9: - | I9: Reject | J9: - | K9: https://drive.google.com/open?id=1zMbcG1lRzhverF7lB1BtbGfPrsd_cgeH | L9: Kupang Kota | Q9: YOHANA NOVIANA MARIANA GAA
A10: 45897.692 | C10: ALEXA DEHOOG | D10: 082217974397 | E10: KARYAWAN SWASTA | F10: 3JT | G10: Tidak ada | H10: 3jt | I10: Acc | J10: - | K10: https://drive.google.com/open?id=1rEp7-vGA12-eDqwR9-3guAOPU3x17IRj | L10: Kupang Kota | M10: Y400 | Q10: DEMARISTI S H FENI
A11: 45897.754 | C11: Maria Inggrid Dogho | D11: 082236726681 | E11: GURU TK PERTIWI | F11: 4.600.000 | G11: Ada | H11: 3.000.000 | I11: Dapat Limit Cuma Dp kurang, masih pulang Bicara Sama Suami Soal Dp | J11: Tidak Ada | K11: https://drive.google.com/open?id=1rRiHChF6lS8XOFDgK-X5qiGX5u3XwASD | L11: Kupang Kota | Q11: YOHANIS TIPNONI
A12: 45897.779 | C12: DOMINGGUS CRISTIAN LEDE | D12: 0811 | E12: Dinas lingkungan dan kebersihan kota kupang | F12: 4.100.000 | G12: Tidak ada | H12: 0 | I12: Reject | J12: tidak ad | K12: https://drive.google.com/open?id=1eDTdhgf1M0aYwBhJdujtSOP_7GChk5Hy | L12: Kupang Kota | Q12: YASINTHA MBU
A13: 45897.78 | C13: Diniati kiki | D13: 082121166521 | E13: Usaha kios | F13: 5.600.000 | G13: Tidak ada | H13: 0 | I13: Sistem masih bermasalah | J13: Nama toko tidak sesuai | K13: https://drive.google.com/open?id=1lv3v6LtVw6JeFo3ACOX3n4QmsdHKoKtG | L13: Kupang Kota | Q13: AINI RAHMATINI NATALIA MOESTAKIM
A14: 45897.781 | C14: Rivaldo nunes | D14: 081237415440 | E14: Wiraswasta | F14: 6.000.000 | G14: Tidak ada | H14: 0 | I14: Sistem bermasalah | J14: Nama toko tidak sesuai | K14: https://drive.google.com/open?id=1B1MwnAjmIQ53ybBXzWRc1E4R86t-OEns | L14: Kupang Kota | Q14: AINI RAHMATINI NATALIA MOESTAKIM
A15: 45897.8 | C15: Anis | D15: 12345678 | E15: Tukang | F15: 2000000 | G15: Tidak ada | H15: 0 | I15: Reject | J15: - | K15: https://drive.google.com/open?id=1szhhvdFusPgOAt9Fcr_gIiUaQ5wUFGrv | L15: Kabupaten | Q15: Tes
A16: 45897.809 | C16: Agus | D16: 082147979471 | E16: Wiraswasta | F16: 10 | G16: Tidak ada | H16: 0 | I16: Reject | J16: Pas | K16: https://drive.google.com/open?id=1w6RCkrMHlBINEIPqpDZDfYISau1-VoZJ | L16: Kabupaten | Q16: Tes
A17: 45897.835 | C17: Maria goretitokan | D17: 081247920167 | E17: Anggota DPRD kabupaten kupang | F17: 7.000.000 | G17: Ada | H17: 0 | I17: Sistem eror | J17: Toko tidak sesuai | K17: https://drive.google.com/open?id=1x8rpntpmgkMZaHVEfyerFJmBfWOQBPUT | L17: Kupang Kota | Q17: AINI RAHMATINI NATALIA MOESTAKIM
A18: 45897.837 | C18: Rangga Djara | D18: 085119992958 | E18: Nelayan | F18: 1.500.000 | G18: Tidak ada | H18: 0 | I18: Reject | J18: - | K18: https://drive.google.com/open?id=1AGXZte4Yb-yCOjMBRQ831OFnxpEHY3m- | L18: Kupang Kota | Q18: FERI ELI KURNIAWAN
A19: 45898.38 | C19: RAFAEL RUNESI | D19: 085338580958 | E19: WIRASWASTA | F19: 4.200.000 | G19: Tidak ada | H19: 0 | I19: Reject | K19: https://drive.google.com/open?id=1Vd0fsJFiBXGfYIHSycubBlH2BpXH_AgF | L19: Kupang Kota | Q19: YASINTHA MBU
A20: 45898.499 | C20: Yavet hati | D20: 082146992105 | E20: Swasta | F20: 5.100.000 | G20: Tidak ada | H20: 7.000.000 | I20: Acc | J20: Tidak ada | K20: https://drive.google.com/open?id=1EJxzoNsNgAbP-nOggCWumQcgyShsv5dU | L20: Kupang Kota | M20: Y400 | Q20: YASINTHA MBU
A21: 45898.571 | C21: Maria Bella Savira Mbao | D21: 081236922745 | E21: Alfa Mart | F21: 3.700.000 | G21: Tidak ada | H21: Tidak ada | I21: Reject | J21: Tidak Dapat Limit | K21: https://drive.google.com/open?id=14ehdJhB5qvnEMFUTjcuAXJiNVSTDhWo- | L21: Kupang Kota | Q21: YOHANIS TIPNONI
A22: 45898.659 | C22: Yuni yulianer suni | D22: 081529259284 | E22: Jaga warung | F22: 2.000.000 | G22: Tidak ada | H22: Tdk dpt limited | I22: Reject | J22: Toko di Sistem tidak sesuai | K22: https://drive.google.com/open?id=10JmHEAWciNGbbewtF8pGd0yImG8FBKrW | L22: Kupang Kota | M22: Y400 | Q22: WARDIA
A23: 45898.676 | C23: IBRAHIM KUSUMA | D23: 081214553021 | E23: Nelayan | F23: 5.700.000 | G23: Tidak ada | H23: 0 | I23: belum dapat limit | J23: belum dapat limit | K23: https://drive.google.com/open?id=16aYa7bofZteV9nGu-VIcZuA-DHA9bSfL | L23: Kupang Kota | M23: Y400 | Q23: YASINTHA MBU
A24: 45898.792 | C24: Adriana luan | D24: 081337998055 | E24: ASN | F24: 5.700.000 | G24: Tidak ada | H24: 7.0000.000 | I24: Acc | J24: tidak ada | K24: https://drive.google.com/open?id=1Zlb06HvHIArpia6RmZLkOfeL7kHkk9Pc | L24: Kupang Kota | M24: V50 LITE | Q24: YASINTHA MBU
A25: 45898.836 | C25: Richi | D25: 082334922953 | E25: Dinas Kesehatan | F25: 3000000 | G25: Tidak ada | H25: 0 | I25: Tidak dapat limit | J25: Pengajuan Kadaluarsa | K25: https://drive.google.com/open?id=1Rfjpfn8wH63-dlGpgFrzF9P681ai2uZ2 | L25: Kupang Kota | M25: Y400 | Q25: SELVINCE BAKO
A26: 45898.865 | C26: Meryanti foeh | D26: - | E26: Wiraswasta | F26: 2jt | G26: Tidak ada | H26: 0 | I26: Reject | J26: Tidak dapat limit | K26: https://drive.google.com/open?id=1O66NvvEF15ofHKvQeyXS1DF8cH1jTH3X | L26: Kupang Kota | M26: Y400 | Q26: SKOLASTIKA B TAUNAES
A27: 45898.865 | C27: Yohana | D27: 08123608690 | E27: Wiraswasta | F27: 0 | G27: Tidak ada | H27: 0 | I27: Tidak dapt limit | J27: Pengajuan Kadaluarsa | K27: https://drive.google.com/open?id=1wmofbO6IAaXPJ9bz1b1yVIYSyu8W8-hx | L27: Kupang Kota | M27: Lain nya... | Q27: SELVINCE BAKO
A28: 45898.867 | C28: Marcia Estin Wathun ximenes | D28: 082298258277 | E28: Wiraswasta | F28: 5.700.000 | G28: Tidak ada | H28: Tidak ada | I28: Tidak dapat limit | J28: Tidak dapat limit | K28: https://drive.google.com/open?id=1B7iDB3xt_eSksY-i5-wrRq3YFS99U7OZ | L28: Kupang Kota | M28: Y400 | Q28: YOHANIS TIPNONI
A29: 45898.867 | C29: Fory Yani F. Tasi | D29: - | E29: Wiraswasta | F29: 2.500.000 | G29: Tidak ada | H29: 0 | I29: Reject | J29: Tidak dapat limit | K29: https://drive.google.com/open?id=1VnURt4QYqFB5k4ks6_7wFARP9SrSrR0g | L29: Kupang Kota | M29: Y400 | Q29: SKOLASTIKA B TAUNAES
A30: 45898.87 | C30: Marsela Sinlaeloe | D30: 082266021692 | E30: Karyawan | F30: 3.400.000 | G30: Tidak ada | H30: Tidak ada | I30: Tidak ada limit | J30: Tidak ada limit | K30: https://drive.google.com/open?id=1_iU8TfcTWtawo4DfXWqrofBtWftHGU1R | L30: Kabupaten | M30: Y400 | Q30: YOHANIS TIPNONI
A31: 45898.87 | C31: Febrianthy Elisabet Nau | D31: 082145568229 | E31: Spg | F31: 1.5 | G31: Tidak ada | H31: 0 | I31: Reject | J31: Tidak dapat limit | K31: https://drive.google.com/open?id=1mGlvXVrtof0kjaMI-wLLPPPmFGUXhjjG | L31: Kupang Kota | M31: Y400 | Q31: FEBRIANTHY ELISABET NA'U
A32: 45898.872 | C32: Aldy pratama johanis lada | D32: 0822-3682-3894 | E32: WO | F32: 2.500.000 | G32: Tidak ada | H32: 0 | I32: Reject | J32: Tidak dapat limit | K32: https://drive.google.com/open?id=1BLCTQ1WZqB_lfm5MzW3Webbdxq1DLpiM | L32: Kupang Kota | M32: Y400 | Q32: FEBRIANTHY ELISABET NA'U
A33: 45899.528 | C33: Hendriani dethan | D33: 081993939068 | E33: Pegawai Negeri Sipil (PNS) | F33: 4000000 | G33: Ada | H33: 5000000 | I33: ACC | K33: https://drive.google.com/open?id=1ICVUf6i_l2qKBjqN9oTwRJrBur9pv_LH, https://drive.google.com/open?id=1-YAnP6KvVlEgZaxLAv-jfl02i31jCkLh | L33: Kupang | M33: Y400 series | N33: TUTOR ANDRI RUDOLOF ELI MANAFE | O33: TUTOR KUSMYATI KILIMANDU | P33: KESIA NATALIA I. BENU | Q33: MARNITHA JUWIKE TIMORATI RUNESI
A34: 45899.572 | C34: Dortia Ndoen | D34: 81284633899 | E34: Pegawai Swasta | F34: 3000000 | G34: Tidak ada | I34: No Limit | J34: Tidak ada limit | K34: https://drive.google.com/open?id=1yahZ4lUxomfSdnZWX2rRVxQ5bcrk4Nf3 | L34: Kupang | N34: TUTOR ANDRI RUDOLOF ELI MANAFE | R34: YOHANA NOVIANA MARIANA GAA
A35: 45899.619 | C35: Silfa Koa | D35: 082178863126 | E35: Pengusaha | F35: 2000000 | G35: Tidak ada | H35: 5000000 | I35: ACC | K35: https://drive.google.com/open?id=1xUVs50VlYdxW5lHJ-y539dikFZzvQ5Tq | L35: Kupang | M35: Y400 series | N35: TUTOR HERY YULIUS DILLAK | W35: MERDA PUTRI BUNGSU KENAT
A36: 45899.775 | C36: Bernadeta Ceunfin | D36: 085333096207 | E36: Wiraswasta | F36: 5000000 | G36: Tidak ada | H36: 7000000 | I36: ACC | K36: https://drive.google.com/open?id=18_Cmkd-ObaypTDAsME5KtYNzxXCn7v8a | L36: Kupang | M36: Y400 series | N36: TUTOR ANTONIO DE JANAIRO TOMASOEY | Q36: EMPI FRANGKI LIEM | S36: EMPI FRANGKI LIEM
A37: 45899.787 | C37: Yunita Elik | D37: 087744028620 | E37: Wiraswasta warung makan | F37: 4700000 | G37: Tidak ada | I37: No Limit | J37: No limit | K37: https://drive.google.com/open?id=1mSKe-BM6uoBOCyt1s-MldJnTbe4uvuso | L37: Kupang | N37: TUTOR ANTONIO DE JANAIRO TOMASOEY | Q37: YOHANIS TIPNONI | S37: YOHANIS TIPNONI
A38: 45899.812 | C38: Sendi M Halla | D38: 082266057704 | E38: Buruh | F38: 2000000 | G38: Tidak ada | I38: Belum disetujui | J38: Reject | K38: https://drive.google.com/open?id=1oxA0-wl-sGAvu8UV-IVLQmkUQzSb2kMi | L38: Kupang | N38: TUTOR ANTONIO DE JANAIRO TOMASOEY | Q38: NOVANTRY RUTHANIA NAFFIE | S38: NOVANTRY RUTHANIA NAFFIE
A39: 45899.826 | C39: 𝘚𝘦𝘯𝘥𝘪 𝘮𝘢𝘳𝘪𝘢𝘯𝘢 𝘩𝘢𝘭𝘭𝘢 | D39: 082266057704 | E39: Buruh | F39: 3000000 | G39: Tidak ada | I39: Belum disetujui | J39: Belum disetujui tidak dapat limite | K39: https://drive.google.com/open?id=1_CG7QP1-jHtth3yizcWkzi3TfUPbcU0u | L39: Kupang | N39: TUTOR ANTONIO DE JANAIRO TOMASOEY | Q39: NOVANTRY RUTHANIA NAFFIE | S39: NOVANTRY RUTHANIA NAFFIE
A40: 45899.828 | C40: RENIJUFTARI LOBO HUKI | D40: 081338255675 | E40: Pegawai Swasta | F40: 4500000 | G40: Tidak ada | H40: 19459000 | I40: ACC | K40: https://drive.google.com/open?id=1uTn6ojdkFMr4okLy-sFSZyuX5qGMG2m4, https://drive.google.com/open?id=1UZ5Q3xQnejGgBBSxoUyRZJ0yZ-BCNpAJ | L40: Kupang | M40: Y400 series | N40: TUTOR ANTONIO DE JANAIRO TOMASOEY | Q40: FERI ELI KURNIAWAN | S40: FERI ELI KURNIAWAN
A41: 45899.901 | C41: Fafa la anie | D41: 081325501451 | E41: Mengurus Rumah Tangga (IRT) | F41: 4200000 | G41: Tidak ada | I41: No Limit | J41: tidak ada | K41: https://drive.google.com/open?id=1yC-9TF9rO14ViAzhAzeWe_w69ew5xsza | L41: Kupang | N41: TUTOR ANDRI RUDOLOF ELI MANAFE | Q41: YASINTHA MBU | R41: YASINTHA MBU
A42: 45900.543 | C42: Romana Pati | D42: 087852181534 | E42: Pegawai Swasta | F42: 3500000 | G42: Tidak ada | I42: Belum disetujui | J42: Pengajuan Kadaluarsa | K42: https://drive.google.com/open?id=1PsolOTzw7FY5U5wbKcu8w07G7SALiqlY | L42: Kupang | N42: TUTOR ANDRI RUDOLOF ELI MANAFE | Q42: PATRIANI MENGI ULY | R42: PATRIANI MENGI ULY
A43: 45900.842 | C43: Farens stingki betti | D43: 081237247814 | E43: Usaha pom mini | F43: 6500000 | G43: Tidak ada | I43: Belum disetujui | J43: Tidak dpt limit | K43: https://drive.google.com/open?id=1oBDBgN_yHiMd4lCVqyhHk-V9s1h26AzA | L43: Kupang | N43: TUTOR ANDRI RUDOLOF ELI MANAFE | Q43: AINI RAHMATINI NATALIA MOESTAKIM | R43: AINI RAHMATINI NATALIA MOESTAKIM
A44: 45901.539 | B44: 45901 | C44: Desianti Margareta Klay | D44: 082127512388 | E44: Buruh | F44: 1500000 | G44: Tidak ada | I44: Belum disetujui | J44: Belum di setujui | K44: https://drive.google.com/open?id=1zBQ50fno2ZQygNA4ftEeg6dUDOtDMSIe | L44: Sumba | O44: TUTOR KUSMYATI KILIMANDU | X44: YOVANDA KATRINA NAE
A45: 45901.544 | B45: 45901 | C45: ESTER LOURU AWANG | D45: 081237260801 | E45: Pegawai Negeri Sipil (PNS) | F45: 3000000 | G45: Tidak ada | H45: 5000000 | I45: ACC | K45: https://drive.google.com/open?id=13P35i9YaK4xw1sFWWHYzxUWw6z7_aY6D | L45: Sumba | M45: Y400 series | O45: SPV ANFAL JUPRIADI AMBU WARU | P45: ASTUTI BELA WAWO
A46: 45901.557 | B46: 45901 | C46: JONIUS LELU NGONGO | D46: 082119966214 | E46: Belum/Tidak Bekerja | F46: 2000000 | G46: Tidak ada | I46: Belum disetujui | J46: Di tolak | K46: https://drive.google.com/open?id=18DzeRaYrxi4WAd-P3JAHrwk_bb_vchry | L46: Sumba | O46: SPV ANFAL JUPRIADI AMBU WARU | P46: ASTUTI BELA WAWO
A47: 45901.559 | B47: 45901 | C47: DORKAS YANA BILI | D47: 085141296784 | E47: Pegawai Swasta | F47: 2800000 | G47: Tidak ada | I47: Belum disetujui | J47: Di Tolak | K47: https://drive.google.com/open?id=1lw45SClcDOcwxB6zsVqGP0rb-WOGi7Ad | L47: Sumba | O47: SPV ANFAL JUPRIADI AMBU WARU | P47: ASTUTI BELA WAWO
A48: 45901.607 | B48: 45901 | C48: Tustinus leti dama | D48: 085339449340 | E48: Pegawai Swasta | F48: 7000000 | G48: Tidak ada | I48: Belum disetujui | J48: Kendala Teknis Aplikasi | K48: https://drive.google.com/open?id=1oZAHP2p1SBMdB523aHJ9yfrvk1BpExrH | L48: Sumba | O48: SPV ANFAL JUPRIADI AMBU WARU | P48: SULIS NURAINI INSYATUN
A49: 45901.608 | B49: 45901 | C49: YANIA NDUN | D49: 085738294557 | E49: Pengusaha Kios | F49: 500000 | G49: Tidak ada | I49: Belum disetujui | J49: DP Yang Disediakan Pemohon Tidak Cukup | K49: https://drive.google.com/open?id=1wzVGa2PDZabA80TkAqckF0jcBBOxd9U4 | L49: Kupang | N49: TUTOR ANDRI RUDOLOF ELI MANAFE | R49: DEMARISTI S H FENI
A50: 45901.609 | B50: 45901 | C50: SAMSUDIN MADJID | D50: 081237162528 | E50: WIRASWASTA | F50: 6200000 | G50: Tidak ada | I50: Belum disetujui | J50: tidak ada | K50: https://drive.google.com/open?id=1wXJBTKRhKjpsUCM7Bz-TNZDSYDST9q47 | L50: Kupang | N50: TUTOR ANDRI RUDOLOF ELI MANAFE | R50: YASINTHA MBU
A51: 45901.613 | B51: 45901 | C51: Yosefina malo | D51: 085336407960 | E51: Petani | F51: 10000000 | G51: Tidak ada | H51: 3000000 | I51: ACC | K51: https://drive.google.com/open?id=15KtriLd8QGaFPBURrrxgU_tD565Wf2ea | L51: Sumba | M51: Y400 series | O51: SPV ANFAL JUPRIADI AMBU WARU | P51: IDMAL YUSDIRAN YUSUF
A52: 45901.654 | B52: 45901 | C52: Gideon fanggidae | D52: 082123541125 | E52: Pelajar/Mahasiswa | F52: 3000000 | G52: Tidak ada | I52: Belum disetujui | J52: Blm di setujui | K52: https://drive.google.com/open?id=1-eTvepTXdoi13Mj3kdf5RpjUpSOXcetj | L52: Kupang | N52: TUTOR ANDRI RUDOLOF ELI MANAFE | R52: MARNITHA JUWIKE TIMORATI RUNESI
A53: 45901.666 | B53: 45901 | C53: Matius loba dowa | D53: 081239561099 | E53: Petani | F53: 10000000 | G53: Tidak ada | I53: Belum disetujui | J53: KTP Rusak | K53: https://drive.google.com/open?id=1ygGYW7yqPetPrwL08mqLKM7N1DzjTWRp | L53: Sumba | O53: SPV ANFAL JUPRIADI AMBU WARU | P53: IDMAL YUSDIRAN YUSUF
A54: 45901.668 | B54: 45901 | C54: Minto umbu ledi deta | D54: 082144317324 | E54: Buruh | F54: 4500000 | G54: Tidak ada | I54: Belum disetujui | J54: Belum disetujui | K54: https://drive.google.com/open?id=1UWi4ZBYcuMMDno0-1j02NBYc0rsT3HlW | L54: Kupang | N54: TUTOR ANTONIO DE JANAIRO TOMASOEY | S54: NOVANTRY RUTHANIA NAFFIE
A55: 45901.685 | B55: 45901 | C55: Margaretha m geli | D55: 085237859297 | E55: Pegawai Swasta | F55: 7000000 | G55: Tidak ada | H55: 3000000 | I55: ACC | K55: https://drive.google.com/open?id=1eOiudCRpc1QHJu9-qOpfNpNXifMglSZu | L55: Sumba | M55: Y400 series | O55: SPV ANFAL JUPRIADI AMBU WARU | P55: SULIS NURAINI INSYATUN
A56: 45901.72 | B56: 45901 | C56: Alfalani | D56: 081246715616 | E56: Wiraswasta | F56: 15000000 | G56: Tidak ada | I56: Belum disetujui | J56: Di tolak | K56: https://drive.google.com/open?id=13mLocfZpZY75Lsdn6-ahLd9Zgt-2LUFT | L56: Sumba | O56: SPV ANFAL JUPRIADI AMBU WARU | P56: SULIS NURAINI INSYATUN
A57: 45901.771 | B57: 45901 | C57: LIWU JADJA | D57: 082341484860 | E57: Ojek online (Grab) | F57: 3000000 | G57: Tidak ada | I57: Belum disetujui | J57: Pengajuan Kadaluarsa | K57: https://drive.google.com/open?id=1ra7OxCXTNfFbD_FL2eaBiRQA0dWusMh8 | L57: Kupang | N57: TUTOR ANDRI RUDOLOF ELI MANAFE | R57: DEMARISTI S H FENI
A58: 45901.779 | B58: 45901 | C58: Lusia Astria sarah | D58: 081246385991 | E58: Jual ikan | F58: 3400000 | G58: Tidak ada | I58: Belum disetujui | J58: Reject | K58: https://drive.google.com/open?id=162C53O_7a_xaGE5RZKZ2Sje6yeovX09j | L58: Kupang | N58: TUTOR LEU ADOLF QICHEN LEI BAIT | T58: BERGITHA NIA OLIN
A59: 45901.788 | B59: 45901 | C59: Kornelia Y. Ati | D59: 085141206337 | E59: Honorer | F59: 4500000 | G59: Tidak ada | I59: Belum disetujui | J59: Reject | K59: https://drive.google.com/open?id=1-MFctavGl3a_8BNPhhXHrf5t7qjYQUdh | L59: Kupang | N59: TUTOR LEU ADOLF QICHEN LEI BAIT | T59: BERGITHA NIA OLIN
A60: 45901.79 | B60: 45901 | C60: Yogia Riki Rinardi Yudo Nenoliu | D60: 081225127660 | E60: Pegawai Swasta | F60: 3500000 | G60: Tidak ada | H60: 3000000 | I60: ACC | K60: https://drive.google.com/open?id=1NfzlYFNWcMYESRE4vT7l9qwcKshD57Ng | L60: Kupang | M60: Y400 series | N60: TUTOR ANTONIO DE JANAIRO TOMASOEY | S60: YOHANIS TIPNONI
A61: 45901.792 | B61: 45901 | C61: Natalia usfinit | D61: 081453518480 | E61: Honorer | F61: 3500000 | G61: Tidak ada | I61: Belum disetujui | J61: Reject | K61: https://drive.google.com/open?id=17FB7uir3OMLSbAOx-1RqBxCEdjKViNdz | L61: Kupang | N61: TUTOR LEU ADOLF QICHEN LEI BAIT | T61: BERGITHA NIA OLIN
A62: 45901.795 | B62: 45901 | C62: Imelda f. Kollo | D62: 085191440353 | E62: Wiraswasta | F62: 5500000 | G62: Tidak ada | I62: Belum disetujui | J62: Tidak disetujui | K62: https://drive.google.com/open?id=1L3UN9LbXCqDVsqz1D9ZfyF-Rjay3H1Bb | L62: Kupang | N62: TUTOR LEU ADOLF QICHEN LEI BAIT | T62: ADRIANA
A63: 45901.802 | B63: 45901 | C63: Sepriyanus dethan | D63: 081339294087 | E63: Pegawai Swasta | F63: 5500000 | G63: Tidak ada | I63: Belum disetujui | J63: Belum disetujui | K63: https://drive.google.com/open?id=1bUxkYu_Z7vu_pCXEDQxooz4h0dN-tCH7 | L63: Kupang | N63: TUTOR ANTONIO DE JANAIRO TOMASOEY | S63: NOVANTRY RUTHANIA NAFFIE
A64: 45901.803 | B64: 45901 | C64: PAULINA DJARI | D64: 081339787162 | E64: Pegawai BUMN | F64: 8000000 | G64: Tidak ada | H64: 500000 | I64: ACC | K64: https://drive.google.com/open?id=1EVymcxCTGSYHCT0EFxP8nW1Y4vNP7PAh | L64: Sumba | M64: Y400 series | O64: SPV ANFAL JUPRIADI AMBU WARU | P64: ASTUTI BELA WAWO
A65: 45901.81 | B65: 45901 | C65: RESTIANI YAPU LETE | D65: 081239102165 | E65: Pelajar/Mahasiswa | F65: 200000 | G65: Tidak ada | I65: Belum disetujui | J65: DI TOLAK | K65: https://drive.google.com/open?id=1F4-YsnrXV6xiPz9Z81ZF9XwWgJfB_fgG | L65: Sumba | O65: SPV ANFAL JUPRIADI AMBU WARU | P65: ASTUTI BELA WAWO
A66: 45901.812 | B66: 45901 | C66: YULIUS YAPU LETE | D66: 081338132873 | E66: Pegawai Swasta | F66: 3000000 | G66: Tidak ada | I66: Belum disetujui | J66: Di tolak | K66: https://drive.google.com/open?id=1qnz-y1vl8uxK2siZCbOi8foauqHSPuwK | L66: Sumba | O66: SPV ANFAL JUPRIADI AMBU WARU | P66: ASTUTI BELA WAWO
A67: 45901.814 | B67: 45901 | C67: YOHANA NONA INA | D67: 085124145525 | E67: Pegawai Swasta | F67: 3500000 | G67: Tidak ada | I67: Belum disetujui | J67: Di tolak | K67: https://drive.google.com/open?id=1Bh13kfDhFcIwKYUa_VeeaP-MLLLEhUyN | L67: Sumba | O67: SPV ANFAL JUPRIADI AMBU WARU | P67: ASTUTI BELA WAWO
A68: 45901.82 | B68: 45901 | C68: Bernadeta ceunfin | D68: 085333096207 | E68: Wiraswasta | F68: 5000000 | G68: Tidak ada | H68: 7000000 | I68: ACC | K68: https://drive.google.com/open?id=1oLlErTA4NNVAGXTM79YI8_81ZrZ-_K3T | L68: Kupang | M68: Y400 series | N68: TUTOR ANTONIO DE JANAIRO TOMASOEY | S68: EMPI FRANGKI LIEM
A69: 45901.822 | B69: 45901 | C69: Lucia fitry Tety | D69: 085167113826 | E69: Honorer | F69: 3500000 | G69: Tidak ada | I69: Belum disetujui | J69: Reject | K69: https://drive.google.com/open?id=1l_HaHZIawcigOKcsYfciqbMwvn3Gkker | L69: Kupang | N69: TUTOR LEU ADOLF QICHEN LEI BAIT | T69: BERGITHA NIA OLIN
A70: 45901.828 | B70: 45901 | C70: YELKI ALFIAN SINLAE | D70: +6285210178289 | E70: Wiraswasta | F70: 3500000 | G70: Tidak ada | I70: Belum disetujui | J70: Tidak disetujui | K70: https://drive.google.com/open?id=1KS772r-lD4DaHX-1GA8EuTTReAGftRUr | L70: Kupang | N70: TUTOR HERY YULIUS DILLAK | W70: LINDA MELSIANA ELLO
A71: 45901.835 | B71: 45901 | C71: Nomensen langga | D71: 082146267482 | E71: Pelajar/Mahasiswa | F71: 1000000 | G71: Tidak ada | I71: Belum disetujui | J71: Rijek | K71: https://drive.google.com/open?id=1L_zUL_tXEt-_R0miUCWj-I2I-glnOLjZ | L71: Kupang | N71: TUTOR ANDRI RUDOLOF ELI MANAFE | R71: ROS YANE KANA LUDJI
A72: 45901.839 | B72: 45901 | C72: Risma rustam | D72: 082155284399 | E72: wirausaha | F72: 3000000 | G72: Tidak ada | I72: Belum disetujui | J72: Rijek | K72: https://drive.google.com/open?id=1ZGyTSW9DP9j2kiB0zKCR8jmpNBnwly_u | L72: Kupang | N72: TUTOR ANDRI RUDOLOF ELI MANAFE | R72: ROS YANE KANA LUDJI
A73: 45901.842 | B73: 45901 | C73: Taufiq Amiruddin kay | D73: 082144813684 | E73: Pegawai Swasta | F73: 3200000 | G73: Tidak ada | I73: Belum disetujui | J73: Pengajuan Kadaluarsa | K73: https://drive.google.com/open?id=1p91nCh0aGQIEqg2w4CtK7eH8qnBVwaS1 | L73: Kupang | N73: TUTOR ANDRI RUDOLOF ELI MANAFE | R73: FEBRIANTHY ELISABET NA'U
A74: 45901.844 | B74: 45901 | C74: Merlin benu | D74: 082123220735 | E74: Mengurus Rumah Tangga (IRT) | F74: 2000000 | G74: Tidak ada | I74: Belum disetujui | J74: Pengajuan Kadaluarsa | K74: https://drive.google.com/open?id=1ASLhdoEhfUenRwPnk-D2J1a3GN3M-VXI | L74: Kupang | N74: TUTOR ANDRI RUDOLOF ELI MANAFE | R74: SELVINCE BAKO
A75: 45901.845 | B75: 45901 | C75: Dorlin Dorkas tiran | D75: 082359468848 | E75: Belum/Tidak Bekerja | F75: 2300000 | G75: Tidak ada | I75: Belum disetujui | J75: KTP Rusak | K75: https://drive.google.com/open?id=11fIR2qXzTVlcF_wPJ0lxmKQM51ZLq6nk | L75: Kupang | N75: TUTOR ANDRI RUDOLOF ELI MANAFE | R75: FEBRIANTHY ELISABET NA'U
A76: 45901.849 | B76: 45901 | C76: Adriani missa | D76: 082144551525 | E76: Pegawai toko | F76: 4500000 | G76: Tidak ada | I76: Belum disetujui | J76: Pengajuan ditolak | K76: https://drive.google.com/open?id=1UdnCbdbD_JV5lTUGf_XtQnrRRfWKLIxW | L76: Kupang | N76: TUTOR ANDRI RUDOLOF ELI MANAFE | R76: AINI RAHMATINI NATALIA MOESTAKIM
A77: 45901.85 | B77: 45901 | C77: Vinsensia Gregoria Thein | D77: 082151112179 | E77: Satuan Pelayanan Pemenuhan Gizi | F77: 6000000 | G77: Tidak ada | H77: 5000000 | I77: ACC | K77: https://drive.google.com/open?id=1ss8U9JszMK5gF3oPAJFi6U-piR2qR1nY | L77: Kupang | M77: V50 Lite series | N77: TUTOR LEU ADOLF QICHEN LEI BAIT | T77: NUR FATIMAH MOLBANG
A78: 45901.854 | B78: 45901 | C78: ordiana oekolo | D78: 081237827332 | E78: Buruh | F78: 3000000 | G78: Tidak ada | I78: Belum disetujui | J78: belum disetujui | K78: https://drive.google.com/open?id=1jlJDDNSgw06AhE9X6IYwFBgj2E7JLltj | L78: Kupang | N78: TUTOR HERY YULIUS DILLAK | W78: ALDIANA WELIA PANIE
A79: 45901.967 | B79: 45901 | C79: YAPSI E.BANO | D79: 081239435292 | E79: honorer | F79: 5700000 | G79: Ada | H79: 3000000 | I79: ACC | K79: https://drive.google.com/open?id=1N0Tqd_rZcNfDuVu93a0WzDZJSJLT2Qnn | L79: Kupang | M79: Y400 series | N79: TUTOR ANDRI RUDOLOF ELI MANAFE | R79: PATRIANI MENGI ULY
A80: 45902.432 | B80: 45902 | C80: Norma norlince abi | D80: 082144317162 | E80: Usaha gorengan | F80: 5600000 | G80: Tidak ada | I80: Belum disetujui | J80: Pengajuab ditolak | K80: https://drive.google.com/open?id=1-XJgfxdI9YIfxqDn3ntoIfEoytMRMatL | L80: Kupang | N80: TUTOR ANDRI RUDOLOF ELI MANAFE | R80: AINI RAHMATINI NATALIA MOESTAKIM
A81: 45902.438 | B81: 45902 | C81: Nikodemus suat | D81: 081337446893 | E81: Wiraswasta | F81: 5000000 | G81: Tidak ada | I81: Belum disetujui | J81: Masi ad pinjaman di luar | K81: https://drive.google.com/open?id=1KBj3fOHOuJEDvZrxPVFq_wQ1UNQ95ez2 | L81: Kupang | N81: TUTOR ANTONIO DE JANAIRO TOMASOEY | S81: EMPI FRANGKI LIEM
A82: 45902.461 | B82: 45902 | C82: LAMADI ABDUMANAN ISHAK | D82: 082147437505 | E82: Belum/Tidak Bekerja | F82: 4600000 | G82: Tidak ada | I82: Belum disetujui | J82: tidak | K82: https://drive.google.com/open?id=1asF4hqy-KFJslAevauzfbZv4_sLqokC- | L82: Kupang | N82: TUTOR ANDRI RUDOLOF ELI MANAFE | R82: YASINTHA MBU
A83: 45902.463 | B83: 45902 | C83: NIMROT NABUNOME | D83: 087726253707 | E83: Wirausaha | F83: 2000000 | G83: Tidak ada | I83: Belum disetujui | J83: Pengajuan Kadaluarsa | K83: https://drive.google.com/open?id=1ku725gkc5d7-_qVo2Ej6AK9sVd4kENB0 | L83: Kupang | N83: TUTOR ANDRI RUDOLOF ELI MANAFE | R83: ROS YANE KANA LUDJI
A84: 45902.485 | B84: 45902 | C84: YUNITA TEWU GOA | D84: 081338736459 | E84: Pelajar/Mahasiswa | F84: 4600000 | G84: Tidak ada | H84: 7000000 | I84: Dapat limit tapi belum diproses | K84: https://drive.google.com/open?id=1GCErL40wwD2wBq2xYi1Tl6_ALMnch1Dc | L84: Kupang | M84: Y400 series | N84: TUTOR ANDRI RUDOLOF ELI MANAFE | R84: YASINTHA MBU
A85: 45902.518 | B85: 45902 | C85: Maria agustina boy | D85: 082247893789 | E85: Petani/pekebun | F85: 6100000 | G85: Tidak ada | I85: Belum disetujui | J85: Tdk disetujui | K85: https://drive.google.com/open?id=1w4fcTbzku10ZJFkQ_dFR_yPrye-FT-aq | L85: Kupang | N85: TUTOR LEU ADOLF QICHEN LEI BAIT | T85: ADRIANA
A86: 45902.521 | B86: 45902 | C86: Argi lete | D86: 081236377499 | E86: Pelajar/Mahasiswa | F86: 3200000 | G86: Tidak ada | I86: Belum disetujui | J86: Tidak dapat limitee | K86: https://drive.google.com/open?id=1v8V097GK1lvro6knoBSnRQvytjjvMBiZ | L86: Kupang | N86: TUTOR ANDRI RUDOLOF ELI MANAFE | R86: WARDIA
A87: 45902.523 | B87: 45902 | C87: Hadat alwi | D87: 082340673115 | E87: Pelajar/Mahasiswa | F87: 1200000 | G87: Tidak ada | I87: Belum disetujui | J87: Tidak dapat limited | K87: https://drive.google.com/open?id=1569qcb89-3Q1N4aYRV7ooRbDVZWDSXPs | L87: Kupang | N87: TUTOR ANDRI RUDOLOF ELI MANAFE | R87: WARDIA
A88: 45902.545 | B88: 45902 | C88: EMMI YANTI LEDOH | D88: 082211482042 | E88: Belum/Tidak Bekerja | F88: 2500 | G88: Tidak ada | I88: Belum disetujui | J88: Kons pernah kredit dan tidak lanjut bayar | K88: https://drive.google.com/open?id=14IF78IjhDn-QdQIkvFL1r6K7RvNjvdMa | L88: Kupang | N88: TUTOR ANDRI RUDOLOF ELI MANAFE | R88: FEBRIANTHY ELISABET NA'U
A89: 45902.556 | B89: 45902 | C89: DIANA LISBETH EXWILA SINA | D89: 081237762213 | E89: Pegawai Swasta | F89: 3000000 | G89: Ada | H89: 5000000 | I89: Dapat limit tapi belum diproses | K89: https://drive.google.com/open?id=1xmqZvDQaWbKliqlANZRFMVusABVOdKrR | L89: Kupang | M89: Y29 series | N89: TUTOR HERY YULIUS DILLAK | W89: MERDA PUTRI BUNGSU KENAT
A90: 45902.558 | B90: 45902 | C90: Melinda emiliana Ndada | D90: 082341220345 | E90: Mengurus Rumah Tangga (IRT) | F90: 100 | G90: Tidak ada | I90: Belum disetujui | J90: Kendala Teknis Aplikasi | K90: https://drive.google.com/open?id=1EpTVZ_w2ZGpbGf90k5GDuOw5wcYsQ1Ji | L90: Kupang | N90: TUTOR HERY YULIUS DILLAK | W90: MERDA PUTRI BUNGSU KENAT
A91: 45902.562 | B91: 45902 | C91: Wilfrido | D91: 081338464906 | E91: Karyawan toko | F91: 4000 | G91: Tidak ada | I91: Belum disetujui | J91: Pengajuan Kadaluarsa | K91: https://drive.google.com/open?id=17XOymdB1wkqPXtkiOgjuqLgCEWky-RTj | L91: Kupang | N91: TUTOR ANDRI RUDOLOF ELI MANAFE | R91: SELVINCE BAKO
A92: 45902.571 | B92: 45902 | C92: Hendrikus Tanik | D92: 082340321780 | E92: Jual ikan | F92: 4200000 | G92: Tidak ada | I92: Belum disetujui | J92: Reject | K92: https://drive.google.com/open?id=1lGumMsUgwXn4uMOzBqIV1CQVxJlZz43C | L92: Kupang | N92: TUTOR LEU ADOLF QICHEN LEI BAIT | T92: BERGITHA NIA OLIN
A93: 45902.573 | B93: 45902 | C93: Imelda erlyn non | D93: 085183907327 | E93: Jual AYAM SUPER | F93: 3400000 | G93: Tidak ada | I93: Belum disetujui | J93: Reject | K93: https://drive.google.com/open?id=1TJBvduiUsx50Fz1P77qAoR3nwspaU5bD | L93: Kupang | N93: TUTOR LEU ADOLF QICHEN LEI BAIT | T93: BERGITHA NIA OLIN
A94: 45902.586 | B94: 45902 | C94: ARIESTA IRAWATU MULLA | D94: 885338534966 | E94: Pegawai Swasta | F94: 2500000 | G94: Tidak ada | I94: Belum disetujui | J94: Tidak dapat limit | K94: https://drive.google.com/open?id=1HohfOEx4yrOJdiOWFph-iNsPJyxuPyRE | L94: Sumba | O94: TUTOR KUSMYATI KILIMANDU | X94: ASRI NINGSI RAMBU ATA ENDI
A95: 45902.589 | B95: 45902 | C95: MARLENI RAMBU ANANGGIYA | D95: 82213300765 | E95: Pegawai Swasta | F95: 3000000 | G95: Ada | I95: Belum disetujui | J95: Tidak dapat limit | K95: https://drive.google.com/open?id=1DSdtV4S6d41vc8A5l4JI6Go6vtl3jxGx | L95: Sumba | O95: TUTOR KUSMYATI KILIMANDU | X95: ASRI NINGSI RAMBU ATA ENDI
A96: 45902.612 | B96: 45902 | C96: Sardinti E Tuthaes | D96: 81236270475 | E96: Wiraswasta | F96: 5000000 | G96: Tidak ada | H96: 7000000 | I96: Dapat limit tapi belum diproses | K96: https://drive.google.com/open?id=1lrTgHRKUUaoUOSDMk4FAFgxeE4klel_J | L96: Kupang | M96: Y400 series | N96: TUTOR ANTONIO DE JANAIRO TOMASOEY | S96: FERI ELI KURNIAWAN
A97: 45902.644 | B97: 45902 | C97: Adelina lite | D97: 082236823498 | E97: Pegawai Swasta | F97: 2000000 | G97: Tidak ada | I97: Belum disetujui | J97: Tidak ada pinjaman | K97: https://drive.google.com/open?id=17uCVWZ0upssKhl0-RJCyeNzuujXgTY8W | L97: Kupang | N97: TUTOR ANTONIO DE JANAIRO TOMASOEY | S97: EMPI FRANGKI LIEM
A98: 45902.663 | B98: 45902 | C98: Yuliana Ikun | D98: 081238448413 | E98: Usaha kain tenun | F98: 8000000 | G98: Tidak ada | I98: Belum disetujui | J98: Belum dapat limit | K98: https://drive.google.com/open?id=19hNdZKwVczKSRbF2avLH7f2TQ6E5XRVK | L98: Kupang | N98: TUTOR ANTONIO DE JANAIRO TOMASOEY | S98: WINDRI MANOE
A99: 45902.666 | B99: 45902 | C99: Ardy surya putra manu | D99: 082144378128 | E99: Pegawai Swasta | F99: 7000000 | G99: Tidak ada | I99: Belum disetujui | J99: Sudah pernah daftar di kredivo | K99: https://drive.google.com/open?id=1dVSbI99-nCI31VYleeNMYh3J8GDxS039 | L99: Kupang | N99: TUTOR ANDRI RUDOLOF ELI MANAFE | R99: IRENE NOVALIA KADJU
A100: 45902.669 | B100: 45902 | C100: Dolorosa maria malo | D100: 085339493049 | E100: Petani | F100: 10000000 | G100: Tidak ada | H100: 3000000 | I100: Dapat limit tapi belum diproses | K100: https://drive.google.com/open?id=1eE53y9P-NrU2X_0_vLbPM0EHqUV2_UyX | L100: Sumba | M100: Y400 series | O100: SPV ANFAL JUPRIADI AMBU WARU | P100: SULIS NURAINI INSYATUN
...

Sheet Sheet21
A1: TANGGAL | B1: NAMA_PROMOTOR | C1: STATUS_PENGAJUAN | D1: TIPE_HP | E1: ID _TOKO | F1: SATOR | G1: TOKO | H1: AREA
A2: =IFERROR(__xludf.DUMMYFUNCTION("SORT({ QUERY('Master Data All'!A2:X37256, ""select A, P, I, M where P is not null"", 0); QUERY('Master Data All'!A2:X37256, ""select A, Q, I, M where Q is not null"", 0); QUERY('Master Data All'!A2:X37256, ""select A, R, I, M where R is not null"", 0);"&" QUERY('Master Data All'!A2:X37256, ""select A, S, I, M where S is not null"", 0); QUERY('Master Data All'!A2:X37256, ""select A, T, I, M where T is not null"", 0); QUERY('Master Data All'!A2:X37256, ""select A, U, I, M where U is not null"", 0); QUER"&"Y('Master Data All'!A2:X37256, ""select A, V, I, M where V is not null"", 0); QUERY('Master Data All'!A2:X37256, ""select A, W, I, M where W is not null"", 0); QUERY('Master Data All'!A2:X37256, ""select A, X, I, M where X is not null"", 0) }, 1, TRUE) "),45897.58597868056) -> 45897.586 | B2: =IFERROR(__xludf.DUMMYFUNCTION("""COMPUTED_VALUE"""),"DEMARISTI S H FENI") -> DEMARISTI S H FENI | C2: =IFERROR(__xludf.DUMMYFUNCTION("""COMPUTED_VALUE"""),"Reject") -> Reject | E2: {=IF(B2:B37256="", "", IFERROR(VLOOKUP(TRIM(B2:B37256), 'Database Promotor'!B:E, 4, FALSE), ""))} | F2: {=IF(B2:B37256="", "", IFERROR(VLOOKUP(TRIM(B2:B37256), 'Database Promotor'!B:E, 2, FALSE), ""))} | G2: {=IF(E2:E37256="", "", IFERROR(VLOOKUP(E2:E37256, 'Database Toko'!A:D, 2, FALSE), ""))} | H2: {=IF(E2:E37256="", "", IFERROR(VLOOKUP(E2:E37256, 'Database Toko'!A:D, 4, FALSE), ""))}
A3: =IFERROR(__xludf.DUMMYFUNCTION("""COMPUTED_VALUE"""),45897.59262289351) -> 45897.593 | B3: =IFERROR(__xludf.DUMMYFUNCTION("""COMPUTED_VALUE"""),"EMPI FRANGKI LIEM") -> EMPI FRANGKI LIEM | C3: =IFERROR(__xludf.DUMMYFUNCTION("""COMPUTED_VALUE"""),"Acc") -> Acc | D3: =IFERROR(__xludf.DUMMYFUNCTION("""COMPUTED_VALUE"""),"Y400") -> Y400 | E3: MCE001 | F3: TUTOR ANTONIO DE JANAIRO TOMASOEY | G3: MCELL | H3: KUPANG
A4: =IFERROR(__xludf.DUMMYFUNCTION("""COMPUTED_VALUE"""),45897.59448921296) -> 45897.594 | B4: =IFERROR(__xludf.DUMMYFUNCTION("""COMPUTED_VALUE"""),"EMPI FRANGKI LIEM") -> EMPI FRANGKI LIEM | C4: =IFERROR(__xludf.DUMMYFUNCTION("""COMPUTED_VALUE"""),"Reject") -> Reject | E4: MCE001 | F4: TUTOR ANTONIO DE JANAIRO TOMASOEY | G4: MCELL | H4: KUPANG
A5: =IFERROR(__xludf.DUMMYFUNCTION("""COMPUTED_VALUE"""),45897.60611929398) -> 45897.606 | B5: =IFERROR(__xludf.DUMMYFUNCTION("""COMPUTED_VALUE"""),"YOHANA NOVIANA MARIANA GAA") -> YOHANA NOVIANA MARIANA GAA | C5: =IFERROR(__xludf.DUMMYFUNCTION("""COMPUTED_VALUE"""),"Reject") -> Reject | E5: SPC007 | F5: TUTOR ANDRI RUDOLOF ELI MANAFE | G5: SPC PLATINUM | H5: KUPANG
A6: =IFERROR(__xludf.DUMMYFUNCTION("""COMPUTED_VALUE"""),45897.639471574075) -> 45897.639 | B6: =IFERROR(__xludf.DUMMYFUNCTION("""COMPUTED_VALUE"""),"PATRIANI MENGI ULY") -> PATRIANI MENGI ULY | C6: =IFERROR(__xludf.DUMMYFUNCTION("""COMPUTED_VALUE"""),"Reject") -> Reject | E6: SPC004 | F6: TUTOR ANDRI RUDOLOF ELI MANAFE | G6: SPC MASTER CELL | H6: KUPANG
A7: =IFERROR(__xludf.DUMMYFUNCTION("""COMPUTED_VALUE"""),45897.64885048611) -> 45897.649 | B7: =IFERROR(__xludf.DUMMYFUNCTION("""COMPUTED_VALUE"""),"NOVANTRY RUTHANIA NAFFIE") -> NOVANTRY RUTHANIA NAFFIE | C7: =IFERROR(__xludf.DUMMYFUNCTION("""COMPUTED_VALUE"""),"Reject") -> Reject | E7: MCE001 | F7: TUTOR ANTONIO DE JANAIRO TOMASOEY | G7: MCELL | H7: KUPANG
A8: =IFERROR(__xludf.DUMMYFUNCTION("""COMPUTED_VALUE"""),45897.65071901621) -> 45897.651 | B8: =IFERROR(__xludf.DUMMYFUNCTION("""COMPUTED_VALUE"""),"NOVANTRY RUTHANIA NAFFIE") -> NOVANTRY RUTHANIA NAFFIE | C8: =IFERROR(__xludf.DUMMYFUNCTION("""COMPUTED_VALUE"""),"Reject") -> Reject | E8: MCE001 | F8: TUTOR ANTONIO DE JANAIRO TOMASOEY | G8: MCELL | H8: KUPANG
A9: =IFERROR(__xludf.DUMMYFUNCTION("""COMPUTED_VALUE"""),45897.65229791666) -> 45897.652 | B9: =IFERROR(__xludf.DUMMYFUNCTION("""COMPUTED_VALUE"""),"YOHANA NOVIANA MARIANA GAA") -> YOHANA NOVIANA MARIANA GAA | C9: =IFERROR(__xludf.DUMMYFUNCTION("""COMPUTED_VALUE"""),"Reject") -> Reject | E9: SPC007 | F9: TUTOR ANDRI RUDOLOF ELI MANAFE | G9: SPC PLATINUM | H9: KUPANG
A10: =IFERROR(__xludf.DUMMYFUNCTION("""COMPUTED_VALUE"""),45897.69177612269) -> 45897.692 | B10: =IFERROR(__xludf.DUMMYFUNCTION("""COMPUTED_VALUE"""),"DEMARISTI S H FENI") -> DEMARISTI S H FENI | C10: =IFERROR(__xludf.DUMMYFUNCTION("""COMPUTED_VALUE"""),"Acc") -> Acc | D10: =IFERROR(__xludf.DUMMYFUNCTION("""COMPUTED_VALUE"""),"Y400") -> Y400
A11: =IFERROR(__xludf.DUMMYFUNCTION("""COMPUTED_VALUE"""),45897.75415983797) -> 45897.754 | B11: =IFERROR(__xludf.DUMMYFUNCTION("""COMPUTED_VALUE"""),"YOHANIS TIPNONI") -> YOHANIS TIPNONI | C11: =IFERROR(__xludf.DUMMYFUNCTION("""COMPUTED_VALUE"""),"Dapat Limit Cuma Dp kurang, masih pulang Bicara Sama Suami Soal Dp") -> Dapat Limit Cuma Dp kurang, masih pulang Bicara Sama Suami Soal Dp | E11: KIN001 | F11: TUTOR ANTONIO DE JANAIRO TOMASOEY | G11: KING CELL | H11: KUPANG
A12: =IFERROR(__xludf.DUMMYFUNCTION("""COMPUTED_VALUE"""),45897.77933287037) -> 45897.779 | B12: =IFERROR(__xludf.DUMMYFUNCTION("""COMPUTED_VALUE"""),"YASINTHA MBU") -> YASINTHA MBU | C12: =IFERROR(__xludf.DUMMYFUNCTION("""COMPUTED_VALUE"""),"Reject") -> Reject | E12: TER001 | F12: TUTOR ANTONIO DE JANAIRO TOMASOEY | G12: TERMINAL HP | H12: KUPANG
A13: =IFERROR(__xludf.DUMMYFUNCTION("""COMPUTED_VALUE"""),45897.77954232639) -> 45897.78 | B13: =IFERROR(__xludf.DUMMYFUNCTION("""COMPUTED_VALUE"""),"AINI RAHMATINI NATALIA MOESTAKIM") -> AINI RAHMATINI NATALIA MOESTAKIM | C13: =IFERROR(__xludf.DUMMYFUNCTION("""COMPUTED_VALUE"""),"Sistem masih bermasalah") -> Sistem masih bermasalah | E13: SPC006 | F13: TUTOR ANDRI RUDOLOF ELI MANAFE | G13: SPC OESAPA | H13: KUPANG
A14: =IFERROR(__xludf.DUMMYFUNCTION("""COMPUTED_VALUE"""),45897.78107916666) -> 45897.781 | B14: =IFERROR(__xludf.DUMMYFUNCTION("""COMPUTED_VALUE"""),"AINI RAHMATINI NATALIA MOESTAKIM") -> AINI RAHMATINI NATALIA MOESTAKIM | C14: =IFERROR(__xludf.DUMMYFUNCTION("""COMPUTED_VALUE"""),"Sistem bermasalah") -> Sistem bermasalah | E14: SPC006 | F14: TUTOR ANDRI RUDOLOF ELI MANAFE | G14: SPC OESAPA | H14: KUPANG
A15: =IFERROR(__xludf.DUMMYFUNCTION("""COMPUTED_VALUE"""),45897.80027759259) -> 45897.8 | B15: =IFERROR(__xludf.DUMMYFUNCTION("""COMPUTED_VALUE"""),"Tes") -> Tes | C15: =IFERROR(__xludf.DUMMYFUNCTION("""COMPUTED_VALUE"""),"Reject") -> Reject
A16: =IFERROR(__xludf.DUMMYFUNCTION("""COMPUTED_VALUE"""),45897.80897542824) -> 45897.809 | B16: =IFERROR(__xludf.DUMMYFUNCTION("""COMPUTED_VALUE"""),"Tes") -> Tes | C16: =IFERROR(__xludf.DUMMYFUNCTION("""COMPUTED_VALUE"""),"Reject") -> Reject
A17: =IFERROR(__xludf.DUMMYFUNCTION("""COMPUTED_VALUE"""),45897.835055891206) -> 45897.835 | B17: =IFERROR(__xludf.DUMMYFUNCTION("""COMPUTED_VALUE"""),"AINI RAHMATINI NATALIA MOESTAKIM") -> AINI RAHMATINI NATALIA MOESTAKIM | C17: =IFERROR(__xludf.DUMMYFUNCTION("""COMPUTED_VALUE"""),"Sistem eror") -> Sistem eror | E17: SPC006 | F17: TUTOR ANDRI RUDOLOF ELI MANAFE | G17: SPC OESAPA | H17: KUPANG
A18: =IFERROR(__xludf.DUMMYFUNCTION("""COMPUTED_VALUE"""),45897.83743508102) -> 45897.837 | B18: =IFERROR(__xludf.DUMMYFUNCTION("""COMPUTED_VALUE"""),"FERI ELI KURNIAWAN") -> FERI ELI KURNIAWAN | C18: =IFERROR(__xludf.DUMMYFUNCTION("""COMPUTED_VALUE"""),"Reject") -> Reject | E18: PLA001 | F18: TUTOR ANTONIO DE JANAIRO TOMASOEY | G18: PLANET GADGET | H18: KUPANG
A19: =IFERROR(__xludf.DUMMYFUNCTION("""COMPUTED_VALUE"""),45898.3801822338) -> 45898.38 | B19: =IFERROR(__xludf.DUMMYFUNCTION("""COMPUTED_VALUE"""),"YASINTHA MBU") -> YASINTHA MBU | C19: =IFERROR(__xludf.DUMMYFUNCTION("""COMPUTED_VALUE"""),"Reject") -> Reject | E19: TER001 | F19: TUTOR ANTONIO DE JANAIRO TOMASOEY | G19: TERMINAL HP | H19: KUPANG
A20: =IFERROR(__xludf.DUMMYFUNCTION("""COMPUTED_VALUE"""),45898.499299629635) -> 45898.499 | B20: =IFERROR(__xludf.DUMMYFUNCTION("""COMPUTED_VALUE"""),"YASINTHA MBU") -> YASINTHA MBU | C20: =IFERROR(__xludf.DUMMYFUNCTION("""COMPUTED_VALUE"""),"Acc") -> Acc | D20: =IFERROR(__xludf.DUMMYFUNCTION("""COMPUTED_VALUE"""),"Y400") -> Y400 | E20: TER001 | F20: TUTOR ANTONIO DE JANAIRO TOMASOEY | G20: TERMINAL HP | H20: KUPANG
A21: =IFERROR(__xludf.DUMMYFUNCTION("""COMPUTED_VALUE"""),45898.57057521991) -> 45898.571 | B21: =IFERROR(__xludf.DUMMYFUNCTION("""COMPUTED_VALUE"""),"YOHANIS TIPNONI") -> YOHANIS TIPNONI | C21: =IFERROR(__xludf.DUMMYFUNCTION("""COMPUTED_VALUE"""),"Reject") -> Reject | E21: KIN001 | F21: TUTOR ANTONIO DE JANAIRO TOMASOEY | G21: KING CELL | H21: KUPANG
A22: =IFERROR(__xludf.DUMMYFUNCTION("""COMPUTED_VALUE"""),45898.65866562499) -> 45898.659 | B22: =IFERROR(__xludf.DUMMYFUNCTION("""COMPUTED_VALUE"""),"WARDIA") -> WARDIA | C22: =IFERROR(__xludf.DUMMYFUNCTION("""COMPUTED_VALUE"""),"Reject") -> Reject | D22: =IFERROR(__xludf.DUMMYFUNCTION("""COMPUTED_VALUE"""),"Y400") -> Y400 | E22: SPC006 | F22: TUTOR ANDRI RUDOLOF ELI MANAFE | G22: SPC OESAPA | H22: KUPANG
A23: =IFERROR(__xludf.DUMMYFUNCTION("""COMPUTED_VALUE"""),45898.6762975) -> 45898.676 | B23: =IFERROR(__xludf.DUMMYFUNCTION("""COMPUTED_VALUE"""),"YASINTHA MBU") -> YASINTHA MBU | C23: =IFERROR(__xludf.DUMMYFUNCTION("""COMPUTED_VALUE"""),"belum dapat limit") -> belum dapat limit | D23: =IFERROR(__xludf.DUMMYFUNCTION("""COMPUTED_VALUE"""),"Y400") -> Y400 | E23: TER001 | F23: TUTOR ANTONIO DE JANAIRO TOMASOEY | G23: TERMINAL HP | H23: KUPANG
A24: =IFERROR(__xludf.DUMMYFUNCTION("""COMPUTED_VALUE"""),45898.79220520833) -> 45898.792 | B24: =IFERROR(__xludf.DUMMYFUNCTION("""COMPUTED_VALUE"""),"YASINTHA MBU") -> YASINTHA MBU | C24: =IFERROR(__xludf.DUMMYFUNCTION("""COMPUTED_VALUE"""),"Acc") -> Acc | D24: =IFERROR(__xludf.DUMMYFUNCTION("""COMPUTED_VALUE"""),"V50 LITE") -> V50 LITE | E24: TER001 | F24: TUTOR ANTONIO DE JANAIRO TOMASOEY | G24: TERMINAL HP | H24: KUPANG
A25: =IFERROR(__xludf.DUMMYFUNCTION("""COMPUTED_VALUE"""),45898.83603935185) -> 45898.836 | B25: =IFERROR(__xludf.DUMMYFUNCTION("""COMPUTED_VALUE"""),"SELVINCE BAKO") -> SELVINCE BAKO | C25: =IFERROR(__xludf.DUMMYFUNCTION("""COMPUTED_VALUE"""),"Tidak dapat limit") -> Tidak dapat limit | D25: =IFERROR(__xludf.DUMMYFUNCTION("""COMPUTED_VALUE"""),"Y400") -> Y400 | E25: SPC003 | F25: TUTOR ANDRI RUDOLOF ELI MANAFE | G25: SPC KUANINO | H25: KUPANG
A26: =IFERROR(__xludf.DUMMYFUNCTION("""COMPUTED_VALUE"""),45898.86502353009) -> 45898.865 | B26: =IFERROR(__xludf.DUMMYFUNCTION("""COMPUTED_VALUE"""),"SKOLASTIKA B TAUNAES") -> SKOLASTIKA B TAUNAES | C26: =IFERROR(__xludf.DUMMYFUNCTION("""COMPUTED_VALUE"""),"Reject") -> Reject | D26: =IFERROR(__xludf.DUMMYFUNCTION("""COMPUTED_VALUE"""),"Y400") -> Y400 | E26: SPC003 | F26: TUTOR ANDRI RUDOLOF ELI MANAFE | G26: SPC KUANINO | H26: KUPANG
A27: =IFERROR(__xludf.DUMMYFUNCTION("""COMPUTED_VALUE"""),45898.86524013889) -> 45898.865 | B27: =IFERROR(__xludf.DUMMYFUNCTION("""COMPUTED_VALUE"""),"SELVINCE BAKO") -> SELVINCE BAKO | C27: =IFERROR(__xludf.DUMMYFUNCTION("""COMPUTED_VALUE"""),"Tidak dapt limit") -> Tidak dapt limit | D27: =IFERROR(__xludf.DUMMYFUNCTION("""COMPUTED_VALUE"""),"Lain nya...") -> Lain nya... | E27: SPC003 | F27: TUTOR ANDRI RUDOLOF ELI MANAFE | G27: SPC KUANINO | H27: KUPANG
A28: =IFERROR(__xludf.DUMMYFUNCTION("""COMPUTED_VALUE"""),45898.866954363424) -> 45898.867 | B28: =IFERROR(__xludf.DUMMYFUNCTION("""COMPUTED_VALUE"""),"YOHANIS TIPNONI") -> YOHANIS TIPNONI | C28: =IFERROR(__xludf.DUMMYFUNCTION("""COMPUTED_VALUE"""),"Tidak dapat limit") -> Tidak dapat limit | D28: =IFERROR(__xludf.DUMMYFUNCTION("""COMPUTED_VALUE"""),"Y400") -> Y400 | E28: KIN001 | F28: TUTOR ANTONIO DE JANAIRO TOMASOEY | G28: KING CELL | H28: KUPANG
A29: =IFERROR(__xludf.DUMMYFUNCTION("""COMPUTED_VALUE"""),45898.867018321755) -> 45898.867 | B29: =IFERROR(__xludf.DUMMYFUNCTION("""COMPUTED_VALUE"""),"SKOLASTIKA B TAUNAES") -> SKOLASTIKA B TAUNAES | C29: =IFERROR(__xludf.DUMMYFUNCTION("""COMPUTED_VALUE"""),"Reject") -> Reject | D29: =IFERROR(__xludf.DUMMYFUNCTION("""COMPUTED_VALUE"""),"Y400") -> Y400 | E29: SPC003 | F29: TUTOR ANDRI RUDOLOF ELI MANAFE | G29: SPC KUANINO | H29: KUPANG
A30: =IFERROR(__xludf.DUMMYFUNCTION("""COMPUTED_VALUE"""),45898.869698692135) -> 45898.87 | B30: =IFERROR(__xludf.DUMMYFUNCTION("""COMPUTED_VALUE"""),"YOHANIS TIPNONI") -> YOHANIS TIPNONI | C30: =IFERROR(__xludf.DUMMYFUNCTION("""COMPUTED_VALUE"""),"Tidak ada limit") -> Tidak ada limit | D30: =IFERROR(__xludf.DUMMYFUNCTION("""COMPUTED_VALUE"""),"Y400") -> Y400 | E30: KIN001 | F30: TUTOR ANTONIO DE JANAIRO TOMASOEY | G30: KING CELL | H30: KUPANG
A31: =IFERROR(__xludf.DUMMYFUNCTION("""COMPUTED_VALUE"""),45898.870139907405) -> 45898.87 | B31: =IFERROR(__xludf.DUMMYFUNCTION("""COMPUTED_VALUE"""),"FEBRIANTHY ELISABET NA'U") -> FEBRIANTHY ELISABET NA'U | C31: =IFERROR(__xludf.DUMMYFUNCTION("""COMPUTED_VALUE"""),"Reject") -> Reject | D31: =IFERROR(__xludf.DUMMYFUNCTION("""COMPUTED_VALUE"""),"Y400") -> Y400 | E31: SPC011 | F31: TUTOR ANDRI RUDOLOF ELI MANAFE | G31: SPC STARLIGHT | H31: KUPANG
A32: =IFERROR(__xludf.DUMMYFUNCTION("""COMPUTED_VALUE"""),45898.87224603009) -> 45898.872 | B32: =IFERROR(__xludf.DUMMYFUNCTION("""COMPUTED_VALUE"""),"FEBRIANTHY ELISABET NA'U") -> FEBRIANTHY ELISABET NA'U | C32: =IFERROR(__xludf.DUMMYFUNCTION("""COMPUTED_VALUE"""),"Reject") -> Reject | D32: =IFERROR(__xludf.DUMMYFUNCTION("""COMPUTED_VALUE"""),"Y400") -> Y400 | E32: SPC011 | F32: TUTOR ANDRI RUDOLOF ELI MANAFE | G32: SPC STARLIGHT | H32: KUPANG
A33: =IFERROR(__xludf.DUMMYFUNCTION("""COMPUTED_VALUE"""),45899.52757194444) -> 45899.528 | B33: =IFERROR(__xludf.DUMMYFUNCTION("""COMPUTED_VALUE"""),"KESIA NATALIA I. BENU") -> KESIA NATALIA I. BENU | C33: =IFERROR(__xludf.DUMMYFUNCTION("""COMPUTED_VALUE"""),"ACC") -> ACC | D33: =IFERROR(__xludf.DUMMYFUNCTION("""COMPUTED_VALUE"""),"Y400 series") -> Y400 series | E33: KHA002 | F33: SPV ANFAL JUPRIADI AMBU WARU | G33: KHAIRIL CELL | H33: SUMBA
A34: =IFERROR(__xludf.DUMMYFUNCTION("""COMPUTED_VALUE"""),45899.52757194444) -> 45899.528 | B34: =IFERROR(__xludf.DUMMYFUNCTION("""COMPUTED_VALUE"""),"MARNITHA JUWIKE TIMORATI RUNESI") -> MARNITHA JUWIKE TIMORATI RUNESI | C34: =IFERROR(__xludf.DUMMYFUNCTION("""COMPUTED_VALUE"""),"ACC") -> ACC | D34: =IFERROR(__xludf.DUMMYFUNCTION("""COMPUTED_VALUE"""),"Y400 series") -> Y400 series | E34: SPC005 | F34: TUTOR ANDRI RUDOLOF ELI MANAFE | G34: SPC OESAO | H34: KUPANG
A35: =IFERROR(__xludf.DUMMYFUNCTION("""COMPUTED_VALUE"""),45899.57235034722) -> 45899.572 | B35: =IFERROR(__xludf.DUMMYFUNCTION("""COMPUTED_VALUE"""),"YOHANA NOVIANA MARIANA GAA") -> YOHANA NOVIANA MARIANA GAA | C35: =IFERROR(__xludf.DUMMYFUNCTION("""COMPUTED_VALUE"""),"No Limit") -> No Limit | E35: SPC007 | F35: TUTOR ANDRI RUDOLOF ELI MANAFE | G35: SPC PLATINUM | H35: KUPANG
A36: =IFERROR(__xludf.DUMMYFUNCTION("""COMPUTED_VALUE"""),45899.619064976854) -> 45899.619 | B36: =IFERROR(__xludf.DUMMYFUNCTION("""COMPUTED_VALUE"""),"MERDA PUTRI BUNGSU KENAT") -> MERDA PUTRI BUNGSU KENAT | C36: =IFERROR(__xludf.DUMMYFUNCTION("""COMPUTED_VALUE"""),"ACC") -> ACC | D36: =IFERROR(__xludf.DUMMYFUNCTION("""COMPUTED_VALUE"""),"Y400 series") -> Y400 series | E36: QIN001 | F36: TUTOR HERY YULIUS DILLAK | G36: QINARA CELL | H36: KABUPATEN
A37: =IFERROR(__xludf.DUMMYFUNCTION("""COMPUTED_VALUE"""),45899.774507256945) -> 45899.775 | B37: =IFERROR(__xludf.DUMMYFUNCTION("""COMPUTED_VALUE"""),"EMPI FRANGKI LIEM") -> EMPI FRANGKI LIEM | C37: =IFERROR(__xludf.DUMMYFUNCTION("""COMPUTED_VALUE"""),"ACC") -> ACC | D37: =IFERROR(__xludf.DUMMYFUNCTION("""COMPUTED_VALUE"""),"Y400 series") -> Y400 series | E37: MCE001 | F37: TUTOR ANTONIO DE JANAIRO TOMASOEY | G37: MCELL | H37: KUPANG
A38: =IFERROR(__xludf.DUMMYFUNCTION("""COMPUTED_VALUE"""),45899.774507256945) -> 45899.775 | B38: =IFERROR(__xludf.DUMMYFUNCTION("""COMPUTED_VALUE"""),"EMPI FRANGKI LIEM") -> EMPI FRANGKI LIEM | C38: =IFERROR(__xludf.DUMMYFUNCTION("""COMPUTED_VALUE"""),"ACC") -> ACC | D38: =IFERROR(__xludf.DUMMYFUNCTION("""COMPUTED_VALUE"""),"Y400 series") -> Y400 series | E38: MCE001 | F38: TUTOR ANTONIO DE JANAIRO TOMASOEY | G38: MCELL | H38: KUPANG
A39: =IFERROR(__xludf.DUMMYFUNCTION("""COMPUTED_VALUE"""),45899.78745510416) -> 45899.787 | B39: =IFERROR(__xludf.DUMMYFUNCTION("""COMPUTED_VALUE"""),"YOHANIS TIPNONI") -> YOHANIS TIPNONI | C39: =IFERROR(__xludf.DUMMYFUNCTION("""COMPUTED_VALUE"""),"No Limit") -> No Limit | E39: KIN001 | F39: TUTOR ANTONIO DE JANAIRO TOMASOEY | G39: KING CELL | H39: KUPANG
A40: =IFERROR(__xludf.DUMMYFUNCTION("""COMPUTED_VALUE"""),45899.78745510416) -> 45899.787 | B40: =IFERROR(__xludf.DUMMYFUNCTION("""COMPUTED_VALUE"""),"YOHANIS TIPNONI") -> YOHANIS TIPNONI | C40: =IFERROR(__xludf.DUMMYFUNCTION("""COMPUTED_VALUE"""),"No Limit") -> No Limit | E40: KIN001 | F40: TUTOR ANTONIO DE JANAIRO TOMASOEY | G40: KING CELL | H40: KUPANG
A41: =IFERROR(__xludf.DUMMYFUNCTION("""COMPUTED_VALUE"""),45899.81200167824) -> 45899.812 | B41: =IFERROR(__xludf.DUMMYFUNCTION("""COMPUTED_VALUE"""),"NOVANTRY RUTHANIA NAFFIE") -> NOVANTRY RUTHANIA NAFFIE | C41: =IFERROR(__xludf.DUMMYFUNCTION("""COMPUTED_VALUE"""),"Belum disetujui") -> Belum disetujui | E41: MCE001 | F41: TUTOR ANTONIO DE JANAIRO TOMASOEY | G41: MCELL | H41: KUPANG
A42: =IFERROR(__xludf.DUMMYFUNCTION("""COMPUTED_VALUE"""),45899.81200167824) -> 45899.812 | B42: =IFERROR(__xludf.DUMMYFUNCTION("""COMPUTED_VALUE"""),"NOVANTRY RUTHANIA NAFFIE") -> NOVANTRY RUTHANIA NAFFIE | C42: =IFERROR(__xludf.DUMMYFUNCTION("""COMPUTED_VALUE"""),"Belum disetujui") -> Belum disetujui | E42: MCE001 | F42: TUTOR ANTONIO DE JANAIRO TOMASOEY | G42: MCELL | H42: KUPANG
A43: =IFERROR(__xludf.DUMMYFUNCTION("""COMPUTED_VALUE"""),45899.82615413194) -> 45899.826 | B43: =IFERROR(__xludf.DUMMYFUNCTION("""COMPUTED_VALUE"""),"NOVANTRY RUTHANIA NAFFIE") -> NOVANTRY RUTHANIA NAFFIE | C43: =IFERROR(__xludf.DUMMYFUNCTION("""COMPUTED_VALUE"""),"Belum disetujui") -> Belum disetujui | E43: MCE001 | F43: TUTOR ANTONIO DE JANAIRO TOMASOEY | G43: MCELL | H43: KUPANG
A44: =IFERROR(__xludf.DUMMYFUNCTION("""COMPUTED_VALUE"""),45899.82615413194) -> 45899.826 | B44: =IFERROR(__xludf.DUMMYFUNCTION("""COMPUTED_VALUE"""),"NOVANTRY RUTHANIA NAFFIE") -> NOVANTRY RUTHANIA NAFFIE | C44: =IFERROR(__xludf.DUMMYFUNCTION("""COMPUTED_VALUE"""),"Belum disetujui") -> Belum disetujui | E44: MCE001 | F44: TUTOR ANTONIO DE JANAIRO TOMASOEY | G44: MCELL | H44: KUPANG
A45: =IFERROR(__xludf.DUMMYFUNCTION("""COMPUTED_VALUE"""),45899.82789027778) -> 45899.828 | B45: =IFERROR(__xludf.DUMMYFUNCTION("""COMPUTED_VALUE"""),"FERI ELI KURNIAWAN") -> FERI ELI KURNIAWAN | C45: =IFERROR(__xludf.DUMMYFUNCTION("""COMPUTED_VALUE"""),"ACC") -> ACC | D45: =IFERROR(__xludf.DUMMYFUNCTION("""COMPUTED_VALUE"""),"Y400 series") -> Y400 series | E45: PLA001 | F45: TUTOR ANTONIO DE JANAIRO TOMASOEY | G45: PLANET GADGET | H45: KUPANG
A46: =IFERROR(__xludf.DUMMYFUNCTION("""COMPUTED_VALUE"""),45899.82789027778) -> 45899.828 | B46: =IFERROR(__xludf.DUMMYFUNCTION("""COMPUTED_VALUE"""),"FERI ELI KURNIAWAN") -> FERI ELI KURNIAWAN | C46: =IFERROR(__xludf.DUMMYFUNCTION("""COMPUTED_VALUE"""),"ACC") -> ACC | D46: =IFERROR(__xludf.DUMMYFUNCTION("""COMPUTED_VALUE"""),"Y400 series") -> Y400 series | E46: PLA001 | F46: TUTOR ANTONIO DE JANAIRO TOMASOEY | G46: PLANET GADGET | H46: KUPANG
A47: =IFERROR(__xludf.DUMMYFUNCTION("""COMPUTED_VALUE"""),45899.90095579861) -> 45899.901 | B47: =IFERROR(__xludf.DUMMYFUNCTION("""COMPUTED_VALUE"""),"YASINTHA MBU") -> YASINTHA MBU | C47: =IFERROR(__xludf.DUMMYFUNCTION("""COMPUTED_VALUE"""),"No Limit") -> No Limit | E47: TER001 | F47: TUTOR ANTONIO DE JANAIRO TOMASOEY | G47: TERMINAL HP | H47: KUPANG
A48: =IFERROR(__xludf.DUMMYFUNCTION("""COMPUTED_VALUE"""),45899.90095579861) -> 45899.901 | B48: =IFERROR(__xludf.DUMMYFUNCTION("""COMPUTED_VALUE"""),"YASINTHA MBU") -> YASINTHA MBU | C48: =IFERROR(__xludf.DUMMYFUNCTION("""COMPUTED_VALUE"""),"No Limit") -> No Limit | E48: TER001 | F48: TUTOR ANTONIO DE JANAIRO TOMASOEY | G48: TERMINAL HP | H48: KUPANG
A49: =IFERROR(__xludf.DUMMYFUNCTION("""COMPUTED_VALUE"""),45900.542593356484) -> 45900.543 | B49: =IFERROR(__xludf.DUMMYFUNCTION("""COMPUTED_VALUE"""),"PATRIANI MENGI ULY") -> PATRIANI MENGI ULY | C49: =IFERROR(__xludf.DUMMYFUNCTION("""COMPUTED_VALUE"""),"Belum disetujui") -> Belum disetujui | E49: SPC004 | F49: TUTOR ANDRI RUDOLOF ELI MANAFE | G49: SPC MASTER CELL | H49: KUPANG
A50: =IFERROR(__xludf.DUMMYFUNCTION("""COMPUTED_VALUE"""),45900.542593356484) -> 45900.543 | B50: =IFERROR(__xludf.DUMMYFUNCTION("""COMPUTED_VALUE"""),"PATRIANI MENGI ULY") -> PATRIANI MENGI ULY | C50: =IFERROR(__xludf.DUMMYFUNCTION("""COMPUTED_VALUE"""),"Belum disetujui") -> Belum disetujui | E50: SPC004 | F50: TUTOR ANDRI RUDOLOF ELI MANAFE | G50: SPC MASTER CELL | H50: KUPANG
A51: =IFERROR(__xludf.DUMMYFUNCTION("""COMPUTED_VALUE"""),45900.84245362269) -> 45900.842 | B51: =IFERROR(__xludf.DUMMYFUNCTION("""COMPUTED_VALUE"""),"AINI RAHMATINI NATALIA MOESTAKIM") -> AINI RAHMATINI NATALIA MOESTAKIM | C51: =IFERROR(__xludf.DUMMYFUNCTION("""COMPUTED_VALUE"""),"Belum disetujui") -> Belum disetujui | E51: SPC006 | F51: TUTOR ANDRI RUDOLOF ELI MANAFE | G51: SPC OESAPA | H51: KUPANG
A52: =IFERROR(__xludf.DUMMYFUNCTION("""COMPUTED_VALUE"""),45900.84245362269) -> 45900.842 | B52: =IFERROR(__xludf.DUMMYFUNCTION("""COMPUTED_VALUE"""),"AINI RAHMATINI NATALIA MOESTAKIM") -> AINI RAHMATINI NATALIA MOESTAKIM | C52: =IFERROR(__xludf.DUMMYFUNCTION("""COMPUTED_VALUE"""),"Belum disetujui") -> Belum disetujui | E52: SPC006 | F52: TUTOR ANDRI RUDOLOF ELI MANAFE | G52: SPC OESAPA | H52: KUPANG
A53: =IFERROR(__xludf.DUMMYFUNCTION("""COMPUTED_VALUE"""),45901.538850578705) -> 45901.539 | B53: =IFERROR(__xludf.DUMMYFUNCTION("""COMPUTED_VALUE"""),"YOVANDA KATRINA NAE") -> YOVANDA KATRINA NAE | C53: =IFERROR(__xludf.DUMMYFUNCTION("""COMPUTED_VALUE"""),"Belum disetujui") -> Belum disetujui | E53: QUE001 | F53: TUTOR KUSMYATI KILIMANDU | G53: QUEEN CELL | H53: SUMBA
A54: =IFERROR(__xludf.DUMMYFUNCTION("""COMPUTED_VALUE"""),45901.544305069445) -> 45901.544 | B54: =IFERROR(__xludf.DUMMYFUNCTION("""COMPUTED_VALUE"""),"ASTUTI BELA WAWO") -> ASTUTI BELA WAWO | C54: =IFERROR(__xludf.DUMMYFUNCTION("""COMPUTED_VALUE"""),"ACC") -> ACC | D54: =IFERROR(__xludf.DUMMYFUNCTION("""COMPUTED_VALUE"""),"Y400 series") -> Y400 series | E54: GLO002 | F54: SPV ANFAL JUPRIADI AMBU WARU | G54: GLOBAL TEKNIK 2 | H54: SUMBA
A55: =IFERROR(__xludf.DUMMYFUNCTION("""COMPUTED_VALUE"""),45901.557086574074) -> 45901.557 | B55: =IFERROR(__xludf.DUMMYFUNCTION("""COMPUTED_VALUE"""),"ASTUTI BELA WAWO") -> ASTUTI BELA WAWO | C55: =IFERROR(__xludf.DUMMYFUNCTION("""COMPUTED_VALUE"""),"Belum disetujui") -> Belum disetujui | E55: GLO002 | F55: SPV ANFAL JUPRIADI AMBU WARU | G55: GLOBAL TEKNIK 2 | H55: SUMBA
A56: =IFERROR(__xludf.DUMMYFUNCTION("""COMPUTED_VALUE"""),45901.55869613426) -> 45901.559 | B56: =IFERROR(__xludf.DUMMYFUNCTION("""COMPUTED_VALUE"""),"ASTUTI BELA WAWO") -> ASTUTI BELA WAWO | C56: =IFERROR(__xludf.DUMMYFUNCTION("""COMPUTED_VALUE"""),"Belum disetujui") -> Belum disetujui | E56: GLO002 | F56: SPV ANFAL JUPRIADI AMBU WARU | G56: GLOBAL TEKNIK 2 | H56: SUMBA
A57: =IFERROR(__xludf.DUMMYFUNCTION("""COMPUTED_VALUE"""),45901.60721225694) -> 45901.607 | B57: =IFERROR(__xludf.DUMMYFUNCTION("""COMPUTED_VALUE"""),"SULIS NURAINI INSYATUN") -> SULIS NURAINI INSYATUN | C57: =IFERROR(__xludf.DUMMYFUNCTION("""COMPUTED_VALUE"""),"Belum disetujui") -> Belum disetujui | E57: KHA001 | F57: SPV ANFAL JUPRIADI AMBU WARU | G57: KHAIR CELL | H57: SUMBA
A58: =IFERROR(__xludf.DUMMYFUNCTION("""COMPUTED_VALUE"""),45901.60798973379) -> 45901.608 | B58: =IFERROR(__xludf.DUMMYFUNCTION("""COMPUTED_VALUE"""),"DEMARISTI S H FENI") -> DEMARISTI S H FENI | C58: =IFERROR(__xludf.DUMMYFUNCTION("""COMPUTED_VALUE"""),"Belum disetujui") -> Belum disetujui
A59: =IFERROR(__xludf.DUMMYFUNCTION("""COMPUTED_VALUE"""),45901.608943148145) -> 45901.609 | B59: =IFERROR(__xludf.DUMMYFUNCTION("""COMPUTED_VALUE"""),"YASINTHA MBU") -> YASINTHA MBU | C59: =IFERROR(__xludf.DUMMYFUNCTION("""COMPUTED_VALUE"""),"Belum disetujui") -> Belum disetujui | E59: TER001 | F59: TUTOR ANTONIO DE JANAIRO TOMASOEY | G59: TERMINAL HP | H59: KUPANG
A60: =IFERROR(__xludf.DUMMYFUNCTION("""COMPUTED_VALUE"""),45901.612523668984) -> 45901.613 | B60: =IFERROR(__xludf.DUMMYFUNCTION("""COMPUTED_VALUE"""),"IDMAL YUSDIRAN YUSUF") -> IDMAL YUSDIRAN YUSUF | C60: =IFERROR(__xludf.DUMMYFUNCTION("""COMPUTED_VALUE"""),"ACC") -> ACC | D60: =IFERROR(__xludf.DUMMYFUNCTION("""COMPUTED_VALUE"""),"Y400 series") -> Y400 series | E60: KHA002 | F60: SPV ANFAL JUPRIADI AMBU WARU | G60: KHAIRIL CELL | H60: SUMBA
A61: =IFERROR(__xludf.DUMMYFUNCTION("""COMPUTED_VALUE"""),45901.654122106476) -> 45901.654 | B61: =IFERROR(__xludf.DUMMYFUNCTION("""COMPUTED_VALUE"""),"MARNITHA JUWIKE TIMORATI RUNESI") -> MARNITHA JUWIKE TIMORATI RUNESI | C61: =IFERROR(__xludf.DUMMYFUNCTION("""COMPUTED_VALUE"""),"Belum disetujui") -> Belum disetujui | E61: SPC005 | F61: TUTOR ANDRI RUDOLOF ELI MANAFE | G61: SPC OESAO | H61: KUPANG
A62: =IFERROR(__xludf.DUMMYFUNCTION("""COMPUTED_VALUE"""),45901.665994166666) -> 45901.666 | B62: =IFERROR(__xludf.DUMMYFUNCTION("""COMPUTED_VALUE"""),"IDMAL YUSDIRAN YUSUF") -> IDMAL YUSDIRAN YUSUF | C62: =IFERROR(__xludf.DUMMYFUNCTION("""COMPUTED_VALUE"""),"Belum disetujui") -> Belum disetujui | E62: KHA002 | F62: SPV ANFAL JUPRIADI AMBU WARU | G62: KHAIRIL CELL | H62: SUMBA
A63: =IFERROR(__xludf.DUMMYFUNCTION("""COMPUTED_VALUE"""),45901.66755630787) -> 45901.668 | B63: =IFERROR(__xludf.DUMMYFUNCTION("""COMPUTED_VALUE"""),"NOVANTRY RUTHANIA NAFFIE") -> NOVANTRY RUTHANIA NAFFIE | C63: =IFERROR(__xludf.DUMMYFUNCTION("""COMPUTED_VALUE"""),"Belum disetujui") -> Belum disetujui | E63: MCE001 | F63: TUTOR ANTONIO DE JANAIRO TOMASOEY | G63: MCELL | H63: KUPANG
A64: =IFERROR(__xludf.DUMMYFUNCTION("""COMPUTED_VALUE"""),45901.68529576389) -> 45901.685 | B64: =IFERROR(__xludf.DUMMYFUNCTION("""COMPUTED_VALUE"""),"SULIS NURAINI INSYATUN") -> SULIS NURAINI INSYATUN | C64: =IFERROR(__xludf.DUMMYFUNCTION("""COMPUTED_VALUE"""),"ACC") -> ACC | D64: =IFERROR(__xludf.DUMMYFUNCTION("""COMPUTED_VALUE"""),"Y400 series") -> Y400 series | E64: KHA001 | F64: SPV ANFAL JUPRIADI AMBU WARU | G64: KHAIR CELL | H64: SUMBA
A65: =IFERROR(__xludf.DUMMYFUNCTION("""COMPUTED_VALUE"""),45901.72030047454) -> 45901.72 | B65: =IFERROR(__xludf.DUMMYFUNCTION("""COMPUTED_VALUE"""),"SULIS NURAINI INSYATUN") -> SULIS NURAINI INSYATUN | C65: =IFERROR(__xludf.DUMMYFUNCTION("""COMPUTED_VALUE"""),"Belum disetujui") -> Belum disetujui | E65: KHA001 | F65: SPV ANFAL JUPRIADI AMBU WARU | G65: KHAIR CELL | H65: SUMBA
A66: =IFERROR(__xludf.DUMMYFUNCTION("""COMPUTED_VALUE"""),45901.7713924537) -> 45901.771 | B66: =IFERROR(__xludf.DUMMYFUNCTION("""COMPUTED_VALUE"""),"DEMARISTI S H FENI") -> DEMARISTI S H FENI | C66: =IFERROR(__xludf.DUMMYFUNCTION("""COMPUTED_VALUE"""),"Belum disetujui") -> Belum disetujui
A67: =IFERROR(__xludf.DUMMYFUNCTION("""COMPUTED_VALUE"""),45901.77915246528) -> 45901.779 | B67: =IFERROR(__xludf.DUMMYFUNCTION("""COMPUTED_VALUE"""),"BERGITHA NIA OLIN") -> BERGITHA NIA OLIN | C67: =IFERROR(__xludf.DUMMYFUNCTION("""COMPUTED_VALUE"""),"Belum disetujui") -> Belum disetujui | E67: INF001 | F67: TUTOR LEU ADOLF QICHEN LEI BAIT | G67: INFINITY CELL | H67: KABUPATEN
A68: =IFERROR(__xludf.DUMMYFUNCTION("""COMPUTED_VALUE"""),45901.78771160879) -> 45901.788 | B68: =IFERROR(__xludf.DUMMYFUNCTION("""COMPUTED_VALUE"""),"BERGITHA NIA OLIN") -> BERGITHA NIA OLIN | C68: =IFERROR(__xludf.DUMMYFUNCTION("""COMPUTED_VALUE"""),"Belum disetujui") -> Belum disetujui | E68: INF001 | F68: TUTOR LEU ADOLF QICHEN LEI BAIT | G68: INFINITY CELL | H68: KABUPATEN
A69: =IFERROR(__xludf.DUMMYFUNCTION("""COMPUTED_VALUE"""),45901.78979534723) -> 45901.79 | B69: =IFERROR(__xludf.DUMMYFUNCTION("""COMPUTED_VALUE"""),"YOHANIS TIPNONI") -> YOHANIS TIPNONI | C69: =IFERROR(__xludf.DUMMYFUNCTION("""COMPUTED_VALUE"""),"ACC") -> ACC | D69: =IFERROR(__xludf.DUMMYFUNCTION("""COMPUTED_VALUE"""),"Y400 series") -> Y400 series | E69: KIN001 | F69: TUTOR ANTONIO DE JANAIRO TOMASOEY | G69: KING CELL | H69: KUPANG
A70: =IFERROR(__xludf.DUMMYFUNCTION("""COMPUTED_VALUE"""),45901.79177538194) -> 45901.792 | B70: =IFERROR(__xludf.DUMMYFUNCTION("""COMPUTED_VALUE"""),"BERGITHA NIA OLIN") -> BERGITHA NIA OLIN | C70: =IFERROR(__xludf.DUMMYFUNCTION("""COMPUTED_VALUE"""),"Belum disetujui") -> Belum disetujui | E70: INF001 | F70: TUTOR LEU ADOLF QICHEN LEI BAIT | G70: INFINITY CELL | H70: KABUPATEN
A71: =IFERROR(__xludf.DUMMYFUNCTION("""COMPUTED_VALUE"""),45901.79504125) -> 45901.795 | B71: =IFERROR(__xludf.DUMMYFUNCTION("""COMPUTED_VALUE"""),"ADRIANA") -> ADRIANA | C71: =IFERROR(__xludf.DUMMYFUNCTION("""COMPUTED_VALUE"""),"Belum disetujui") -> Belum disetujui | E71: MUT001 | F71: TUTOR LEU ADOLF QICHEN LEI BAIT | G71: MUTIARA CELL | H71: KABUPATEN
A72: =IFERROR(__xludf.DUMMYFUNCTION("""COMPUTED_VALUE"""),45901.80172587963) -> 45901.802 | B72: =IFERROR(__xludf.DUMMYFUNCTION("""COMPUTED_VALUE"""),"NOVANTRY RUTHANIA NAFFIE") -> NOVANTRY RUTHANIA NAFFIE | C72: =IFERROR(__xludf.DUMMYFUNCTION("""COMPUTED_VALUE"""),"Belum disetujui") -> Belum disetujui | E72: MCE001 | F72: TUTOR ANTONIO DE JANAIRO TOMASOEY | G72: MCELL | H72: KUPANG
A73: =IFERROR(__xludf.DUMMYFUNCTION("""COMPUTED_VALUE"""),45901.803267453695) -> 45901.803 | B73: =IFERROR(__xludf.DUMMYFUNCTION("""COMPUTED_VALUE"""),"ASTUTI BELA WAWO") -> ASTUTI BELA WAWO | C73: =IFERROR(__xludf.DUMMYFUNCTION("""COMPUTED_VALUE"""),"ACC") -> ACC | D73: =IFERROR(__xludf.DUMMYFUNCTION("""COMPUTED_VALUE"""),"Y400 series") -> Y400 series | E73: GLO002 | F73: SPV ANFAL JUPRIADI AMBU WARU | G73: GLOBAL TEKNIK 2 | H73: SUMBA
A74: =IFERROR(__xludf.DUMMYFUNCTION("""COMPUTED_VALUE"""),45901.80976429398) -> 45901.81 | B74: =IFERROR(__xludf.DUMMYFUNCTION("""COMPUTED_VALUE"""),"ASTUTI BELA WAWO") -> ASTUTI BELA WAWO | C74: =IFERROR(__xludf.DUMMYFUNCTION("""COMPUTED_VALUE"""),"Belum disetujui") -> Belum disetujui | E74: GLO002 | F74: SPV ANFAL JUPRIADI AMBU WARU | G74: GLOBAL TEKNIK 2 | H74: SUMBA
A75: =IFERROR(__xludf.DUMMYFUNCTION("""COMPUTED_VALUE"""),45901.812202685185) -> 45901.812 | B75: =IFERROR(__xludf.DUMMYFUNCTION("""COMPUTED_VALUE"""),"ASTUTI BELA WAWO") -> ASTUTI BELA WAWO | C75: =IFERROR(__xludf.DUMMYFUNCTION("""COMPUTED_VALUE"""),"Belum disetujui") -> Belum disetujui | E75: GLO002 | F75: SPV ANFAL JUPRIADI AMBU WARU | G75: GLOBAL TEKNIK 2 | H75: SUMBA
A76: =IFERROR(__xludf.DUMMYFUNCTION("""COMPUTED_VALUE"""),45901.813779791664) -> 45901.814 | B76: =IFERROR(__xludf.DUMMYFUNCTION("""COMPUTED_VALUE"""),"ASTUTI BELA WAWO") -> ASTUTI BELA WAWO | C76: =IFERROR(__xludf.DUMMYFUNCTION("""COMPUTED_VALUE"""),"Belum disetujui") -> Belum disetujui | E76: GLO002 | F76: SPV ANFAL JUPRIADI AMBU WARU | G76: GLOBAL TEKNIK 2 | H76: SUMBA
A77: =IFERROR(__xludf.DUMMYFUNCTION("""COMPUTED_VALUE"""),45901.82026493055) -> 45901.82 | B77: =IFERROR(__xludf.DUMMYFUNCTION("""COMPUTED_VALUE"""),"EMPI FRANGKI LIEM") -> EMPI FRANGKI LIEM | C77: =IFERROR(__xludf.DUMMYFUNCTION("""COMPUTED_VALUE"""),"ACC") -> ACC | D77: =IFERROR(__xludf.DUMMYFUNCTION("""COMPUTED_VALUE"""),"Y400 series") -> Y400 series | E77: MCE001 | F77: TUTOR ANTONIO DE JANAIRO TOMASOEY | G77: MCELL | H77: KUPANG
A78: =IFERROR(__xludf.DUMMYFUNCTION("""COMPUTED_VALUE"""),45901.82213983796) -> 45901.822 | B78: =IFERROR(__xludf.DUMMYFUNCTION("""COMPUTED_VALUE"""),"BERGITHA NIA OLIN") -> BERGITHA NIA OLIN | C78: =IFERROR(__xludf.DUMMYFUNCTION("""COMPUTED_VALUE"""),"Belum disetujui") -> Belum disetujui | E78: INF001 | F78: TUTOR LEU ADOLF QICHEN LEI BAIT | G78: INFINITY CELL | H78: KABUPATEN
A79: =IFERROR(__xludf.DUMMYFUNCTION("""COMPUTED_VALUE"""),45901.82789208333) -> 45901.828 | B79: =IFERROR(__xludf.DUMMYFUNCTION("""COMPUTED_VALUE"""),"LINDA MELSIANA ELLO") -> LINDA MELSIANA ELLO | C79: =IFERROR(__xludf.DUMMYFUNCTION("""COMPUTED_VALUE"""),"Belum disetujui") -> Belum disetujui | E79: AND001 | F79: TUTOR HERY YULIUS DILLAK | G79: ANDYS CELL | H79: KABUPATEN
A80: =IFERROR(__xludf.DUMMYFUNCTION("""COMPUTED_VALUE"""),45901.83536979166) -> 45901.835 | B80: =IFERROR(__xludf.DUMMYFUNCTION("""COMPUTED_VALUE"""),"ROS YANE KANA LUDJI") -> ROS YANE KANA LUDJI | C80: =IFERROR(__xludf.DUMMYFUNCTION("""COMPUTED_VALUE"""),"Belum disetujui") -> Belum disetujui | E80: SPC013 | F80: TUTOR ANDRI RUDOLOF ELI MANAFE | G80: SPC TERMINAL | H80: KUPANG
A81: =IFERROR(__xludf.DUMMYFUNCTION("""COMPUTED_VALUE"""),45901.839190879626) -> 45901.839 | B81: =IFERROR(__xludf.DUMMYFUNCTION("""COMPUTED_VALUE"""),"ROS YANE KANA LUDJI") -> ROS YANE KANA LUDJI | C81: =IFERROR(__xludf.DUMMYFUNCTION("""COMPUTED_VALUE"""),"Belum disetujui") -> Belum disetujui | E81: SPC013 | F81: TUTOR ANDRI RUDOLOF ELI MANAFE | G81: SPC TERMINAL | H81: KUPANG
A82: =IFERROR(__xludf.DUMMYFUNCTION("""COMPUTED_VALUE"""),45901.84227118056) -> 45901.842 | B82: =IFERROR(__xludf.DUMMYFUNCTION("""COMPUTED_VALUE"""),"FEBRIANTHY ELISABET NA'U") -> FEBRIANTHY ELISABET NA'U | C82: =IFERROR(__xludf.DUMMYFUNCTION("""COMPUTED_VALUE"""),"Belum disetujui") -> Belum disetujui | E82: SPC011 | F82: TUTOR ANDRI RUDOLOF ELI MANAFE | G82: SPC STARLIGHT | H82: KUPANG
A83: =IFERROR(__xludf.DUMMYFUNCTION("""COMPUTED_VALUE"""),45901.8436855787) -> 45901.844 | B83: =IFERROR(__xludf.DUMMYFUNCTION("""COMPUTED_VALUE"""),"SELVINCE BAKO") -> SELVINCE BAKO | C83: =IFERROR(__xludf.DUMMYFUNCTION("""COMPUTED_VALUE"""),"Belum disetujui") -> Belum disetujui | E83: SPC003 | F83: TUTOR ANDRI RUDOLOF ELI MANAFE | G83: SPC KUANINO | H83: KUPANG
A84: =IFERROR(__xludf.DUMMYFUNCTION("""COMPUTED_VALUE"""),45901.84539569444) -> 45901.845 | B84: =IFERROR(__xludf.DUMMYFUNCTION("""COMPUTED_VALUE"""),"FEBRIANTHY ELISABET NA'U") -> FEBRIANTHY ELISABET NA'U | C84: =IFERROR(__xludf.DUMMYFUNCTION("""COMPUTED_VALUE"""),"Belum disetujui") -> Belum disetujui | E84: SPC011 | F84: TUTOR ANDRI RUDOLOF ELI MANAFE | G84: SPC STARLIGHT | H84: KUPANG
A85: =IFERROR(__xludf.DUMMYFUNCTION("""COMPUTED_VALUE"""),45901.84898120371) -> 45901.849 | B85: =IFERROR(__xludf.DUMMYFUNCTION("""COMPUTED_VALUE"""),"AINI RAHMATINI NATALIA MOESTAKIM") -> AINI RAHMATINI NATALIA MOESTAKIM | C85: =IFERROR(__xludf.DUMMYFUNCTION("""COMPUTED_VALUE"""),"Belum disetujui") -> Belum disetujui | E85: SPC006 | F85: TUTOR ANDRI RUDOLOF ELI MANAFE | G85: SPC OESAPA | H85: KUPANG
A86: =IFERROR(__xludf.DUMMYFUNCTION("""COMPUTED_VALUE"""),45901.84956012731) -> 45901.85 | B86: =IFERROR(__xludf.DUMMYFUNCTION("""COMPUTED_VALUE"""),"NUR FATIMAH MOLBANG") -> NUR FATIMAH MOLBANG | C86: =IFERROR(__xludf.DUMMYFUNCTION("""COMPUTED_VALUE"""),"ACC") -> ACC | D86: =IFERROR(__xludf.DUMMYFUNCTION("""COMPUTED_VALUE"""),"V50 Lite series") -> V50 Lite series | E86: PUT001 | F86: TUTOR LEU ADOLF QICHEN LEI BAIT | G86: PUTRA SULAWESI | H86: KABUPATEN
A87: =IFERROR(__xludf.DUMMYFUNCTION("""COMPUTED_VALUE"""),45901.854148969906) -> 45901.854 | B87: =IFERROR(__xludf.DUMMYFUNCTION("""COMPUTED_VALUE"""),"ALDIANA WELIA PANIE") -> ALDIANA WELIA PANIE | C87: =IFERROR(__xludf.DUMMYFUNCTION("""COMPUTED_VALUE"""),"Belum disetujui") -> Belum disetujui | E87: QIN001 | F87: TUTOR HERY YULIUS DILLAK | G87: QINARA CELL | H87: KABUPATEN
A88: =IFERROR(__xludf.DUMMYFUNCTION("""COMPUTED_VALUE"""),45901.96731184028) -> 45901.967 | B88: =IFERROR(__xludf.DUMMYFUNCTION("""COMPUTED_VALUE"""),"PATRIANI MENGI ULY") -> PATRIANI MENGI ULY | C88: =IFERROR(__xludf.DUMMYFUNCTION("""COMPUTED_VALUE"""),"ACC") -> ACC | D88: =IFERROR(__xludf.DUMMYFUNCTION("""COMPUTED_VALUE"""),"Y400 series") -> Y400 series | E88: SPC004 | F88: TUTOR ANDRI RUDOLOF ELI MANAFE | G88: SPC MASTER CELL | H88: KUPANG
A89: =IFERROR(__xludf.DUMMYFUNCTION("""COMPUTED_VALUE"""),45902.43235957176) -> 45902.432 | B89: =IFERROR(__xludf.DUMMYFUNCTION("""COMPUTED_VALUE"""),"AINI RAHMATINI NATALIA MOESTAKIM") -> AINI RAHMATINI NATALIA MOESTAKIM | C89: =IFERROR(__xludf.DUMMYFUNCTION("""COMPUTED_VALUE"""),"Belum disetujui") -> Belum disetujui | E89: SPC006 | F89: TUTOR ANDRI RUDOLOF ELI MANAFE | G89: SPC OESAPA | H89: KUPANG
A90: =IFERROR(__xludf.DUMMYFUNCTION("""COMPUTED_VALUE"""),45902.437738657405) -> 45902.438 | B90: =IFERROR(__xludf.DUMMYFUNCTION("""COMPUTED_VALUE"""),"EMPI FRANGKI LIEM") -> EMPI FRANGKI LIEM | C90: =IFERROR(__xludf.DUMMYFUNCTION("""COMPUTED_VALUE"""),"Belum disetujui") -> Belum disetujui | E90: MCE001 | F90: TUTOR ANTONIO DE JANAIRO TOMASOEY | G90: MCELL | H90: KUPANG
A91: =IFERROR(__xludf.DUMMYFUNCTION("""COMPUTED_VALUE"""),45902.460727233796) -> 45902.461 | B91: =IFERROR(__xludf.DUMMYFUNCTION("""COMPUTED_VALUE"""),"YASINTHA MBU") -> YASINTHA MBU | C91: =IFERROR(__xludf.DUMMYFUNCTION("""COMPUTED_VALUE"""),"Belum disetujui") -> Belum disetujui | E91: TER001 | F91: TUTOR ANTONIO DE JANAIRO TOMASOEY | G91: TERMINAL HP | H91: KUPANG
A92: =IFERROR(__xludf.DUMMYFUNCTION("""COMPUTED_VALUE"""),45902.46295875) -> 45902.463 | B92: =IFERROR(__xludf.DUMMYFUNCTION("""COMPUTED_VALUE"""),"ROS YANE KANA LUDJI") -> ROS YANE KANA LUDJI | C92: =IFERROR(__xludf.DUMMYFUNCTION("""COMPUTED_VALUE"""),"Belum disetujui") -> Belum disetujui | E92: SPC013 | F92: TUTOR ANDRI RUDOLOF ELI MANAFE | G92: SPC TERMINAL | H92: KUPANG
A93: =IFERROR(__xludf.DUMMYFUNCTION("""COMPUTED_VALUE"""),45902.48496108797) -> 45902.485 | B93: =IFERROR(__xludf.DUMMYFUNCTION("""COMPUTED_VALUE"""),"YASINTHA MBU") -> YASINTHA MBU | C93: =IFERROR(__xludf.DUMMYFUNCTION("""COMPUTED_VALUE"""),"Dapat limit tapi belum diproses") -> Dapat limit tapi belum diproses | D93: =IFERROR(__xludf.DUMMYFUNCTION("""COMPUTED_VALUE"""),"Y400 series") -> Y400 series | E93: TER001 | F93: TUTOR ANTONIO DE JANAIRO TOMASOEY | G93: TERMINAL HP | H93: KUPANG
A94: =IFERROR(__xludf.DUMMYFUNCTION("""COMPUTED_VALUE"""),45902.51811761574) -> 45902.518 | B94: =IFERROR(__xludf.DUMMYFUNCTION("""COMPUTED_VALUE"""),"ADRIANA") -> ADRIANA | C94: =IFERROR(__xludf.DUMMYFUNCTION("""COMPUTED_VALUE"""),"Belum disetujui") -> Belum disetujui | E94: MUT001 | F94: TUTOR LEU ADOLF QICHEN LEI BAIT | G94: MUTIARA CELL | H94: KABUPATEN
A95: =IFERROR(__xludf.DUMMYFUNCTION("""COMPUTED_VALUE"""),45902.5211544676) -> 45902.521 | B95: =IFERROR(__xludf.DUMMYFUNCTION("""COMPUTED_VALUE"""),"WARDIA") -> WARDIA | C95: =IFERROR(__xludf.DUMMYFUNCTION("""COMPUTED_VALUE"""),"Belum disetujui") -> Belum disetujui | E95: SPC006 | F95: TUTOR ANDRI RUDOLOF ELI MANAFE | G95: SPC OESAPA | H95: KUPANG
A96: =IFERROR(__xludf.DUMMYFUNCTION("""COMPUTED_VALUE"""),45902.52319717593) -> 45902.523 | B96: =IFERROR(__xludf.DUMMYFUNCTION("""COMPUTED_VALUE"""),"WARDIA") -> WARDIA | C96: =IFERROR(__xludf.DUMMYFUNCTION("""COMPUTED_VALUE"""),"Belum disetujui") -> Belum disetujui | E96: SPC006 | F96: TUTOR ANDRI RUDOLOF ELI MANAFE | G96: SPC OESAPA | H96: KUPANG
A97: =IFERROR(__xludf.DUMMYFUNCTION("""COMPUTED_VALUE"""),45902.545426805555) -> 45902.545 | B97: =IFERROR(__xludf.DUMMYFUNCTION("""COMPUTED_VALUE"""),"FEBRIANTHY ELISABET NA'U") -> FEBRIANTHY ELISABET NA'U | C97: =IFERROR(__xludf.DUMMYFUNCTION("""COMPUTED_VALUE"""),"Belum disetujui") -> Belum disetujui | E97: SPC011 | F97: TUTOR ANDRI RUDOLOF ELI MANAFE | G97: SPC STARLIGHT | H97: KUPANG
A98: =IFERROR(__xludf.DUMMYFUNCTION("""COMPUTED_VALUE"""),45902.555692581016) -> 45902.556 | B98: =IFERROR(__xludf.DUMMYFUNCTION("""COMPUTED_VALUE"""),"MERDA PUTRI BUNGSU KENAT") -> MERDA PUTRI BUNGSU KENAT | C98: =IFERROR(__xludf.DUMMYFUNCTION("""COMPUTED_VALUE"""),"Dapat limit tapi belum diproses") -> Dapat limit tapi belum diproses | D98: =IFERROR(__xludf.DUMMYFUNCTION("""COMPUTED_VALUE"""),"Y29 series") -> Y29 series | E98: QIN001 | F98: TUTOR HERY YULIUS DILLAK | G98: QINARA CELL | H98: KABUPATEN
A99: =IFERROR(__xludf.DUMMYFUNCTION("""COMPUTED_VALUE"""),45902.55781012731) -> 45902.558 | B99: =IFERROR(__xludf.DUMMYFUNCTION("""COMPUTED_VALUE"""),"MERDA PUTRI BUNGSU KENAT") -> MERDA PUTRI BUNGSU KENAT | C99: =IFERROR(__xludf.DUMMYFUNCTION("""COMPUTED_VALUE"""),"Belum disetujui") -> Belum disetujui | E99: QIN001 | F99: TUTOR HERY YULIUS DILLAK | G99: QINARA CELL | H99: KABUPATEN
A100: =IFERROR(__xludf.DUMMYFUNCTION("""COMPUTED_VALUE"""),45902.562344363425) -> 45902.562 | B100: =IFERROR(__xludf.DUMMYFUNCTION("""COMPUTED_VALUE"""),"SELVINCE BAKO") -> SELVINCE BAKO | C100: =IFERROR(__xludf.DUMMYFUNCTION("""COMPUTED_VALUE"""),"Belum disetujui") -> Belum disetujui | E100: SPC003 | F100: TUTOR ANDRI RUDOLOF ELI MANAFE | G100: SPC KUANINO | H100: KUPANG
...

Sheet Database Promotor
A1: ID Promotor | B1: Promotor | C1: Sator | D1: Target Pengajuan | E1: ID Toko Penempatan
A2: DEW001 | B2: DEWI RAHMAN | C2: TUTOR YACOB CHRISTIAN BOLING | D2: 48 | E2: TIM001
A3: ISW001 | B3: ISWAN ASAMAU | C3: TUTOR YACOB CHRISTIAN BOLING | D3: 48 | E3: NAB001
A4: KAM001 | B4: KAMARIA ANDI BASO | C4: TUTOR YACOB CHRISTIAN BOLING | D4: 48 | E4: FAT001
A5: MEL001 | B5: MELIYANI RATNASARI SYUKRI | C5: TUTOR YACOB CHRISTIAN BOLING | D5: 48 | E5: PRI001 | G5: area kabupaten
A6: ABB001 | B6: ANGELA BOUKA BERI | C6: TUTOR YACOB CHRISTIAN BOLING | D6: 48 | E6: PRI001
A7: ARF001 | B7: ANNA RAHMATIA JUFRI | C7: TUTOR YACOB CHRISTIAN BOLING | D7: 48 | E7: BGD001
A8: PRE001 | B8: PRETI SISILIA SILA | C8: TUTOR MARSELUS M LAMBO | D8: 48 | E8: SPC009 | G8: TUTOR YACOB CHRISTIAN BOLING
A9: YUT001 | B9: YUNITA TAMELAB | C9: TUTOR MARSELUS M LAMBO | D9: 48 | E9: SRI001
A10: ADR004 | B10: ADRIANA | C10: TUTOR LEU ADOLF QICHEN LEI BAIT | D10: 48 | E10: MUT001 | G10: TUTOR LEU ADOLF QICHEN LEI BAIT
A11: BER001 | B11: BERGITHA NIA OLIN | C11: TUTOR LEU ADOLF QICHEN LEI BAIT | D11: 48 | E11: INF001 | G11: TUTOR HERY YULIUS DILLAK
A12: MAR002 | B12: MARIA DENTIANA L HAUMETAN | C12: TUTOR LEU ADOLF QICHEN LEI BAIT | D12: 48 | E12: KER001 | G12: SPV WILIBRODUS R MANEK SAMARA
A13: ATM001 | B13: ARMINDA TEKU MANEK | C13: TUTOR LEU ADOLF QICHEN LEI BAIT | D13: 48 | E13: SPC014
A14: NUR001 | B14: NUR FATIMAH MOLBANG | C14: TUTOR LEU ADOLF QICHEN LEI BAIT | D14: 48 | E14: PUT001
A15: MIN001 | B15: MARIA ISABELA NONIS | C15: TUTOR LEU ADOLF QICHEN LEI BAIT | D15: 48 | E15: MAR001
A16: ALI001 | B16: ALITA D PAU | C16: TUTOR KUSMYATI KILIMANDU | D16: 48 | E16: GLO001 | G16: area kota kupang
A17: AMB001 | B17: AMBU BAIQ JUMENAH | C17: TUTOR KUSMYATI KILIMANDU | D17: 48 | E17: SAC001 | G17: TUTOR ANTONIO DE JANAIRO TOMASOEY
A18: ANI001 | B18: ANITA ANA AMAH | C18: TUTOR KUSMYATI KILIMANDU | D18: 48 | E18: QUE001 | G18: TUTOR ANDRI RUDOLOF ELI MANAFE
A19: NOV001 | B19: NOVLIANA BARBALINA MISA | C19: TUTOR KUSMYATI KILIMANDU | D19: 48 | E19: GLO003
A20: YER001 | B20: YEREMIAS MBAWA KANJAPI | C20: TUTOR KUSMYATI KILIMANDU | D20: 48 | E20: GLO001 | G20: area sumba
A21: YOV001 | B21: YOVANDA KATRINA NAE | C21: TUTOR KUSMYATI KILIMANDU | D21: 48 | E21: QUE001 | G21: SPV ANFAL JUPRIADI AMBU WARU
A22: ASR001 | B22: ASRI NINGSI RAMBU ATA ENDI | C22: TUTOR KUSMYATI KILIMANDU | D22: 48 | E22: SPC010
A23: EST001 | B23: ESTER LUDJI | C23: TUTOR KUSMYATI KILIMANDU | D23: 48 | E23: SPC010
A24: AGW001 | B24: ANAK AGUNG SRI WULANTIWI | C24: TUTOR KUSMYATI KILIMANDU | D24: 48 | E24: DCE001
A25: HER001 | B25: HERONIMUS NAMU WALI | C25: TUTOR KUSMYATI KILIMANDU | D25: 48 | E25: SRT001
A26: ALD001 | B26: ALDIANA WELIA PANIE | C26: TUTOR HERY YULIUS DILLAK | D26: 48 | E26: QIN001
A27: ELI001 | B27: LINDA MELSIANA ELLO | C27: TUTOR HERY YULIUS DILLAK | D27: 48 | E27: AND001
A28: MAR001 | B28: MARATHA MARLINDA FANGGIDAE | C28: TUTOR HERY YULIUS DILLAK | D28: 48 | E28: AND001
A29: EME001 | B29: MERDA PUTRI BUNGSU KENAT | C29: TUTOR HERY YULIUS DILLAK | D29: 48 | E29: QIN001
A30: YRM001 | B30: ANYARMITHA SOPHIA SUEK | C30: TUTOR ANTONIO DE JANAIRO TOMASOEY | D30: 48 | E30: CEL001
A31: DWI001 | B31: DWITNEY PRETY WANGGANDIMA | C31: TUTOR ANTONIO DE JANAIRO TOMASOEY | D31: 48 | E31: CEL001
A32: EFL001 | B32: EMPI FRANGKI LIEM | C32: TUTOR ANTONIO DE JANAIRO TOMASOEY | D32: 48 | E32: MCE001
A33: FER001 | B33: FERI ELI KURNIAWAN | C33: TUTOR ANTONIO DE JANAIRO TOMASOEY | D33: 48 | E33: PLA001
... A73: AST001 | B73: ASTUTI BELA WAWO | C73: SPV ANFAL JUPRIADI AMBU WARU | D73: 48 | E73: GLO002

Sheet Database Toko
A1: ID Toko | B1: Nama Toko | C1: Area | D1: Area Detail
A2: ALI001 | B2: ALIONG CELL | C2: PULAU SUMBA | D2: SUMBA
A3: AND001 | B3: ANDYS CELL | C3: PULAU TIMOR | D3: KABUPATEN
A4: AZI001 | B4: AZIZAH CELL | C4: PULAU SUMBA | D4: SUMBA
A5: CEL001 | B5: CELLULER WORLD | C5: PULAU TIMOR | D5: KUPANG
A6: FAT001 | B6: FATIMA CELL | C6: PULAU TIMOR | D6: KABUPATEN
A7: GAR001 | B7: GARUDA CELL | C7: PULAU TIMOR | D7: KABUPATEN
A8: GIS001 | B8: GISMCELL | C8: PULAU SUMBA | D8: SUMBA
A9: GLO001 | B9: GLOBAL TEKNIK 1 | C9: PULAU SUMBA | D9: SUMBA
A10: GLO002 | B10: GLOBAL TEKNIK 2 | C10: PULAU SUMBA | D10: SUMBA
A11: GLO003 | B11: GLOBAL TEKNIK 3 | C11: PULAU SUMBA | D11: SUMBA
A12: GLO004 | B12: GLOBAL TEKNIK 4 | C12: PULAU SUMBA | D12: SUMBA
... A57: DCE001 | B57: DCELL | C57: PULAU SUMBA | D57: SUMBA

Sheet Data Penjualan Bersih
A1: Timestamp | B1: Nama Promotor | C1: Status | D1: Tipe hp | E1: ID Toko | F1: Sator | G1: Area
A2: =IFERROR(__xludf.DUMMYFUNCTION("LET( data_range, 'Master Data All'!A2:X1499, first_day, EOMONTH(TODAY(),-1)+1, stack, { IFERROR(QUERY(data_range, ""SELECT A, P, I, M WHERE P IS NOT NULL AND A IS NOT NULL"")); IFERROR(QUERY(data_range, ""SELECT A, Q, I, M WHERE Q IS NOT NU"&"LL AND A IS NOT NULL"")); IFERROR(QUERY(data_range, ""SELECT A, R, I, M WHERE R IS NOT NULL AND A IS NOT NULL"")); IFERROR(QUERY(data_range, ""SELECT A, S, I, M WHERE S IS NOT NULL AND A IS NOT NULL"")); IFERROR(QUERY(data_range, ""SELECT A, T"&", I, M WHERE T IS NOT NULL AND A IS NOT NULL"")); IFERROR(QUERY(data_range, ""SELECT A, U, I, M WHERE U IS NOT NULL AND A IS NOT NULL"")); IFERROR(QUERY(data_range, ""SELECT A, V, I, M WHERE V IS NOT NULL AND A IS NOT NULL"")); IFERROR(QUERY(d"&"ata_range, ""SELECT A, W, I, M WHERE W IS NOT NULL AND A IS NOT NULL"")); IFERROR(QUERY(data_range, ""SELECT A, X, I, M WHERE X IS NOT NULL AND A IS NOT NULL"")) }, SORT( FILTER( stack, INDEX(stack, 0, 1) >= first_day ), 1, "&"TRUE) )"),45992.000220925926) -> 45992 | B2: =IFERROR(__xludf.DUMMYFUNCTION("""COMPUTED_VALUE"""),"ROS YANE KANA LUDJI") -> ROS YANE KANA LUDJI | C2: =IFERROR(__xludf.DUMMYFUNCTION("""COMPUTED_VALUE"""),"Belum disetujui") -> Belum disetujui | E2: {=IF(B2:B1499="", "", IFNA( VLOOKUP( UPPER(TRIM(B2:B1499)), {UPPER(TRIM('Database Promotor'!B2:B1499)), 'Database Promotor'!E2:E1499}, 2, FALSE ), "Promotor Tidak Ditemukan" ) )} -> SPC013 | F2: {=IF(B2:B1499="",, IFERROR(VLOOKUP(B2:B1499, {'Database Promotor'!B:B , 'Database Promotor'!C:C}, 2, FALSE), "Sator Tdk Ditemukan"))} -> TUTOR ANDRI RUDOLOF ELI MANAFE | G2: {=IF(E2:E1499="", "", IFNA( VLOOKUP(UPPER(TRIM(E2:E1499)), {UPPER(TRIM('Database Toko'!A2:A499)), 'Database Toko'!D2:D499}, 2, FALSE ), "Detail Tdk Ditemukan" ) )} -> KUPANG
A3: =IFERROR(__xludf.DUMMYFUNCTION("""COMPUTED_VALUE"""),45992.39247590278) -> 45992.392 | B3: =IFERROR(__xludf.DUMMYFUNCTION("""COMPUTED_VALUE"""),"MARNITHA JUWIKE TIMORATI RUNESI") -> MARNITHA JUWIKE TIMORATI RUNESI | C3: =IFERROR(__xludf.DUMMYFUNCTION("""COMPUTED_VALUE"""),"Belum disetujui") -> Belum disetujui | E3: SPC005 | F3: TUTOR ANDRI RUDOLOF ELI MANAFE | G3: KUPANG
A4: =IFERROR(__xludf.DUMMYFUNCTION("""COMPUTED_VALUE"""),45992.41216761574) -> 45992.412 | B4: =IFERROR(__xludf.DUMMYFUNCTION("""COMPUTED_VALUE"""),"ROS YANE KANA LUDJI") -> ROS YANE KANA LUDJI | C4: =IFERROR(__xludf.DUMMYFUNCTION("""COMPUTED_VALUE"""),"Belum disetujui") -> Belum disetujui | E4: SPC013 | F4: TUTOR ANDRI RUDOLOF ELI MANAFE | G4: KUPANG
A5: =IFERROR(__xludf.DUMMYFUNCTION("""COMPUTED_VALUE"""),45992.42242364584) -> 45992.422 | B5: =IFERROR(__xludf.DUMMYFUNCTION("""COMPUTED_VALUE"""),"ANDHIKA ULLY") -> ANDHIKA ULLY | C5: =IFERROR(__xludf.DUMMYFUNCTION("""COMPUTED_VALUE"""),"Belum disetujui") -> Belum disetujui | E5: ERA001 | F5: TUTOR ANTONIO DE JANAIRO TOMASOEY | G5: KUPANG
A6: =IFERROR(__xludf.DUMMYFUNCTION("""COMPUTED_VALUE"""),45992.42366331018) -> 45992.424 | B6: =IFERROR(__xludf.DUMMYFUNCTION("""COMPUTED_VALUE"""),"MARNITHA JUWIKE TIMORATI RUNESI") -> MARNITHA JUWIKE TIMORATI RUNESI | C6: =IFERROR(__xludf.DUMMYFUNCTION("""COMPUTED_VALUE"""),"Belum disetujui") -> Belum disetujui | E6: SPC005 | F6: TUTOR ANDRI RUDOLOF ELI MANAFE | G6: KUPANG
A7: =IFERROR(__xludf.DUMMYFUNCTION("""COMPUTED_VALUE"""),45992.43756385417) -> 45992.438 | B7: =IFERROR(__xludf.DUMMYFUNCTION("""COMPUTED_VALUE"""),"AINI RAHMATINI NATALIA MOESTAKIM") -> AINI RAHMATINI NATALIA MOESTAKIM | C7: =IFERROR(__xludf.DUMMYFUNCTION("""COMPUTED_VALUE"""),"Dapat limit tapi belum diproses") -> Dapat limit tapi belum diproses | D7: =IFERROR(__xludf.DUMMYFUNCTION("""COMPUTED_VALUE"""),"Y21d series") -> Y21d series | E7: SPC006 | F7: TUTOR ANDRI RUDOLOF ELI MANAFE | G7: KUPANG
A8: =IFERROR(__xludf.DUMMYFUNCTION("""COMPUTED_VALUE"""),45992.46769275463) -> 45992.468 | B8: =IFERROR(__xludf.DUMMYFUNCTION("""COMPUTED_VALUE"""),"EMPI FRANGKI LIEM") -> EMPI FRANGKI LIEM | C8: =IFERROR(__xludf.DUMMYFUNCTION("""COMPUTED_VALUE"""),"Belum disetujui") -> Belum disetujui | E8: MCE001 | F8: TUTOR ANTONIO DE JANAIRO TOMASOEY | G8: KUPANG
A9: =IFERROR(__xludf.DUMMYFUNCTION("""COMPUTED_VALUE"""),45992.50544042824) -> 45992.505 | B9: =IFERROR(__xludf.DUMMYFUNCTION("""COMPUTED_VALUE"""),"YENDRI ELISHABET BERELOE") -> YENDRI ELISHABET BERELOE | C9: =IFERROR(__xludf.DUMMYFUNCTION("""COMPUTED_VALUE"""),"Belum disetujui") -> Belum disetujui | E9: SCO001 | F9: TUTOR ANTONIO DE JANAIRO TOMASOEY | G9: KUPANG
A10: =IFERROR(__xludf.DUMMYFUNCTION("""COMPUTED_VALUE"""),45992.564250324074) -> 45992.564 | B10: =IFERROR(__xludf.DUMMYFUNCTION("""COMPUTED_VALUE"""),"ANNA RAHMATIA JUFRI") -> ANNA RAHMATIA JUFRI | C10: =IFERROR(__xludf.DUMMYFUNCTION("""COMPUTED_VALUE"""),"Belum disetujui") -> Belum disetujui | E10: BGD001 | F10: TUTOR YACOB CHRISTIAN BOLING | G10: KABUPATEN
A11: =IFERROR(__xludf.DUMMYFUNCTION("""COMPUTED_VALUE"""),45992.568997662034) -> 45992.569 | B11: =IFERROR(__xludf.DUMMYFUNCTION("""COMPUTED_VALUE"""),"SANTI MARIA LUKMINI NAHAK") -> SANTI MARIA LUKMINI NAHAK | C11: =IFERROR(__xludf.DUMMYFUNCTION("""COMPUTED_VALUE"""),"Belum disetujui") -> Belum disetujui | E11: PKR001 | F11: SPV WILIBRODUS R MANEK SAMARA | G11: KABUPATEN
A12: =IFERROR(__xludf.DUMMYFUNCTION("""COMPUTED_VALUE"""),45992.56975221065) -> 45992.57 | B12: =IFERROR(__xludf.DUMMYFUNCTION("""COMPUTED_VALUE"""),"RESTIANY MARIA LUAN KALI") -> RESTIANY MARIA LUAN KALI | C12: =IFERROR(__xludf.DUMMYFUNCTION("""COMPUTED_VALUE"""),"Belum disetujui") -> Belum disetujui | E12: SPC007 | F12: TUTOR ANDRI RUDOLOF ELI MANAFE | G12: KUPANG
A13: =IFERROR(__xludf.DUMMYFUNCTION("""COMPUTED_VALUE"""),45992.575315960654) -> 45992.575 | B13: =IFERROR(__xludf.DUMMYFUNCTION("""COMPUTED_VALUE"""),"NUR FATIMAH MOLBANG") -> NUR FATIMAH MOLBANG | C13: =IFERROR(__xludf.DUMMYFUNCTION("""COMPUTED_VALUE"""),"Belum disetujui") -> Belum disetujui | E13: PUT001 | F13: TUTOR LEU ADOLF QICHEN LEI BAIT | G13: KABUPATEN
A14: =IFERROR(__xludf.DUMMYFUNCTION("""COMPUTED_VALUE"""),45992.5792065162) -> 45992.579 | B14: =IFERROR(__xludf.DUMMYFUNCTION("""COMPUTED_VALUE"""),"NUR FATIMAH MOLBANG") -> NUR FATIMAH MOLBANG | C14: =IFERROR(__xludf.DUMMYFUNCTION("""COMPUTED_VALUE"""),"Belum disetujui") -> Belum disetujui | E14: PUT001 | F14: TUTOR LEU ADOLF QICHEN LEI BAIT | G14: KABUPATEN
A15: =IFERROR(__xludf.DUMMYFUNCTION("""COMPUTED_VALUE"""),45992.583182372684) -> 45992.583 | B15: =IFERROR(__xludf.DUMMYFUNCTION("""COMPUTED_VALUE"""),"PATRIANI MENGI ULY") -> PATRIANI MENGI ULY | C15: =IFERROR(__xludf.DUMMYFUNCTION("""COMPUTED_VALUE"""),"Belum disetujui") -> Belum disetujui | E15: SPC004 | F15: TUTOR ANDRI RUDOLOF ELI MANAFE | G15: KUPANG
A16: =IFERROR(__xludf.DUMMYFUNCTION("""COMPUTED_VALUE"""),45992.60638649306) -> 45992.606 | B16: =IFERROR(__xludf.DUMMYFUNCTION("""COMPUTED_VALUE"""),"BERGITHA NIA OLIN") -> BERGITHA NIA OLIN | C16: =IFERROR(__xludf.DUMMYFUNCTION("""COMPUTED_VALUE"""),"Belum disetujui") -> Belum disetujui | E16: INF001 | F16: TUTOR LEU ADOLF QICHEN LEI BAIT | G16: KABUPATEN
A17: =IFERROR(__xludf.DUMMYFUNCTION("""COMPUTED_VALUE"""),45992.61478524306) -> 45992.615 | B17: =IFERROR(__xludf.DUMMYFUNCTION("""COMPUTED_VALUE"""),"YENDRI ELISHABET BERELOE") -> YENDRI ELISHABET BERELOE | C17: =IFERROR(__xludf.DUMMYFUNCTION("""COMPUTED_VALUE"""),"Dapat limit tapi belum diproses") -> Dapat limit tapi belum diproses | D17: =IFERROR(__xludf.DUMMYFUNCTION("""COMPUTED_VALUE"""),"Y21d series") -> Y21d series | E17: SCO001 | F17: TUTOR ANTONIO DE JANAIRO TOMASOEY | G17: KUPANG
A18: =IFERROR(__xludf.DUMMYFUNCTION("""COMPUTED_VALUE"""),45992.67328905092) -> 45992.673 | B18: =IFERROR(__xludf.DUMMYFUNCTION("""COMPUTED_VALUE"""),"NABILA RAHMAWATI") -> NABILA RAHMAWATI | C18: =IFERROR(__xludf.DUMMYFUNCTION("""COMPUTED_VALUE"""),"Belum disetujui") -> Belum disetujui | E18: AZI001 | F18: SPV ANFAL JUPRIADI AMBU WARU | G18: SUMBA
A19: =IFERROR(__xludf.DUMMYFUNCTION("""COMPUTED_VALUE"""),45992.728126319445) -> 45992.728 | B19: =IFERROR(__xludf.DUMMYFUNCTION("""COMPUTED_VALUE"""),"WARDIA") -> WARDIA | C19: =IFERROR(__xludf.DUMMYFUNCTION("""COMPUTED_VALUE"""),"Belum disetujui") -> Belum disetujui | E19: SPC006 | F19: TUTOR ANDRI RUDOLOF ELI MANAFE | G19: KUPANG
A20: =IFERROR(__xludf.DUMMYFUNCTION("""COMPUTED_VALUE"""),45992.74368403935) -> 45992.744 | B20: =IFERROR(__xludf.DUMMYFUNCTION("""COMPUTED_VALUE"""),"ESTER LUDJI") -> ESTER LUDJI | C20: =IFERROR(__xludf.DUMMYFUNCTION("""COMPUTED_VALUE"""),"ACC") -> ACC | D20: =IFERROR(__xludf.DUMMYFUNCTION("""COMPUTED_VALUE"""),"Y21d series") -> Y21d series | E20: SPC010 | F20: TUTOR KUSMYATI KILIMANDU | G20: SUMBA
A21: =IFERROR(__xludf.DUMMYFUNCTION("""COMPUTED_VALUE"""),45992.767859479165) -> 45992.768 | B21: =IFERROR(__xludf.DUMMYFUNCTION("""COMPUTED_VALUE"""),"ESTER LUDJI") -> ESTER LUDJI | C21: =IFERROR(__xludf.DUMMYFUNCTION("""COMPUTED_VALUE"""),"Belum disetujui") -> Belum disetujui | E21: SPC010 | F21: TUTOR KUSMYATI KILIMANDU | G21: SUMBA
A22: =IFERROR(__xludf.DUMMYFUNCTION("""COMPUTED_VALUE"""),45992.77763405093) -> 45992.778 | B22: =IFERROR(__xludf.DUMMYFUNCTION("""COMPUTED_VALUE"""),"ASRI NINGSI RAMBU ATA ENDI") -> ASRI NINGSI RAMBU ATA ENDI | C22: =IFERROR(__xludf.DUMMYFUNCTION("""COMPUTED_VALUE"""),"Dapat limit tapi belum diproses") -> Dapat limit tapi belum diproses | D22: =IFERROR(__xludf.DUMMYFUNCTION("""COMPUTED_VALUE"""),"Y400 series") -> Y400 series | E22: SPC010 | F22: TUTOR KUSMYATI KILIMANDU | G22: SUMBA
A23: =IFERROR(__xludf.DUMMYFUNCTION("""COMPUTED_VALUE"""),45992.77939128473) -> 45992.779 | B23: =IFERROR(__xludf.DUMMYFUNCTION("""COMPUTED_VALUE"""),"ROS YANE KANA LUDJI") -> ROS YANE KANA LUDJI | C23: =IFERROR(__xludf.DUMMYFUNCTION("""COMPUTED_VALUE"""),"Belum disetujui") -> Belum disetujui | E23: SPC013 | F23: TUTOR ANDRI RUDOLOF ELI MANAFE | G23: KUPANG
A24: =IFERROR(__xludf.DUMMYFUNCTION("""COMPUTED_VALUE"""),45992.78130732638) -> 45992.781 | B24: =IFERROR(__xludf.DUMMYFUNCTION("""COMPUTED_VALUE"""),"BERGITHA NIA OLIN") -> BERGITHA NIA OLIN | C24: =IFERROR(__xludf.DUMMYFUNCTION("""COMPUTED_VALUE"""),"ACC") -> ACC | D24: =IFERROR(__xludf.DUMMYFUNCTION("""COMPUTED_VALUE"""),"V60 Lite series") -> V60 Lite series | E24: INF001 | F24: TUTOR LEU ADOLF QICHEN LEI BAIT | G24: KABUPATEN
A25: =IFERROR(__xludf.DUMMYFUNCTION("""COMPUTED_VALUE"""),45992.796267280086) -> 45992.796 | B25: =IFERROR(__xludf.DUMMYFUNCTION("""COMPUTED_VALUE"""),"SANTI MARIA LUKMINI NAHAK") -> SANTI MARIA LUKMINI NAHAK | C25: =IFERROR(__xludf.DUMMYFUNCTION("""COMPUTED_VALUE"""),"Belum disetujui") -> Belum disetujui | E25: PKR001 | F25: SPV WILIBRODUS R MANEK SAMARA | G25: KABUPATEN
A26: =IFERROR(__xludf.DUMMYFUNCTION("""COMPUTED_VALUE"""),45992.819738726845) -> 45992.82 | B26: =IFERROR(__xludf.DUMMYFUNCTION("""COMPUTED_VALUE"""),"YOVANDA KATRINA NAE") -> YOVANDA KATRINA NAE | C26: =IFERROR(__xludf.DUMMYFUNCTION("""COMPUTED_VALUE"""),"Belum disetujui") -> Belum disetujui | E26: QUE001 | F26: TUTOR KUSMYATI KILIMANDU | G26: SUMBA
A27: =IFERROR(__xludf.DUMMYFUNCTION("""COMPUTED_VALUE"""),45992.83968498843) -> 45992.84 | B27: =IFERROR(__xludf.DUMMYFUNCTION("""COMPUTED_VALUE"""),"WINDRI MANOE") -> WINDRI MANOE | C27: =IFERROR(__xludf.DUMMYFUNCTION("""COMPUTED_VALUE"""),"Belum disetujui") -> Belum disetujui | E27: CEL001 | F27: TUTOR ANTONIO DE JANAIRO TOMASOEY | G27: KUPANG
A28: =IFERROR(__xludf.DUMMYFUNCTION("""COMPUTED_VALUE"""),45992.840489166665) -> 45992.84 | B28: =IFERROR(__xludf.DUMMYFUNCTION("""COMPUTED_VALUE"""),"WINDRI MANOE") -> WINDRI MANOE | C28: =IFERROR(__xludf.DUMMYFUNCTION("""COMPUTED_VALUE"""),"Belum disetujui") -> Belum disetujui | E28: CEL001 | F28: TUTOR ANTONIO DE JANAIRO TOMASOEY | G28: KUPANG
A29: =IFERROR(__xludf.DUMMYFUNCTION("""COMPUTED_VALUE"""),45992.85128471065) -> 45992.851 | B29: =IFERROR(__xludf.DUMMYFUNCTION("""COMPUTED_VALUE"""),"DWITNEY PRETY WANGGANDIMA") -> DWITNEY PRETY WANGGANDIMA | C29: =IFERROR(__xludf.DUMMYFUNCTION("""COMPUTED_VALUE"""),"Belum disetujui") -> Belum disetujui | E29: CEL001 | F29: TUTOR ANTONIO DE JANAIRO TOMASOEY | G29: KUPANG
A30: =IFERROR(__xludf.DUMMYFUNCTION("""COMPUTED_VALUE"""),45992.85280275463) -> 45992.853 | B30: =IFERROR(__xludf.DUMMYFUNCTION("""COMPUTED_VALUE"""),"DWITNEY PRETY WANGGANDIMA") -> DWITNEY PRETY WANGGANDIMA | C30: =IFERROR(__xludf.DUMMYFUNCTION("""COMPUTED_VALUE"""),"Belum disetujui") -> Belum disetujui | E30: CEL001 | F30: TUTOR ANTONIO DE JANAIRO TOMASOEY | G30: KUPANG
A31: =IFERROR(__xludf.DUMMYFUNCTION("""COMPUTED_VALUE"""),45992.866584537034) -> 45992.867 | B31: =IFERROR(__xludf.DUMMYFUNCTION("""COMPUTED_VALUE"""),"YOVANDA KATRINA NAE") -> YOVANDA KATRINA NAE | C31: =IFERROR(__xludf.DUMMYFUNCTION("""COMPUTED_VALUE"""),"ACC") -> ACC | D31: =IFERROR(__xludf.DUMMYFUNCTION("""COMPUTED_VALUE"""),"Y21d series") -> Y21d series | E31: QUE001 | F31: TUTOR KUSMYATI KILIMANDU | G31: SUMBA
A32: =IFERROR(__xludf.DUMMYFUNCTION("""COMPUTED_VALUE"""),45992.90303767362) -> 45992.903 | B32: =IFERROR(__xludf.DUMMYFUNCTION("""COMPUTED_VALUE"""),"HERONIMUS NAMU WALI") -> HERONIMUS NAMU WALI | C32: =IFERROR(__xludf.DUMMYFUNCTION("""COMPUTED_VALUE"""),"ACC") -> ACC | D32: =IFERROR(__xludf.DUMMYFUNCTION("""COMPUTED_VALUE"""),"Y21d series") -> Y21d series | E32: SRT001 | F32: TUTOR KUSMYATI KILIMANDU | G32: SUMBA
A33: =IFERROR(__xludf.DUMMYFUNCTION("""COMPUTED_VALUE"""),45992.90552940972) -> 45992.906 | B33: =IFERROR(__xludf.DUMMYFUNCTION("""COMPUTED_VALUE"""),"HERONIMUS NAMU WALI") -> HERONIMUS NAMU WALI | C33: =IFERROR(__xludf.DUMMYFUNCTION("""COMPUTED_VALUE"""),"Belum disetujui") -> Belum disetujui | E33: SRT001 | F33: TUTOR KUSMYATI KILIMANDU | G33: SUMBA
A34: =IFERROR(__xludf.DUMMYFUNCTION("""COMPUTED_VALUE"""),45993.40507277778) -> 45993.405 | B34: =IFERROR(__xludf.DUMMYFUNCTION("""COMPUTED_VALUE"""),"AZ ZAHRA SITI ZAINAB") -> AZ ZAHRA SITI ZAINAB | C34: =IFERROR(__xludf.DUMMYFUNCTION("""COMPUTED_VALUE"""),"Belum disetujui") -> Belum disetujui | E34: PIT001 | F34: SPV ANFAL JUPRIADI AMBU WARU | G34: SUMBA
A35: =IFERROR(__xludf.DUMMYFUNCTION("""COMPUTED_VALUE"""),45993.41075219907) -> 45993.411 | B35: =IFERROR(__xludf.DUMMYFUNCTION("""COMPUTED_VALUE"""),"YUNITA TAMELAB") -> YUNITA TAMELAB | C35: =IFERROR(__xludf.DUMMYFUNCTION("""COMPUTED_VALUE"""),"Belum disetujui") -> Belum disetujui | E35: SRI001 | F35: TUTOR MARSELUS M LAMBO | G35: KABUPATEN
A36: =IFERROR(__xludf.DUMMYFUNCTION("""COMPUTED_VALUE"""),45993.416915821756) -> 45993.417 | B36: =IFERROR(__xludf.DUMMYFUNCTION("""COMPUTED_VALUE"""),"PUSPA ANGGREINI") -> PUSPA ANGGREINI | C36: =IFERROR(__xludf.DUMMYFUNCTION("""COMPUTED_VALUE"""),"Dapat limit tapi belum diproses") -> Dapat limit tapi belum diproses | D36: =IFERROR(__xludf.DUMMYFUNCTION("""COMPUTED_VALUE"""),"Y21d series") -> Y21d series | E36: GLO002 | F36: SPV ANFAL JUPRIADI AMBU WARU | G36: SUMBA
A37: =IFERROR(__xludf.DUMMYFUNCTION("""COMPUTED_VALUE"""),45993.43785559028) -> 45993.438 | B37: =IFERROR(__xludf.DUMMYFUNCTION("""COMPUTED_VALUE"""),"ASTUTI BELA WAWO") -> ASTUTI BELA WAWO | C37: =IFERROR(__xludf.DUMMYFUNCTION("""COMPUTED_VALUE"""),"Belum disetujui") -> Belum disetujui | E37: GLO002 | F37: SPV ANFAL JUPRIADI AMBU WARU | G37: SUMBA
A38: =IFERROR(__xludf.DUMMYFUNCTION("""COMPUTED_VALUE"""),45993.43924400463) -> 45993.439 | B38: =IFERROR(__xludf.DUMMYFUNCTION("""COMPUTED_VALUE"""),"ASTUTI BELA WAWO") -> ASTUTI BELA WAWO | C38: =IFERROR(__xludf.DUMMYFUNCTION("""COMPUTED_VALUE"""),"Belum disetujui") -> Belum disetujui | E38: GLO002 | F38: SPV ANFAL JUPRIADI AMBU WARU | G38: SUMBA
A39: =IFERROR(__xludf.DUMMYFUNCTION("""COMPUTED_VALUE"""),45993.440446458335) -> 45993.44 | B39: =IFERROR(__xludf.DUMMYFUNCTION("""COMPUTED_VALUE"""),"ASTUTI BELA WAWO") -> ASTUTI BELA WAWO | C39: =IFERROR(__xludf.DUMMYFUNCTION("""COMPUTED_VALUE"""),"Belum disetujui") -> Belum disetujui | E39: GLO002 | F39: SPV ANFAL JUPRIADI AMBU WARU | G39: SUMBA
A40: =IFERROR(__xludf.DUMMYFUNCTION("""COMPUTED_VALUE"""),45993.47803436343) -> 45993.478 | B40: =IFERROR(__xludf.DUMMYFUNCTION("""COMPUTED_VALUE"""),"PRETI SISILIA SILA") -> PRETI SISILIA SILA | C40: =IFERROR(__xludf.DUMMYFUNCTION("""COMPUTED_VALUE"""),"Dapat limit tapi belum diproses") -> Dapat limit tapi belum diproses | D40: =IFERROR(__xludf.DUMMYFUNCTION("""COMPUTED_VALUE"""),"Y21d series") -> Y21d series | E40: SPC009 | F40: TUTOR MARSELUS M LAMBO | G40: KABUPATEN
A41: =IFERROR(__xludf.DUMMYFUNCTION("""COMPUTED_VALUE"""),45993.49545135416) -> 45993.495 | B41: =IFERROR(__xludf.DUMMYFUNCTION("""COMPUTED_VALUE"""),"MARATHA MARLINDA FANGGIDAE") -> MARATHA MARLINDA FANGGIDAE | C41: =IFERROR(__xludf.DUMMYFUNCTION("""COMPUTED_VALUE"""),"Dapat limit tapi belum diproses") -> Dapat limit tapi belum diproses | D41: =IFERROR(__xludf.DUMMYFUNCTION("""COMPUTED_VALUE"""),"Y21d series") -> Y21d series | E41: AND001 | F41: TUTOR HERY YULIUS DILLAK | G41: KABUPATEN
A42: =IFERROR(__xludf.DUMMYFUNCTION("""COMPUTED_VALUE"""),45993.49679296297) -> 45993.497 | B42: =IFERROR(__xludf.DUMMYFUNCTION("""COMPUTED_VALUE"""),"NOVLIANA BARBALINA MISA") -> NOVLIANA BARBALINA MISA | C42: =IFERROR(__xludf.DUMMYFUNCTION("""COMPUTED_VALUE"""),"Belum disetujui") -> Belum disetujui | E42: GLO003 | F42: TUTOR KUSMYATI KILIMANDU | G42: SUMBA
A43: =IFERROR(__xludf.DUMMYFUNCTION("""COMPUTED_VALUE"""),45993.50505728009) -> 45993.505 | B43: =IFERROR(__xludf.DUMMYFUNCTION("""COMPUTED_VALUE"""),"MARIA MELAN ANANCE BILI") -> MARIA MELAN ANANCE BILI | C43: =IFERROR(__xludf.DUMMYFUNCTION("""COMPUTED_VALUE"""),"Belum disetujui") -> Belum disetujui | E43: SOC002 | F43: SPV ANFAL JUPRIADI AMBU WARU | G43: SUMBA
A44: =IFERROR(__xludf.DUMMYFUNCTION("""COMPUTED_VALUE"""),45993.522510324074) -> 45993.523 | B44: =IFERROR(__xludf.DUMMYFUNCTION("""COMPUTED_VALUE"""),"ANDHIKA ULLY") -> ANDHIKA ULLY | C44: =IFERROR(__xludf.DUMMYFUNCTION("""COMPUTED_VALUE"""),"Belum disetujui") -> Belum disetujui | E44: ERA001 | F44: TUTOR ANTONIO DE JANAIRO TOMASOEY | G44: KUPANG
A45: =IFERROR(__xludf.DUMMYFUNCTION("""COMPUTED_VALUE"""),45993.53238291667) -> 45993.532 | B45: =IFERROR(__xludf.DUMMYFUNCTION("""COMPUTED_VALUE"""),"NOVLIANA BARBALINA MISA") -> NOVLIANA BARBALINA MISA | C45: =IFERROR(__xludf.DUMMYFUNCTION("""COMPUTED_VALUE"""),"Dapat limit tapi belum diproses") -> Dapat limit tapi belum diproses | D45: =IFERROR(__xludf.DUMMYFUNCTION("""COMPUTED_VALUE"""),"Y21d series") -> Y21d series | E45: GLO003 | F45: TUTOR KUSMYATI KILIMANDU | G45: SUMBA
A46: =IFERROR(__xludf.DUMMYFUNCTION("""COMPUTED_VALUE"""),45993.53481921297) -> 45993.535 | B46: =IFERROR(__xludf.DUMMYFUNCTION("""COMPUTED_VALUE"""),"IDMAL YUSDIRAN YUSUF") -> IDMAL YUSDIRAN YUSUF | C46: =IFERROR(__xludf.DUMMYFUNCTION("""COMPUTED_VALUE"""),"Belum disetujui") -> Belum disetujui | E46: KHA002 | F46: SPV ANFAL JUPRIADI AMBU WARU | G46: SUMBA
A47: =IFERROR(__xludf.DUMMYFUNCTION("""COMPUTED_VALUE"""),45993.544780335644) -> 45993.545 | B47: =IFERROR(__xludf.DUMMYFUNCTION("""COMPUTED_VALUE"""),"ROS YANE KANA LUDJI") -> ROS YANE KANA LUDJI | C47: =IFERROR(__xludf.DUMMYFUNCTION("""COMPUTED_VALUE"""),"Belum disetujui") -> Belum disetujui | E47: SPC013 | F47: TUTOR ANDRI RUDOLOF ELI MANAFE | G47: KUPANG
A48: =IFERROR(__xludf.DUMMYFUNCTION("""COMPUTED_VALUE"""),45993.54682649305) -> 45993.547 | B48: =IFERROR(__xludf.DUMMYFUNCTION("""COMPUTED_VALUE"""),"SANTI MARIA LUKMINI NAHAK") -> SANTI MARIA LUKMINI NAHAK | C48: =IFERROR(__xludf.DUMMYFUNCTION("""COMPUTED_VALUE"""),"Belum disetujui") -> Belum disetujui | E48: PKR001 | F48: SPV WILIBRODUS R MANEK SAMARA | G48: KABUPATEN
A49: =IFERROR(__xludf.DUMMYFUNCTION("""COMPUTED_VALUE"""),45993.54807872685) -> 45993.548 | B49: =IFERROR(__xludf.DUMMYFUNCTION("""COMPUTED_VALUE"""),"ROS YANE KANA LUDJI") -> ROS YANE KANA LUDJI | C49: =IFERROR(__xludf.DUMMYFUNCTION("""COMPUTED_VALUE"""),"Belum disetujui") -> Belum disetujui | E49: SPC013 | F49: TUTOR ANDRI RUDOLOF ELI MANAFE | G49: KUPANG
A50: =IFERROR(__xludf.DUMMYFUNCTION("""COMPUTED_VALUE"""),45993.55046239583) -> 45993.55 | B50: =IFERROR(__xludf.DUMMYFUNCTION("""COMPUTED_VALUE"""),"MARNITHA JUWIKE TIMORATI RUNESI") -> MARNITHA JUWIKE TIMORATI RUNESI | C50: =IFERROR(__xludf.DUMMYFUNCTION("""COMPUTED_VALUE"""),"Belum disetujui") -> Belum disetujui | E50: SPC005 | F50: TUTOR ANDRI RUDOLOF ELI MANAFE | G50: KUPANG
A51: =IFERROR(__xludf.DUMMYFUNCTION("""COMPUTED_VALUE"""),45993.554693541664) -> 45993.555 | B51: =IFERROR(__xludf.DUMMYFUNCTION("""COMPUTED_VALUE"""),"ASRI NINGSI RAMBU ATA ENDI") -> ASRI NINGSI RAMBU ATA ENDI | C51: =IFERROR(__xludf.DUMMYFUNCTION("""COMPUTED_VALUE"""),"Belum disetujui") -> Belum disetujui | E51: SPC010 | F51: TUTOR KUSMYATI KILIMANDU | G51: SUMBA
A52: =IFERROR(__xludf.DUMMYFUNCTION("""COMPUTED_VALUE"""),45993.65028991898) -> 45993.65 | B52: =IFERROR(__xludf.DUMMYFUNCTION("""COMPUTED_VALUE"""),"NOVLIANA BARBALINA MISA") -> NOVLIANA BARBALINA MISA | C52: =IFERROR(__xludf.DUMMYFUNCTION("""COMPUTED_VALUE"""),"ACC") -> ACC | D52: =IFERROR(__xludf.DUMMYFUNCTION("""COMPUTED_VALUE"""),"Y21d series") -> Y21d series | E52: GLO003 | F52: TUTOR KUSMYATI KILIMANDU | G52: SUMBA
A53: =IFERROR(__xludf.DUMMYFUNCTION("""COMPUTED_VALUE"""),45993.66795928241) -> 45993.668 | B53: =IFERROR(__xludf.DUMMYFUNCTION("""COMPUTED_VALUE"""),"ASRI NINGSI RAMBU ATA ENDI") -> ASRI NINGSI RAMBU ATA ENDI | C53: =IFERROR(__xludf.DUMMYFUNCTION("""COMPUTED_VALUE"""),"Belum disetujui") -> Belum disetujui | E53: SPC010 | F53: TUTOR KUSMYATI KILIMANDU | G53: SUMBA
A54: =IFERROR(__xludf.DUMMYFUNCTION("""COMPUTED_VALUE"""),45993.69571012732) -> 45993.696 | B54: =IFERROR(__xludf.DUMMYFUNCTION("""COMPUTED_VALUE"""),"NUR FATIMAH MOLBANG") -> NUR FATIMAH MOLBANG | C54: =IFERROR(__xludf.DUMMYFUNCTION("""COMPUTED_VALUE"""),"ACC") -> ACC | D54: =IFERROR(__xludf.DUMMYFUNCTION("""COMPUTED_VALUE"""),"Y21d series") -> Y21d series | E54: PUT001 | F54: TUTOR LEU ADOLF QICHEN LEI BAIT | G54: KABUPATEN
A55: =IFERROR(__xludf.DUMMYFUNCTION("""COMPUTED_VALUE"""),45993.69793998842) -> 45993.698 | B55: =IFERROR(__xludf.DUMMYFUNCTION("""COMPUTED_VALUE"""),"NUR FATIMAH MOLBANG") -> NUR FATIMAH MOLBANG | C55: =IFERROR(__xludf.DUMMYFUNCTION("""COMPUTED_VALUE"""),"ACC") -> ACC | D55: =IFERROR(__xludf.DUMMYFUNCTION("""COMPUTED_VALUE"""),"Y21d series") -> Y21d series | E55: PUT001 | F55: TUTOR LEU ADOLF QICHEN LEI BAIT | G55: KABUPATEN
A56: =IFERROR(__xludf.DUMMYFUNCTION("""COMPUTED_VALUE"""),45993.69931180555) -> 45993.699 | B56: =IFERROR(__xludf.DUMMYFUNCTION("""COMPUTED_VALUE"""),"WINDRI MANOE") -> WINDRI MANOE | C56: =IFERROR(__xludf.DUMMYFUNCTION("""COMPUTED_VALUE"""),"Belum disetujui") -> Belum disetujui | E56: CEL001 | F56: TUTOR ANTONIO DE JANAIRO TOMASOEY | G56: KUPANG
A57: =IFERROR(__xludf.DUMMYFUNCTION("""COMPUTED_VALUE"""),45993.70677390046) -> 45993.707 | B57: =IFERROR(__xludf.DUMMYFUNCTION("""COMPUTED_VALUE"""),"SULIS NURAINI INSYATUN") -> SULIS NURAINI INSYATUN | C57: =IFERROR(__xludf.DUMMYFUNCTION("""COMPUTED_VALUE"""),"Belum disetujui") -> Belum disetujui | E57: KHA001 | F57: SPV ANFAL JUPRIADI AMBU WARU | G57: SUMBA
A58: =IFERROR(__xludf.DUMMYFUNCTION("""COMPUTED_VALUE"""),45993.724381273154) -> 45993.724 | B58: =IFERROR(__xludf.DUMMYFUNCTION("""COMPUTED_VALUE"""),"ASRI NINGSI RAMBU ATA ENDI") -> ASRI NINGSI RAMBU ATA ENDI | C58: =IFERROR(__xludf.DUMMYFUNCTION("""COMPUTED_VALUE"""),"Belum disetujui") -> Belum disetujui | E58: SPC010 | F58: TUTOR KUSMYATI KILIMANDU | G58: SUMBA
A59: =IFERROR(__xludf.DUMMYFUNCTION("""COMPUTED_VALUE"""),45993.728520543984) -> 45993.729 | B59: =IFERROR(__xludf.DUMMYFUNCTION("""COMPUTED_VALUE"""),"ESTER LUDJI") -> ESTER LUDJI | C59: =IFERROR(__xludf.DUMMYFUNCTION("""COMPUTED_VALUE"""),"Belum disetujui") -> Belum disetujui | E59: SPC010 | F59: TUTOR KUSMYATI KILIMANDU | G59: SUMBA
A60: =IFERROR(__xludf.DUMMYFUNCTION("""COMPUTED_VALUE"""),45993.73269866898) -> 45993.733 | B60: =IFERROR(__xludf.DUMMYFUNCTION("""COMPUTED_VALUE"""),"NOVLIANA BARBALINA MISA") -> NOVLIANA BARBALINA MISA | C60: =IFERROR(__xludf.DUMMYFUNCTION("""COMPUTED_VALUE"""),"ACC") -> ACC | D60: =IFERROR(__xludf.DUMMYFUNCTION("""COMPUTED_VALUE"""),"Y21d series") -> Y21d series | E60: GLO003 | F60: TUTOR KUSMYATI KILIMANDU | G60: SUMBA
A61: =IFERROR(__xludf.DUMMYFUNCTION("""COMPUTED_VALUE"""),45993.741195787035) -> 45993.741 | B61: =IFERROR(__xludf.DUMMYFUNCTION("""COMPUTED_VALUE"""),"WARDIA") -> WARDIA | C61: =IFERROR(__xludf.DUMMYFUNCTION("""COMPUTED_VALUE"""),"Belum disetujui") -> Belum disetujui | E61: SPC006 | F61: TUTOR ANDRI RUDOLOF ELI MANAFE | G61: KUPANG
A62: =IFERROR(__xludf.DUMMYFUNCTION("""COMPUTED_VALUE"""),45993.7423109375) -> 45993.742 | B62: =IFERROR(__xludf.DUMMYFUNCTION("""COMPUTED_VALUE"""),"MARNITHA JUWIKE TIMORATI RUNESI") -> MARNITHA JUWIKE TIMORATI RUNESI | C62: =IFERROR(__xludf.DUMMYFUNCTION("""COMPUTED_VALUE"""),"ACC") -> ACC | D62: =IFERROR(__xludf.DUMMYFUNCTION("""COMPUTED_VALUE"""),"Y21d series") -> Y21d series | E62: SPC005 | F62: TUTOR ANDRI RUDOLOF ELI MANAFE | G62: KUPANG
A63: =IFERROR(__xludf.DUMMYFUNCTION("""COMPUTED_VALUE"""),45993.75063717592) -> 45993.751 | B63: =IFERROR(__xludf.DUMMYFUNCTION("""COMPUTED_VALUE"""),"NENY MERLIANTI NA'U") -> NENY MERLIANTI NA'U | C63: =IFERROR(__xludf.DUMMYFUNCTION("""COMPUTED_VALUE"""),"Dapat limit tapi belum diproses") -> Dapat limit tapi belum diproses | D63: =IFERROR(__xludf.DUMMYFUNCTION("""COMPUTED_VALUE"""),"Y21d series") -> Y21d series | E63: SPC008 | F63: TUTOR ANDRI RUDOLOF ELI MANAFE | G63: KUPANG
A64: =IFERROR(__xludf.DUMMYFUNCTION("""COMPUTED_VALUE"""),45993.770085069445) -> 45993.77 | B64: =IFERROR(__xludf.DUMMYFUNCTION("""COMPUTED_VALUE"""),"YOVANDA KATRINA NAE") -> YOVANDA KATRINA NAE | C64: =IFERROR(__xludf.DUMMYFUNCTION("""COMPUTED_VALUE"""),"Belum disetujui") -> Belum disetujui | E64: QUE001 | F64: TUTOR KUSMYATI KILIMANDU | G64: SUMBA
A65: =IFERROR(__xludf.DUMMYFUNCTION("""COMPUTED_VALUE"""),45993.77797498842) -> 45993.778 | B65: =IFERROR(__xludf.DUMMYFUNCTION("""COMPUTED_VALUE"""),"YOVANDA KATRINA NAE") -> YOVANDA KATRINA NAE | C65: =IFERROR(__xludf.DUMMYFUNCTION("""COMPUTED_VALUE"""),"Belum disetujui") -> Belum disetujui | E65: QUE001 | F65: TUTOR KUSMYATI KILIMANDU | G65: SUMBA
A66: =IFERROR(__xludf.DUMMYFUNCTION("""COMPUTED_VALUE"""),45993.78051347222) -> 45993.781 | B66: =IFERROR(__xludf.DUMMYFUNCTION("""COMPUTED_VALUE"""),"ANYARMITHA SOPHIA SUEK") -> ANYARMITHA SOPHIA SUEK | C66: =IFERROR(__xludf.DUMMYFUNCTION("""COMPUTED_VALUE"""),"Belum disetujui") -> Belum disetujui | E66: CEL001 | F66: TUTOR ANTONIO DE JANAIRO TOMASOEY | G66: KUPANG
A67: =IFERROR(__xludf.DUMMYFUNCTION("""COMPUTED_VALUE"""),45993.78811693287) -> 45993.788 | B67: =IFERROR(__xludf.DUMMYFUNCTION("""COMPUTED_VALUE"""),"ASTUTI BELA WAWO") -> ASTUTI BELA WAWO | C67: =IFERROR(__xludf.DUMMYFUNCTION("""COMPUTED_VALUE"""),"Dapat limit tapi belum diproses") -> Dapat limit tapi belum diproses | D67: =IFERROR(__xludf.DUMMYFUNCTION("""COMPUTED_VALUE"""),"Y21d series") -> Y21d series | E67: GLO002 | F67: SPV ANFAL JUPRIADI AMBU WARU | G67: SUMBA
A68: =IFERROR(__xludf.DUMMYFUNCTION("""COMPUTED_VALUE"""),45993.80144224537) -> 45993.801 | B68: =IFERROR(__xludf.DUMMYFUNCTION("""COMPUTED_VALUE"""),"AZ ZAHRA SITI ZAINAB") -> AZ ZAHRA SITI ZAINAB | C68: =IFERROR(__xludf.DUMMYFUNCTION("""COMPUTED_VALUE"""),"Belum disetujui") -> Belum disetujui | E68: PIT001 | F68: SPV ANFAL JUPRIADI AMBU WARU | G68: SUMBA
A69: =IFERROR(__xludf.DUMMYFUNCTION("""COMPUTED_VALUE"""),45993.812384212964) -> 45993.812 | B69: =IFERROR(__xludf.DUMMYFUNCTION("""COMPUTED_VALUE"""),"IRENE NOVALIA KADJU") -> IRENE NOVALIA KADJU | C69: =IFERROR(__xludf.DUMMYFUNCTION("""COMPUTED_VALUE"""),"Belum disetujui") -> Belum disetujui | E69: SPC012 | F69: TUTOR ANDRI RUDOLOF ELI MANAFE | G69: KUPANG
A70: =IFERROR(__xludf.DUMMYFUNCTION("""COMPUTED_VALUE"""),45993.814452673614) -> 45993.814 | B70: =IFERROR(__xludf.DUMMYFUNCTION("""COMPUTED_VALUE"""),"PRETI SISILIA SILA") -> PRETI SISILIA SILA | C70: =IFERROR(__xludf.DUMMYFUNCTION("""COMPUTED_VALUE"""),"Dapat limit tapi belum diproses") -> Dapat limit tapi belum diproses | D70: =IFERROR(__xludf.DUMMYFUNCTION("""COMPUTED_VALUE"""),"V60 series") -> V60 series | E70: SPC009 | F70: TUTOR MARSELUS M LAMBO | G70: KABUPATEN
A71: =IFERROR(__xludf.DUMMYFUNCTION("""COMPUTED_VALUE"""),45993.837161180556) -> 45993.837 | B71: =IFERROR(__xludf.DUMMYFUNCTION("""COMPUTED_VALUE"""),"ADRIANA") -> ADRIANA | C71: =IFERROR(__xludf.DUMMYFUNCTION("""COMPUTED_VALUE"""),"Dapat limit tapi belum diproses") -> Dapat limit tapi belum diproses | D71: =IFERROR(__xludf.DUMMYFUNCTION("""COMPUTED_VALUE"""),"Y21d series") -> Y21d series | E71: MUT001 | F71: TUTOR LEU ADOLF QICHEN LEI BAIT | G71: KABUPATEN
A72: =IFERROR(__xludf.DUMMYFUNCTION("""COMPUTED_VALUE"""),45993.845966863424) -> 45993.846 | B72: =IFERROR(__xludf.DUMMYFUNCTION("""COMPUTED_VALUE"""),"MARIA MELAN ANANCE BILI") -> MARIA MELAN ANANCE BILI | C72: =IFERROR(__xludf.DUMMYFUNCTION("""COMPUTED_VALUE"""),"ACC") -> ACC | D72: =IFERROR(__xludf.DUMMYFUNCTION("""COMPUTED_VALUE"""),"V60 Lite series") -> V60 Lite series | E72: SOC002 | F72: SPV ANFAL JUPRIADI AMBU WARU | G72: SUMBA
A73: =IFERROR(__xludf.DUMMYFUNCTION("""COMPUTED_VALUE"""),45993.8541271412) -> 45993.854 | B73: =IFERROR(__xludf.DUMMYFUNCTION("""COMPUTED_VALUE"""),"NUR FATIMAH MOLBANG") -> NUR FATIMAH MOLBANG | C73: =IFERROR(__xludf.DUMMYFUNCTION("""COMPUTED_VALUE"""),"Belum disetujui") -> Belum disetujui | E73: PUT001 | F73: TUTOR LEU ADOLF QICHEN LEI BAIT | G73: KABUPATEN
A74: =IFERROR(__xludf.DUMMYFUNCTION("""COMPUTED_VALUE"""),45993.91202762732) -> 45993.912 | B74: =IFERROR(__xludf.DUMMYFUNCTION("""COMPUTED_VALUE"""),"ESTER LUDJI") -> ESTER LUDJI | C74: =IFERROR(__xludf.DUMMYFUNCTION("""COMPUTED_VALUE"""),"ACC") -> ACC | D74: =IFERROR(__xludf.DUMMYFUNCTION("""COMPUTED_VALUE"""),"Y400 series") -> Y400 series | E74: SPC010 | F74: TUTOR KUSMYATI KILIMANDU | G74: SUMBA
A75: =IFERROR(__xludf.DUMMYFUNCTION("""COMPUTED_VALUE"""),45993.94131409722) -> 45993.941 | B75: =IFERROR(__xludf.DUMMYFUNCTION("""COMPUTED_VALUE"""),"SANTI MARIA LUKMINI NAHAK") -> SANTI MARIA LUKMINI NAHAK | C75: =IFERROR(__xludf.DUMMYFUNCTION("""COMPUTED_VALUE"""),"Belum disetujui") -> Belum disetujui | E75: PKR001 | F75: SPV WILIBRODUS R MANEK SAMARA | G75: KABUPATEN
A76: =IFERROR(__xludf.DUMMYFUNCTION("""COMPUTED_VALUE"""),45994.42721375) -> 45994.427 | B76: =IFERROR(__xludf.DUMMYFUNCTION("""COMPUTED_VALUE"""),"MARIA MELAN ANANCE BILI") -> MARIA MELAN ANANCE BILI | C76: =IFERROR(__xludf.DUMMYFUNCTION("""COMPUTED_VALUE"""),"Belum disetujui") -> Belum disetujui | E76: SOC002 | F76: SPV ANFAL JUPRIADI AMBU WARU | G76: SUMBA
A77: =IFERROR(__xludf.DUMMYFUNCTION("""COMPUTED_VALUE"""),45994.428609675924) -> 45994.429 | B77: =IFERROR(__xludf.DUMMYFUNCTION("""COMPUTED_VALUE"""),"MARIA MELAN ANANCE BILI") -> MARIA MELAN ANANCE BILI | C77: =IFERROR(__xludf.DUMMYFUNCTION("""COMPUTED_VALUE"""),"Belum disetujui") -> Belum disetujui | E77: SOC002 | F77: SPV ANFAL JUPRIADI AMBU WARU | G77: SUMBA
A78: =IFERROR(__xludf.DUMMYFUNCTION("""COMPUTED_VALUE"""),45994.42870438657) -> 45994.429 | B78: =IFERROR(__xludf.DUMMYFUNCTION("""COMPUTED_VALUE"""),"PRETI SISILIA SILA") -> PRETI SISILIA SILA | C78: =IFERROR(__xludf.DUMMYFUNCTION("""COMPUTED_VALUE"""),"Belum disetujui") -> Belum disetujui | E78: SPC009 | F78: TUTOR MARSELUS M LAMBO | G78: KABUPATEN
A79: =IFERROR(__xludf.DUMMYFUNCTION("""COMPUTED_VALUE"""),45994.43426706018) -> 45994.434 | B79: =IFERROR(__xludf.DUMMYFUNCTION("""COMPUTED_VALUE"""),"YUNITA TAMELAB") -> YUNITA TAMELAB | C79: =IFERROR(__xludf.DUMMYFUNCTION("""COMPUTED_VALUE"""),"Belum disetujui") -> Belum disetujui | E79: SRI001 | F79: TUTOR MARSELUS M LAMBO | G79: KABUPATEN
A80: =IFERROR(__xludf.DUMMYFUNCTION("""COMPUTED_VALUE"""),45994.46554200232) -> 45994.466 | B80: =IFERROR(__xludf.DUMMYFUNCTION("""COMPUTED_VALUE"""),"NOVANTRY RUTHANIA NAFFIE") -> NOVANTRY RUTHANIA NAFFIE | C80: =IFERROR(__xludf.DUMMYFUNCTION("""COMPUTED_VALUE"""),"Belum disetujui") -> Belum disetujui | E80: MCE001 | F80: TUTOR ANTONIO DE JANAIRO TOMASOEY | G80: KUPANG
A81: =IFERROR(__xludf.DUMMYFUNCTION("""COMPUTED_VALUE"""),45994.46812059028) -> 45994.468 | B81: =IFERROR(__xludf.DUMMYFUNCTION("""COMPUTED_VALUE"""),"FEBRIANTHY ELISABET NA'U") -> FEBRIANTHY ELISABET NA'U | C81: =IFERROR(__xludf.DUMMYFUNCTION("""COMPUTED_VALUE"""),"Belum disetujui") -> Belum disetujui | E81: SPC011 | F81: TUTOR ANDRI RUDOLOF ELI MANAFE | G81: KUPANG
A82: =IFERROR(__xludf.DUMMYFUNCTION("""COMPUTED_VALUE"""),45994.48669936343) -> 45994.487 | B82: =IFERROR(__xludf.DUMMYFUNCTION("""COMPUTED_VALUE"""),"AZ ZAHRA SITI ZAINAB") -> AZ ZAHRA SITI ZAINAB | C82: =IFERROR(__xludf.DUMMYFUNCTION("""COMPUTED_VALUE"""),"ACC") -> ACC | D82: =IFERROR(__xludf.DUMMYFUNCTION("""COMPUTED_VALUE"""),"Y400 series") -> Y400 series | E82: PIT001 | F82: SPV ANFAL JUPRIADI AMBU WARU | G82: SUMBA
A83: =IFERROR(__xludf.DUMMYFUNCTION("""COMPUTED_VALUE"""),45994.48809438658) -> 45994.488 | B83: =IFERROR(__xludf.DUMMYFUNCTION("""COMPUTED_VALUE"""),"ROS YANE KANA LUDJI") -> ROS YANE KANA LUDJI | C83: =IFERROR(__xludf.DUMMYFUNCTION("""COMPUTED_VALUE"""),"Belum disetujui") -> Belum disetujui | E83: SPC013 | F83: TUTOR ANDRI RUDOLOF ELI MANAFE | G83: KUPANG
A84: =IFERROR(__xludf.DUMMYFUNCTION("""COMPUTED_VALUE"""),45994.497347476856) -> 45994.497 | B84: =IFERROR(__xludf.DUMMYFUNCTION("""COMPUTED_VALUE"""),"KESIA NATALIA I. BENU") -> KESIA NATALIA I. BENU | C84: =IFERROR(__xludf.DUMMYFUNCTION("""COMPUTED_VALUE"""),"ACC") -> ACC | D84: =IFERROR(__xludf.DUMMYFUNCTION("""COMPUTED_VALUE"""),"Y400 series") -> Y400 series | E84: KHA002 | F84: SPV ANFAL JUPRIADI AMBU WARU | G84: SUMBA
A85: =IFERROR(__xludf.DUMMYFUNCTION("""COMPUTED_VALUE"""),45994.50929259259) -> 45994.509 | B85: =IFERROR(__xludf.DUMMYFUNCTION("""COMPUTED_VALUE"""),"NABILA RAHMAWATI") -> NABILA RAHMAWATI | C85: =IFERROR(__xludf.DUMMYFUNCTION("""COMPUTED_VALUE"""),"Belum disetujui") -> Belum disetujui | E85: AZI001 | F85: SPV ANFAL JUPRIADI AMBU WARU | G85: SUMBA
A86: =IFERROR(__xludf.DUMMYFUNCTION("""COMPUTED_VALUE"""),45994.51020031251) -> 45994.51 | B86: =IFERROR(__xludf.DUMMYFUNCTION("""COMPUTED_VALUE"""),"ASTUTI BELA WAWO") -> ASTUTI BELA WAWO | C86: =IFERROR(__xludf.DUMMYFUNCTION("""COMPUTED_VALUE"""),"Dapat limit tapi belum diproses") -> Dapat limit tapi belum diproses | D86: =IFERROR(__xludf.DUMMYFUNCTION("""COMPUTED_VALUE"""),"Y21d series") -> Y21d series | E86: GLO002 | F86: SPV ANFAL JUPRIADI AMBU WARU | G86: SUMBA
A87: =IFERROR(__xludf.DUMMYFUNCTION("""COMPUTED_VALUE"""),45994.513593692136) -> 45994.514 | B87: =IFERROR(__xludf.DUMMYFUNCTION("""COMPUTED_VALUE"""),"ALDIANA WELIA PANIE") -> ALDIANA WELIA PANIE | C87: =IFERROR(__xludf.DUMMYFUNCTION("""COMPUTED_VALUE"""),"Belum disetujui") -> Belum disetujui | E87: QIN001 | F87: TUTOR HERY YULIUS DILLAK | G87: KABUPATEN
A88: =IFERROR(__xludf.DUMMYFUNCTION("""COMPUTED_VALUE"""),45994.51465967592) -> 45994.515 | B88: =IFERROR(__xludf.DUMMYFUNCTION("""COMPUTED_VALUE"""),"RESTIANY MARIA LUAN KALI") -> RESTIANY MARIA LUAN KALI | C88: =IFERROR(__xludf.DUMMYFUNCTION("""COMPUTED_VALUE"""),"Belum disetujui") -> Belum disetujui | E88: SPC007 | F88: TUTOR ANDRI RUDOLOF ELI MANAFE | G88: KUPANG
A89: =IFERROR(__xludf.DUMMYFUNCTION("""COMPUTED_VALUE"""),45994.51734414352) -> 45994.517 | B89: =IFERROR(__xludf.DUMMYFUNCTION("""COMPUTED_VALUE"""),"BERGITHA NIA OLIN") -> BERGITHA NIA OLIN | C89: =IFERROR(__xludf.DUMMYFUNCTION("""COMPUTED_VALUE"""),"Belum disetujui") -> Belum disetujui | E89: INF001 | F89: TUTOR LEU ADOLF QICHEN LEI BAIT | G89: KABUPATEN
A90: =IFERROR(__xludf.DUMMYFUNCTION("""COMPUTED_VALUE"""),45994.53813782408) -> 45994.538 | B90: =IFERROR(__xludf.DUMMYFUNCTION("""COMPUTED_VALUE"""),"ANYARMITHA SOPHIA SUEK") -> ANYARMITHA SOPHIA SUEK | C90: =IFERROR(__xludf.DUMMYFUNCTION("""COMPUTED_VALUE"""),"Belum disetujui") -> Belum disetujui | E90: CEL001 | F90: TUTOR ANTONIO DE JANAIRO TOMASOEY | G90: KUPANG
A91: =IFERROR(__xludf.DUMMYFUNCTION("""COMPUTED_VALUE"""),45994.54844388889) -> 45994.548 | B91: =IFERROR(__xludf.DUMMYFUNCTION("""COMPUTED_VALUE"""),"YASINTHA MBU") -> YASINTHA MBU | C91: =IFERROR(__xludf.DUMMYFUNCTION("""COMPUTED_VALUE"""),"Belum disetujui") -> Belum disetujui | E91: TER001 | F91: TUTOR ANTONIO DE JANAIRO TOMASOEY | G91: KUPANG
A92: =IFERROR(__xludf.DUMMYFUNCTION("""COMPUTED_VALUE"""),45994.577952210646) -> 45994.578 | B92: =IFERROR(__xludf.DUMMYFUNCTION("""COMPUTED_VALUE"""),"ASTUTI BELA WAWO") -> ASTUTI BELA WAWO | C92: =IFERROR(__xludf.DUMMYFUNCTION("""COMPUTED_VALUE"""),"Belum disetujui") -> Belum disetujui | E92: GLO002 | F92: SPV ANFAL JUPRIADI AMBU WARU | G92: SUMBA
A93: =IFERROR(__xludf.DUMMYFUNCTION("""COMPUTED_VALUE"""),45994.58770231482) -> 45994.588 | B93: =IFERROR(__xludf.DUMMYFUNCTION("""COMPUTED_VALUE"""),"YUNITA TAMELAB") -> YUNITA TAMELAB | C93: =IFERROR(__xludf.DUMMYFUNCTION("""COMPUTED_VALUE"""),"Belum disetujui") -> Belum disetujui | E93: SRI001 | F93: TUTOR MARSELUS M LAMBO | G93: KABUPATEN
A94: =IFERROR(__xludf.DUMMYFUNCTION("""COMPUTED_VALUE"""),45994.59161390046) -> 45994.592 | B94: =IFERROR(__xludf.DUMMYFUNCTION("""COMPUTED_VALUE"""),"ANYARMITHA SOPHIA SUEK") -> ANYARMITHA SOPHIA SUEK | C94: =IFERROR(__xludf.DUMMYFUNCTION("""COMPUTED_VALUE"""),"Belum disetujui") -> Belum disetujui | E94: CEL001 | F94: TUTOR ANTONIO DE JANAIRO TOMASOEY | G94: KUPANG
A95: =IFERROR(__xludf.DUMMYFUNCTION("""COMPUTED_VALUE"""),45994.60704673611) -> 45994.607 | B95: =IFERROR(__xludf.DUMMYFUNCTION("""COMPUTED_VALUE"""),"ADRIANA") -> ADRIANA | C95: =IFERROR(__xludf.DUMMYFUNCTION("""COMPUTED_VALUE"""),"Belum disetujui") -> Belum disetujui | E95: MUT001 | F95: TUTOR LEU ADOLF QICHEN LEI BAIT | G95: KABUPATEN
A96: =IFERROR(__xludf.DUMMYFUNCTION("""COMPUTED_VALUE"""),45994.60910775463) -> 45994.609 | B96: =IFERROR(__xludf.DUMMYFUNCTION("""COMPUTED_VALUE"""),"ADRIANA") -> ADRIANA | C96: =IFERROR(__xludf.DUMMYFUNCTION("""COMPUTED_VALUE"""),"Belum disetujui") -> Belum disetujui | E96: MUT001 | F96: TUTOR LEU ADOLF QICHEN LEI BAIT | G96: KABUPATEN
A97: =IFERROR(__xludf.DUMMYFUNCTION("""COMPUTED_VALUE"""),45994.61069847223) -> 45994.611 | B97: =IFERROR(__xludf.DUMMYFUNCTION("""COMPUTED_VALUE"""),"ADRIANA") -> ADRIANA | C97: =IFERROR(__xludf.DUMMYFUNCTION("""COMPUTED_VALUE"""),"Dapat limit tapi belum diproses") -> Dapat limit tapi belum diproses | D97: =IFERROR(__xludf.DUMMYFUNCTION("""COMPUTED_VALUE"""),"Y21d series") -> Y21d series | E97: MUT001 | F97: TUTOR LEU ADOLF QICHEN LEI BAIT | G97: KABUPATEN
A98: =IFERROR(__xludf.DUMMYFUNCTION("""COMPUTED_VALUE"""),45994.61302736111) -> 45994.613 | B98: =IFERROR(__xludf.DUMMYFUNCTION("""COMPUTED_VALUE"""),"ASRI NINGSI RAMBU ATA ENDI") -> ASRI NINGSI RAMBU ATA ENDI | C98: =IFERROR(__xludf.DUMMYFUNCTION("""COMPUTED_VALUE"""),"ACC") -> ACC | D98: =IFERROR(__xludf.DUMMYFUNCTION("""COMPUTED_VALUE"""),"Y21d series") -> Y21d series | E98: SPC010 | F98: TUTOR KUSMYATI KILIMANDU | G98: SUMBA
A99: =IFERROR(__xludf.DUMMYFUNCTION("""COMPUTED_VALUE"""),45994.62247973379) -> 45994.622 | B99: =IFERROR(__xludf.DUMMYFUNCTION("""COMPUTED_VALUE"""),"SANTI MARIA LUKMINI NAHAK") -> SANTI MARIA LUKMINI NAHAK | C99: =IFERROR(__xludf.DUMMYFUNCTION("""COMPUTED_VALUE"""),"Dapat limit tapi belum diproses") -> Dapat limit tapi belum diproses | D99: =IFERROR(__xludf.DUMMYFUNCTION("""COMPUTED_VALUE"""),"Y400 series") -> Y400 series | E99: PKR001 | F99: SPV WILIBRODUS R MANEK SAMARA | G99: KABUPATEN
A100: =IFERROR(__xludf.DUMMYFUNCTION("""COMPUTED_VALUE"""),45994.625472280095) -> 45994.625 | B100: =IFERROR(__xludf.DUMMYFUNCTION("""COMPUTED_VALUE"""),"NABILA RAHMAWATI") -> NABILA RAHMAWATI | C100: =IFERROR(__xludf.DUMMYFUNCTION("""COMPUTED_VALUE"""),"Dapat limit tapi belum diproses") -> Dapat limit tapi belum diproses | D100: =IFERROR(__xludf.DUMMYFUNCTION("""COMPUTED_VALUE"""),"Y21d series") -> Y21d series | E100: AZI001 | F100: SPV ANFAL JUPRIADI AMBU WARU | G100: SUMBA
...

Sheet Data Gabungan Timor Sumba
A1: Timestamp | B1: Nama Promotor | C1: Status | D1: Tipe hp
A2: =IFERROR(__xludf.DUMMYFUNCTION("LET( data_range, 'Master Data All'!A2:X1501, first_day, EOMONTH(TODAY(),-1)+1, stack, { IFERROR(QUERY(data_range, ""SELECT A, P, I, M WHERE P IS NOT NULL AND A IS NOT NULL"")); IFERROR(QUERY(data_range, ""SELECT A, Q, I, M WHERE Q IS NOT NU"&"LL AND A IS NOT NULL"")); IFERROR(QUERY(data_range, ""SELECT A, R, I, M WHERE R IS NOT NULL AND A IS NOT NULL"")); IFERROR(QUERY(data_range, ""SELECT A, S, I, M WHERE S IS NOT NULL AND A IS NOT NULL"")); IFERROR(QUERY(data_range, ""SELECT A, T"&", I, M WHERE T IS NOT NULL AND A IS NOT NULL"")); IFERROR(QUERY(data_range, ""SELECT A, U, I, M WHERE U IS NOT NULL AND A IS NOT NULL"")); IFERROR(QUERY(data_range, ""SELECT A, V, I, M WHERE V IS NOT NULL AND A IS NOT NULL"")); IFERROR(QUERY(d"&"ata_range, ""SELECT A, W, I, M WHERE W IS NOT NULL AND A IS NOT NULL"")); IFERROR(QUERY(data_range, ""SELECT A, X, I, M WHERE X IS NOT NULL AND A IS NOT NULL"")) }, SORT( FILTER( stack, INDEX(stack, 0, 1) >= first_day ), 1, "&"TRUE) )"),45992.000220925926) -> 45992 | B2: =IFERROR(__xludf.DUMMYFUNCTION("""COMPUTED_VALUE"""),"ROS YANE KANA LUDJI") -> ROS YANE KANA LUDJI | C2: =IFERROR(__xludf.DUMMYFUNCTION("""COMPUTED_VALUE"""),"Belum disetujui") -> Belum disetujui
A3: =IFERROR(__xludf.DUMMYFUNCTION("""COMPUTED_VALUE"""),45992.39247590278) -> 45992.392 | B3: =IFERROR(__xludf.DUMMYFUNCTION("""COMPUTED_VALUE"""),"MARNITHA JUWIKE TIMORATI RUNESI") -> MARNITHA JUWIKE TIMORATI RUNESI | C3: =IFERROR(__xludf.DUMMYFUNCTION("""COMPUTED_VALUE"""),"Belum disetujui") -> Belum disetujui
A4: =IFERROR(__xludf.DUMMYFUNCTION("""COMPUTED_VALUE"""),45992.41216761574) -> 45992.412 | B4: =IFERROR(__xludf.DUMMYFUNCTION("""COMPUTED_VALUE"""),"ROS YANE KANA LUDJI") -> ROS YANE KANA LUDJI | C4: =IFERROR(__xludf.DUMMYFUNCTION("""COMPUTED_VALUE"""),"Belum disetujui") -> Belum disetujui
A5: =IFERROR(__xludf.DUMMYFUNCTION("""COMPUTED_VALUE"""),45992.42242364584) -> 45992.422 | B5: =IFERROR(__xludf.DUMMYFUNCTION("""COMPUTED_VALUE"""),"ANDHIKA ULLY") -> ANDHIKA ULLY | C5: =IFERROR(__xludf.DUMMYFUNCTION("""COMPUTED_VALUE"""),"Belum disetujui") -> Belum disetujui
A6: =IFERROR(__xludf.DUMMYFUNCTION("""COMPUTED_VALUE"""),45992.42366331018) -> 45992.424 | B6: =IFERROR(__xludf.DUMMYFUNCTION("""COMPUTED_VALUE"""),"MARNITHA JUWIKE TIMORATI RUNESI") -> MARNITHA JUWIKE TIMORATI RUNESI | C6: =IFERROR(__xludf.DUMMYFUNCTION("""COMPUTED_VALUE"""),"Belum disetujui") -> Belum disetujui
A7: =IFERROR(__xludf.DUMMYFUNCTION("""COMPUTED_VALUE"""),45992.43756385417) -> 45992.438 | B7: =IFERROR(__xludf.DUMMYFUNCTION("""COMPUTED_VALUE"""),"AINI RAHMATINI NATALIA MOESTAKIM") -> AINI RAHMATINI NATALIA MOESTAKIM | C7: =IFERROR(__xludf.DUMMYFUNCTION("""COMPUTED_VALUE"""),"Dapat limit tapi belum diproses") -> Dapat limit tapi belum diproses | D7: =IFERROR(__xludf.DUMMYFUNCTION("""COMPUTED_VALUE"""),"Y21d series") -> Y21d series
A8: =IFERROR(__xludf.DUMMYFUNCTION("""COMPUTED_VALUE"""),45992.46769275463) -> 45992.468 | B8: =IFERROR(__xludf.DUMMYFUNCTION("""COMPUTED_VALUE"""),"EMPI FRANGKI LIEM") -> EMPI FRANGKI LIEM | C8: =IFERROR(__xludf.DUMMYFUNCTION("""COMPUTED_VALUE"""),"Belum disetujui") -> Belum disetujui
A9: =IFERROR(__xludf.DUMMYFUNCTION("""COMPUTED_VALUE"""),45992.50544042824) -> 45992.505 | B9: =IFERROR(__xludf.DUMMYFUNCTION("""COMPUTED_VALUE"""),"YENDRI ELISHABET BERELOE") -> YENDRI ELISHABET BERELOE | C9: =IFERROR(__xludf.DUMMYFUNCTION("""COMPUTED_VALUE"""),"Belum disetujui") -> Belum disetujui
A10: =IFERROR(__xludf.DUMMYFUNCTION("""COMPUTED_VALUE"""),45992.564250324074) -> 45992.564 | B10: =IFERROR(__xludf.DUMMYFUNCTION("""COMPUTED_VALUE"""),"ANNA RAHMATIA JUFRI") -> ANNA RAHMATIA JUFRI | C10: =IFERROR(__xludf.DUMMYFUNCTION("""COMPUTED_VALUE"""),"Belum disetujui") -> Belum disetujui
A11: =IFERROR(__xludf.DUMMYFUNCTION("""COMPUTED_VALUE"""),45992.568997662034) -> 45992.569 | B11: =IFERROR(__xludf.DUMMYFUNCTION("""COMPUTED_VALUE"""),"SANTI MARIA LUKMINI NAHAK") -> SANTI MARIA LUKMINI NAHAK | C11: =IFERROR(__xludf.DUMMYFUNCTION("""COMPUTED_VALUE"""),"Belum disetujui") -> Belum disetujui
A12: =IFERROR(__xludf.DUMMYFUNCTION("""COMPUTED_VALUE"""),45992.56975221065) -> 45992.57 | B12: =IFERROR(__xludf.DUMMYFUNCTION("""COMPUTED_VALUE"""),"RESTIANY MARIA LUAN KALI") -> RESTIANY MARIA LUAN KALI | C12: =IFERROR(__xludf.DUMMYFUNCTION("""COMPUTED_VALUE"""),"Belum disetujui") -> Belum disetujui
A13: =IFERROR(__xludf.DUMMYFUNCTION("""COMPUTED_VALUE"""),45992.575315960654) -> 45992.575 | B13: =IFERROR(__xludf.DUMMYFUNCTION("""COMPUTED_VALUE"""),"NUR FATIMAH MOLBANG") -> NUR FATIMAH MOLBANG | C13: =IFERROR(__xludf.DUMMYFUNCTION("""COMPUTED_VALUE"""),"Belum disetujui") -> Belum disetujui
A14: =IFERROR(__xludf.DUMMYFUNCTION("""COMPUTED_VALUE"""),45992.5792065162) -> 45992.579 | B14: =IFERROR(__xludf.DUMMYFUNCTION("""COMPUTED_VALUE"""),"NUR FATIMAH MOLBANG") -> NUR FATIMAH MOLBANG | C14: =IFERROR(__xludf.DUMMYFUNCTION("""COMPUTED_VALUE"""),"Belum disetujui") -> Belum disetujui
A15: =IFERROR(__xludf.DUMMYFUNCTION("""COMPUTED_VALUE"""),45992.583182372684) -> 45992.583 | B15: =IFERROR(__xludf.DUMMYFUNCTION("""COMPUTED_VALUE"""),"PATRIANI MENGI ULY") -> PATRIANI MENGI ULY | C15: =IFERROR(__xludf.DUMMYFUNCTION("""COMPUTED_VALUE"""),"Belum disetujui") -> Belum disetujui
A16: =IFERROR(__xludf.DUMMYFUNCTION("""COMPUTED_VALUE"""),45992.60638649306) -> 45992.606 | B16: =IFERROR(__xludf.DUMMYFUNCTION("""COMPUTED_VALUE"""),"BERGITHA NIA OLIN") -> BERGITHA NIA OLIN | C16: =IFERROR(__xludf.DUMMYFUNCTION("""COMPUTED_VALUE"""),"Belum disetujui") -> Belum disetujui
A17: =IFERROR(__xludf.DUMMYFUNCTION("""COMPUTED_VALUE"""),45992.61478524306) -> 45992.615 | B17: =IFERROR(__xludf.DUMMYFUNCTION("""COMPUTED_VALUE"""),"YENDRI ELISHABET BERELOE") -> YENDRI ELISHABET BERELOE | C17: =IFERROR(__xludf.DUMMYFUNCTION("""COMPUTED_VALUE"""),"Dapat limit tapi belum diproses") -> Dapat limit tapi belum diproses | D17: =IFERROR(__xludf.DUMMYFUNCTION("""COMPUTED_VALUE"""),"Y21d series") -> Y21d series
A18: =IFERROR(__xludf.DUMMYFUNCTION("""COMPUTED_VALUE"""),45992.67328905092) -> 45992.673 | B18: =IFERROR(__xludf.DUMMYFUNCTION("""COMPUTED_VALUE"""),"NABILA RAHMAWATI") -> NABILA RAHMAWATI | C18: =IFERROR(__xludf.DUMMYFUNCTION("""COMPUTED_VALUE"""),"Belum disetujui") -> Belum disetujui
A19: =IFERROR(__xludf.DUMMYFUNCTION("""COMPUTED_VALUE"""),45992.728126319445) -> 45992.728 | B19: =IFERROR(__xludf.DUMMYFUNCTION("""COMPUTED_VALUE"""),"WARDIA") -> WARDIA | C19: =IFERROR(__xludf.DUMMYFUNCTION("""COMPUTED_VALUE"""),"Belum disetujui") -> Belum disetujui
A20: =IFERROR(__xludf.DUMMYFUNCTION("""COMPUTED_VALUE"""),45992.74368403935) -> 45992.744 | B20: =IFERROR(__xludf.DUMMYFUNCTION("""COMPUTED_VALUE"""),"ESTER LUDJI") -> ESTER LUDJI | C20: =IFERROR(__xludf.DUMMYFUNCTION("""COMPUTED_VALUE"""),"ACC") -> ACC | D20: =IFERROR(__xludf.DUMMYFUNCTION("""COMPUTED_VALUE"""),"Y21d series") -> Y21d series
A21: =IFERROR(__xludf.DUMMYFUNCTION("""COMPUTED_VALUE"""),45992.767859479165) -> 45992.768 | B21: =IFERROR(__xludf.DUMMYFUNCTION("""COMPUTED_VALUE"""),"ESTER LUDJI") -> ESTER LUDJI | C21: =IFERROR(__xludf.DUMMYFUNCTION("""COMPUTED_VALUE"""),"Belum disetujui") -> Belum disetujui
A22: =IFERROR(__xludf.DUMMYFUNCTION("""COMPUTED_VALUE"""),45992.77763405093) -> 45992.778 | B22: =IFERROR(__xludf.DUMMYFUNCTION("""COMPUTED_VALUE"""),"ASRI NINGSI RAMBU ATA ENDI") -> ASRI NINGSI RAMBU ATA ENDI | C22: =IFERROR(__xludf.DUMMYFUNCTION("""COMPUTED_VALUE"""),"Dapat limit tapi belum diproses") -> Dapat limit tapi belum diproses | D22: =IFERROR(__xludf.DUMMYFUNCTION("""COMPUTED_VALUE"""),"Y400 series") -> Y400 series
A23: =IFERROR(__xludf.DUMMYFUNCTION("""COMPUTED_VALUE"""),45992.77939128473) -> 45992.779 | B23: =IFERROR(__xludf.DUMMYFUNCTION("""COMPUTED_VALUE"""),"ROS YANE KANA LUDJI") -> ROS YANE KANA LUDJI | C23: =IFERROR(__xludf.DUMMYFUNCTION("""COMPUTED_VALUE"""),"Belum disetujui") -> Belum disetujui
A24: =IFERROR(__xludf.DUMMYFUNCTION("""COMPUTED_VALUE"""),45992.78130732638) -> 45992.781 | B24: =IFERROR(__xludf.DUMMYFUNCTION("""COMPUTED_VALUE"""),"BERGITHA NIA OLIN") -> BERGITHA NIA OLIN | C24: =IFERROR(__xludf.DUMMYFUNCTION("""COMPUTED_VALUE"""),"ACC") -> ACC | D24: =IFERROR(__xludf.DUMMYFUNCTION("""COMPUTED_VALUE"""),"V60 Lite series") -> V60 Lite series
A25: =IFERROR(__xludf.DUMMYFUNCTION("""COMPUTED_VALUE"""),45992.796267280086) -> 45992.796 | B25: =IFERROR(__xludf.DUMMYFUNCTION("""COMPUTED_VALUE"""),"SANTI MARIA LUKMINI NAHAK") -> SANTI MARIA LUKMINI NAHAK | C25: =IFERROR(__xludf.DUMMYFUNCTION("""COMPUTED_VALUE"""),"Belum disetujui") -> Belum disetujui
A26: =IFERROR(__xludf.DUMMYFUNCTION("""COMPUTED_VALUE"""),45992.819738726845) -> 45992.82 | B26: =IFERROR(__xludf.DUMMYFUNCTION("""COMPUTED_VALUE"""),"YOVANDA KATRINA NAE") -> YOVANDA KATRINA NAE | C26: =IFERROR(__xludf.DUMMYFUNCTION("""COMPUTED_VALUE"""),"Belum disetujui") -> Belum disetujui
A27: =IFERROR(__xludf.DUMMYFUNCTION("""COMPUTED_VALUE"""),45992.83968498843) -> 45992.84 | B27: =IFERROR(__xludf.DUMMYFUNCTION("""COMPUTED_VALUE"""),"WINDRI MANOE") -> WINDRI MANOE | C27: =IFERROR(__xludf.DUMMYFUNCTION("""COMPUTED_VALUE"""),"Belum disetujui") -> Belum disetujui
A28: =IFERROR(__xludf.DUMMYFUNCTION("""COMPUTED_VALUE"""),45992.840489166665) -> 45992.84 | B28: =IFERROR(__xludf.DUMMYFUNCTION("""COMPUTED_VALUE"""),"WINDRI MANOE") -> WINDRI MANOE | C28: =IFERROR(__xludf.DUMMYFUNCTION("""COMPUTED_VALUE"""),"Belum disetujui") -> Belum disetujui
A29: =IFERROR(__xludf.DUMMYFUNCTION("""COMPUTED_VALUE"""),45992.85128471065) -> 45992.851 | B29: =IFERROR(__xludf.DUMMYFUNCTION("""COMPUTED_VALUE"""),"DWITNEY PRETY WANGGANDIMA") -> DWITNEY PRETY WANGGANDIMA | C29: =IFERROR(__xludf.DUMMYFUNCTION("""COMPUTED_VALUE"""),"Belum disetujui") -> Belum disetujui
A30: =IFERROR(__xludf.DUMMYFUNCTION("""COMPUTED_VALUE"""),45992.85280275463) -> 45992.853 | B30: =IFERROR(__xludf.DUMMYFUNCTION("""COMPUTED_VALUE"""),"DWITNEY PRETY WANGGANDIMA") -> DWITNEY PRETY WANGGANDIMA | C30: =IFERROR(__xludf.DUMMYFUNCTION("""COMPUTED_VALUE"""),"Belum disetujui") -> Belum disetujui
A31: =IFERROR(__xludf.DUMMYFUNCTION("""COMPUTED_VALUE"""),45992.866584537034) -> 45992.867 | B31: =IFERROR(__xludf.DUMMYFUNCTION("""COMPUTED_VALUE"""),"YOVANDA KATRINA NAE") -> YOVANDA KATRINA NAE | C31: =IFERROR(__xludf.DUMMYFUNCTION("""COMPUTED_VALUE"""),"ACC") -> ACC | D31: =IFERROR(__xludf.DUMMYFUNCTION("""COMPUTED_VALUE"""),"Y21d series") -> Y21d series
A32: =IFERROR(__xludf.DUMMYFUNCTION("""COMPUTED_VALUE"""),45992.90303767362) -> 45992.903 | B32: =IFERROR(__xludf.DUMMYFUNCTION("""COMPUTED_VALUE"""),"HERONIMUS NAMU WALI") -> HERONIMUS NAMU WALI | C32: =IFERROR(__xludf.DUMMYFUNCTION("""COMPUTED_VALUE"""),"ACC") -> ACC | D32: =IFERROR(__xludf.DUMMYFUNCTION("""COMPUTED_VALUE"""),"Y21d series") -> Y21d series
A33: =IFERROR(__xludf.DUMMYFUNCTION("""COMPUTED_VALUE"""),45992.90552940972) -> 45992.906 | B33: =IFERROR(__xludf.DUMMYFUNCTION("""COMPUTED_VALUE"""),"HERONIMUS NAMU WALI") -> HERONIMUS NAMU WALI | C33: =IFERROR(__xludf.DUMMYFUNCTION("""COMPUTED_VALUE"""),"Belum disetujui") -> Belum disetujui
A34: =IFERROR(__xludf.DUMMYFUNCTION("""COMPUTED_VALUE"""),45993.40507277778) -> 45993.405 | B34: =IFERROR(__xludf.DUMMYFUNCTION("""COMPUTED_VALUE"""),"AZ ZAHRA SITI ZAINAB") -> AZ ZAHRA SITI ZAINAB | C34: =IFERROR(__xludf.DUMMYFUNCTION("""COMPUTED_VALUE"""),"Belum disetujui") -> Belum disetujui
A35: =IFERROR(__xludf.DUMMYFUNCTION("""COMPUTED_VALUE"""),45993.41075219907) -> 45993.411 | B35: =IFERROR(__xludf.DUMMYFUNCTION("""COMPUTED_VALUE"""),"YUNITA TAMELAB") -> YUNITA TAMELAB | C35: =IFERROR(__xludf.DUMMYFUNCTION("""COMPUTED_VALUE"""),"Belum disetujui") -> Belum disetujui
A36: =IFERROR(__xludf.DUMMYFUNCTION("""COMPUTED_VALUE"""),45993.416915821756) -> 45993.417 | B36: =IFERROR(__xludf.DUMMYFUNCTION("""COMPUTED_VALUE"""),"PUSPA ANGGREINI") -> PUSPA ANGGREINI | C36: =IFERROR(__xludf.DUMMYFUNCTION("""COMPUTED_VALUE"""),"Dapat limit tapi belum diproses") -> Dapat limit tapi belum diproses | D36: =IFERROR(__xludf.DUMMYFUNCTION("""COMPUTED_VALUE"""),"Y21d series") -> Y21d series
A37: =IFERROR(__xludf.DUMMYFUNCTION("""COMPUTED_VALUE"""),45993.43785559028) -> 45993.438 | B37: =IFERROR(__xludf.DUMMYFUNCTION("""COMPUTED_VALUE"""),"ASTUTI BELA WAWO") -> ASTUTI BELA WAWO | C37: =IFERROR(__xludf.DUMMYFUNCTION("""COMPUTED_VALUE"""),"Belum disetujui") -> Belum disetujui
A38: =IFERROR(__xludf.DUMMYFUNCTION("""COMPUTED_VALUE"""),45993.43924400463) -> 45993.439 | B38: =IFERROR(__xludf.DUMMYFUNCTION("""COMPUTED_VALUE"""),"ASTUTI BELA WAWO") -> ASTUTI BELA WAWO | C38: =IFERROR(__xludf.DUMMYFUNCTION("""COMPUTED_VALUE"""),"Belum disetujui") -> Belum disetujui
A39: =IFERROR(__xludf.DUMMYFUNCTION("""COMPUTED_VALUE"""),45993.440446458335) -> 45993.44 | B39: =IFERROR(__xludf.DUMMYFUNCTION("""COMPUTED_VALUE"""),"ASTUTI BELA WAWO") -> ASTUTI BELA WAWO | C39: =IFERROR(__xludf.DUMMYFUNCTION("""COMPUTED_VALUE"""),"Belum disetujui") -> Belum disetujui
A40: =IFERROR(__xludf.DUMMYFUNCTION("""COMPUTED_VALUE"""),45993.47803436343) -> 45993.478 | B40: =IFERROR(__xludf.DUMMYFUNCTION("""COMPUTED_VALUE"""),"PRETI SISILIA SILA") -> PRETI SISILIA SILA | C40: =IFERROR(__xludf.DUMMYFUNCTION("""COMPUTED_VALUE"""),"Dapat limit tapi belum diproses") -> Dapat limit tapi belum diproses | D40: =IFERROR(__xludf.DUMMYFUNCTION("""COMPUTED_VALUE"""),"Y21d series") -> Y21d series
A41: =IFERROR(__xludf.DUMMYFUNCTION("""COMPUTED_VALUE"""),45993.49545135416) -> 45993.495 | B41: =IFERROR(__xludf.DUMMYFUNCTION("""COMPUTED_VALUE"""),"MARATHA MARLINDA FANGGIDAE") -> MARATHA MARLINDA FANGGIDAE | C41: =IFERROR(__xludf.DUMMYFUNCTION("""COMPUTED_VALUE"""),"Dapat limit tapi belum diproses") -> Dapat limit tapi belum diproses | D41: =IFERROR(__xludf.DUMMYFUNCTION("""COMPUTED_VALUE"""),"Y21d series") -> Y21d series
A42: =IFERROR(__xludf.DUMMYFUNCTION("""COMPUTED_VALUE"""),45993.49679296297) -> 45993.497 | B42: =IFERROR(__xludf.DUMMYFUNCTION("""COMPUTED_VALUE"""),"NOVLIANA BARBALINA MISA") -> NOVLIANA BARBALINA MISA | C42: =IFERROR(__xludf.DUMMYFUNCTION("""COMPUTED_VALUE"""),"Belum disetujui") -> Belum disetujui
A43: =IFERROR(__xludf.DUMMYFUNCTION("""COMPUTED_VALUE"""),45993.50505728009) -> 45993.505 | B43: =IFERROR(__xludf.DUMMYFUNCTION("""COMPUTED_VALUE"""),"MARIA MELAN ANANCE BILI") -> MARIA MELAN ANANCE BILI | C43: =IFERROR(__xludf.DUMMYFUNCTION("""COMPUTED_VALUE"""),"Belum disetujui") -> Belum disetujui
A44: =IFERROR(__xludf.DUMMYFUNCTION("""COMPUTED_VALUE"""),45993.522510324074) -> 45993.523 | B44: =IFERROR(__xludf.DUMMYFUNCTION("""COMPUTED_VALUE"""),"ANDHIKA ULLY") -> ANDHIKA ULLY | C44: =IFERROR(__xludf.DUMMYFUNCTION("""COMPUTED_VALUE"""),"Belum disetujui") -> Belum disetujui
A45: =IFERROR(__xludf.DUMMYFUNCTION("""COMPUTED_VALUE"""),45993.53238291667) -> 45993.532 | B45: =IFERROR(__xludf.DUMMYFUNCTION("""COMPUTED_VALUE"""),"NOVLIANA BARBALINA MISA") -> NOVLIANA BARBALINA MISA | C45: =IFERROR(__xludf.DUMMYFUNCTION("""COMPUTED_VALUE"""),"Dapat limit tapi belum diproses") -> Dapat limit tapi belum diproses | D45: =IFERROR(__xludf.DUMMYFUNCTION("""COMPUTED_VALUE"""),"Y21d series") -> Y21d series
A46: =IFERROR(__xludf.DUMMYFUNCTION("""COMPUTED_VALUE"""),45993.53481921297) -> 45993.535 | B46: =IFERROR(__xludf.DUMMYFUNCTION("""COMPUTED_VALUE"""),"IDMAL YUSDIRAN YUSUF") -> IDMAL YUSDIRAN YUSUF | C46: =IFERROR(__xludf.DUMMYFUNCTION("""COMPUTED_VALUE"""),"Belum disetujui") -> Belum disetujui
A47: =IFERROR(__xludf.DUMMYFUNCTION("""COMPUTED_VALUE"""),45993.544780335644) -> 45993.545 | B47: =IFERROR(__xludf.DUMMYFUNCTION("""COMPUTED_VALUE"""),"ROS YANE KANA LUDJI") -> ROS YANE KANA LUDJI | C47: =IFERROR(__xludf.DUMMYFUNCTION("""COMPUTED_VALUE"""),"Belum disetujui") -> Belum disetujui
A48: =IFERROR(__xludf.DUMMYFUNCTION("""COMPUTED_VALUE"""),45993.54682649305) -> 45993.547 | B48: =IFERROR(__xludf.DUMMYFUNCTION("""COMPUTED_VALUE"""),"SANTI MARIA LUKMINI NAHAK") -> SANTI MARIA LUKMINI NAHAK | C48: =IFERROR(__xludf.DUMMYFUNCTION("""COMPUTED_VALUE"""),"Belum disetujui") -> Belum disetujui
A49: =IFERROR(__xludf.DUMMYFUNCTION("""COMPUTED_VALUE"""),45993.54807872685) -> 45993.548 | B49: =IFERROR(__xludf.DUMMYFUNCTION("""COMPUTED_VALUE"""),"ROS YANE KANA LUDJI") -> ROS YANE KANA LUDJI | C49: =IFERROR(__xludf.DUMMYFUNCTION("""COMPUTED_VALUE"""),"Belum disetujui") -> Belum disetujui
A50: =IFERROR(__xludf.DUMMYFUNCTION("""COMPUTED_VALUE"""),45993.55046239583) -> 45993.55 | B50: =IFERROR(__xludf.DUMMYFUNCTION("""COMPUTED_VALUE"""),"MARNITHA JUWIKE TIMORATI RUNESI") -> MARNITHA JUWIKE TIMORATI RUNESI | C50: =IFERROR(__xludf.DUMMYFUNCTION("""COMPUTED_VALUE"""),"Belum disetujui") -> Belum disetujui
A51: =IFERROR(__xludf.DUMMYFUNCTION("""COMPUTED_VALUE"""),45993.554693541664) -> 45993.555 | B51: =IFERROR(__xludf.DUMMYFUNCTION("""COMPUTED_VALUE"""),"ASRI NINGSI RAMBU ATA ENDI") -> ASRI NINGSI RAMBU ATA ENDI | C51: =IFERROR(__xludf.DUMMYFUNCTION("""COMPUTED_VALUE"""),"Belum disetujui") -> Belum disetujui
A52: =IFERROR(__xludf.DUMMYFUNCTION("""COMPUTED_VALUE"""),45993.65028991898) -> 45993.65 | B52: =IFERROR(__xludf.DUMMYFUNCTION("""COMPUTED_VALUE"""),"NOVLIANA BARBALINA MISA") -> NOVLIANA BARBALINA MISA | C52: =IFERROR(__xludf.DUMMYFUNCTION("""COMPUTED_VALUE"""),"ACC") -> ACC | D52: =IFERROR(__xludf.DUMMYFUNCTION("""COMPUTED_VALUE"""),"Y21d series") -> Y21d series
A53: =IFERROR(__xludf.DUMMYFUNCTION("""COMPUTED_VALUE"""),45993.66795928241) -> 45993.668 | B53: =IFERROR(__xludf.DUMMYFUNCTION("""COMPUTED_VALUE"""),"ASRI NINGSI RAMBU ATA ENDI") -> ASRI NINGSI RAMBU ATA ENDI | C53: =IFERROR(__xludf.DUMMYFUNCTION("""COMPUTED_VALUE"""),"Belum disetujui") -> Belum disetujui
A54: =IFERROR(__xludf.DUMMYFUNCTION("""COMPUTED_VALUE"""),45993.69571012732) -> 45993.696 | B54: =IFERROR(__xludf.DUMMYFUNCTION("""COMPUTED_VALUE"""),"NUR FATIMAH MOLBANG") -> NUR FATIMAH MOLBANG | C54: =IFERROR(__xludf.DUMMYFUNCTION("""COMPUTED_VALUE"""),"ACC") -> ACC | D54: =IFERROR(__xludf.DUMMYFUNCTION("""COMPUTED_VALUE"""),"Y21d series") -> Y21d series
A55: =IFERROR(__xludf.DUMMYFUNCTION("""COMPUTED_VALUE"""),45993.69793998842) -> 45993.698 | B55: =IFERROR(__xludf.DUMMYFUNCTION("""COMPUTED_VALUE"""),"NUR FATIMAH MOLBANG") -> NUR FATIMAH MOLBANG | C55: =IFERROR(__xludf.DUMMYFUNCTION("""COMPUTED_VALUE"""),"ACC") -> ACC | D55: =IFERROR(__xludf.DUMMYFUNCTION("""COMPUTED_VALUE"""),"Y21d series") -> Y21d series
A56: =IFERROR(__xludf.DUMMYFUNCTION("""COMPUTED_VALUE"""),45993.69931180555) -> 45993.699 | B56: =IFERROR(__xludf.DUMMYFUNCTION("""COMPUTED_VALUE"""),"WINDRI MANOE") -> WINDRI MANOE | C56: =IFERROR(__xludf.DUMMYFUNCTION("""COMPUTED_VALUE"""),"Belum disetujui") -> Belum disetujui
A57: =IFERROR(__xludf.DUMMYFUNCTION("""COMPUTED_VALUE"""),45993.70677390046) -> 45993.707 | B57: =IFERROR(__xludf.DUMMYFUNCTION("""COMPUTED_VALUE"""),"SULIS NURAINI INSYATUN") -> SULIS NURAINI INSYATUN | C57: =IFERROR(__xludf.DUMMYFUNCTION("""COMPUTED_VALUE"""),"Belum disetujui") -> Belum disetujui
A58: =IFERROR(__xludf.DUMMYFUNCTION("""COMPUTED_VALUE"""),45993.724381273154) -> 45993.724 | B58: =IFERROR(__xludf.DUMMYFUNCTION("""COMPUTED_VALUE"""),"ASRI NINGSI RAMBU ATA ENDI") -> ASRI NINGSI RAMBU ATA ENDI | C58: =IFERROR(__xludf.DUMMYFUNCTION("""COMPUTED_VALUE"""),"Belum disetujui") -> Belum disetujui
A59: =IFERROR(__xludf.DUMMYFUNCTION("""COMPUTED_VALUE"""),45993.728520543984) -> 45993.729 | B59: =IFERROR(__xludf.DUMMYFUNCTION("""COMPUTED_VALUE"""),"ESTER LUDJI") -> ESTER LUDJI | C59: =IFERROR(__xludf.DUMMYFUNCTION("""COMPUTED_VALUE"""),"Belum disetujui") -> Belum disetujui
A60: =IFERROR(__xludf.DUMMYFUNCTION("""COMPUTED_VALUE"""),45993.73269866898) -> 45993.733 | B60: =IFERROR(__xludf.DUMMYFUNCTION("""COMPUTED_VALUE"""),"NOVLIANA BARBALINA MISA") -> NOVLIANA BARBALINA MISA | C60: =IFERROR(__xludf.DUMMYFUNCTION("""COMPUTED_VALUE"""),"ACC") -> ACC | D60: =IFERROR(__xludf.DUMMYFUNCTION("""COMPUTED_VALUE"""),"Y21d series") -> Y21d series
A61: =IFERROR(__xludf.DUMMYFUNCTION("""COMPUTED_VALUE"""),45993.741195787035) -> 45993.741 | B61: =IFERROR(__xludf.DUMMYFUNCTION("""COMPUTED_VALUE"""),"WARDIA") -> WARDIA | C61: =IFERROR(__xludf.DUMMYFUNCTION("""COMPUTED_VALUE"""),"Belum disetujui") -> Belum disetujui
A62: =IFERROR(__xludf.DUMMYFUNCTION("""COMPUTED_VALUE"""),45993.7423109375) -> 45993.742 | B62: =IFERROR(__xludf.DUMMYFUNCTION("""COMPUTED_VALUE"""),"MARNITHA JUWIKE TIMORATI RUNESI") -> MARNITHA JUWIKE TIMORATI RUNESI | C62: =IFERROR(__xludf.DUMMYFUNCTION("""COMPUTED_VALUE"""),"ACC") -> ACC | D62: =IFERROR(__xludf.DUMMYFUNCTION("""COMPUTED_VALUE"""),"Y21d series") -> Y21d series
A63: =IFERROR(__xludf.DUMMYFUNCTION("""COMPUTED_VALUE"""),45993.75063717592) -> 45993.751 | B63: =IFERROR(__xludf.DUMMYFUNCTION("""COMPUTED_VALUE"""),"NENY MERLIANTI NA'U") -> NENY MERLIANTI NA'U | C63: =IFERROR(__xludf.DUMMYFUNCTION("""COMPUTED_VALUE"""),"Dapat limit tapi belum diproses") -> Dapat limit tapi belum diproses | D63: =IFERROR(__xludf.DUMMYFUNCTION("""COMPUTED_VALUE"""),"Y21d series") -> Y21d series
A64: =IFERROR(__xludf.DUMMYFUNCTION("""COMPUTED_VALUE"""),45993.770085069445) -> 45993.77 | B64: =IFERROR(__xludf.DUMMYFUNCTION("""COMPUTED_VALUE"""),"YOVANDA KATRINA NAE") -> YOVANDA KATRINA NAE | C64: =IFERROR(__xludf.DUMMYFUNCTION("""COMPUTED_VALUE"""),"Belum disetujui") -> Belum disetujui
A65: =IFERROR(__xludf.DUMMYFUNCTION("""COMPUTED_VALUE"""),45993.77797498842) -> 45993.778 | B65: =IFERROR(__xludf.DUMMYFUNCTION("""COMPUTED_VALUE"""),"YOVANDA KATRINA NAE") -> YOVANDA KATRINA NAE | C65: =IFERROR(__xludf.DUMMYFUNCTION("""COMPUTED_VALUE"""),"Belum disetujui") -> Belum disetujui
A66: =IFERROR(__xludf.DUMMYFUNCTION("""COMPUTED_VALUE"""),45993.78051347222) -> 45993.781 | B66: =IFERROR(__xludf.DUMMYFUNCTION("""COMPUTED_VALUE"""),"ANYARMITHA SOPHIA SUEK") -> ANYARMITHA SOPHIA SUEK | C66: =IFERROR(__xludf.DUMMYFUNCTION("""COMPUTED_VALUE"""),"Belum disetujui") -> Belum disetujui
A67: =IFERROR(__xludf.DUMMYFUNCTION("""COMPUTED_VALUE"""),45993.78811693287) -> 45993.788 | B67: =IFERROR(__xludf.DUMMYFUNCTION("""COMPUTED_VALUE"""),"ASTUTI BELA WAWO") -> ASTUTI BELA WAWO | C67: =IFERROR(__xludf.DUMMYFUNCTION("""COMPUTED_VALUE"""),"Dapat limit tapi belum diproses") -> Dapat limit tapi belum diproses | D67: =IFERROR(__xludf.DUMMYFUNCTION("""COMPUTED_VALUE"""),"Y21d series") -> Y21d series
A68: =IFERROR(__xludf.DUMMYFUNCTION("""COMPUTED_VALUE"""),45993.80144224537) -> 45993.801 | B68: =IFERROR(__xludf.DUMMYFUNCTION("""COMPUTED_VALUE"""),"AZ ZAHRA SITI ZAINAB") -> AZ ZAHRA SITI ZAINAB | C68: =IFERROR(__xludf.DUMMYFUNCTION("""COMPUTED_VALUE"""),"Belum disetujui") -> Belum disetujui
A69: =IFERROR(__xludf.DUMMYFUNCTION("""COMPUTED_VALUE"""),45993.812384212964) -> 45993.812 | B69: =IFERROR(__xludf.DUMMYFUNCTION("""COMPUTED_VALUE"""),"IRENE NOVALIA KADJU") -> IRENE NOVALIA KADJU | C69: =IFERROR(__xludf.DUMMYFUNCTION("""COMPUTED_VALUE"""),"Belum disetujui") -> Belum disetujui
A70: =IFERROR(__xludf.DUMMYFUNCTION("""COMPUTED_VALUE"""),45993.814452673614) -> 45993.814 | B70: =IFERROR(__xludf.DUMMYFUNCTION("""COMPUTED_VALUE"""),"PRETI SISILIA SILA") -> PRETI SISILIA SILA | C70: =IFERROR(__xludf.DUMMYFUNCTION("""COMPUTED_VALUE"""),"Dapat limit tapi belum diproses") -> Dapat limit tapi belum diproses | D70: =IFERROR(__xludf.DUMMYFUNCTION("""COMPUTED_VALUE"""),"V60 series") -> V60 series
A71: =IFERROR(__xludf.DUMMYFUNCTION("""COMPUTED_VALUE"""),45993.837161180556) -> 45993.837 | B71: =IFERROR(__xludf.DUMMYFUNCTION("""COMPUTED_VALUE"""),"ADRIANA") -> ADRIANA | C71: =IFERROR(__xludf.DUMMYFUNCTION("""COMPUTED_VALUE"""),"Dapat limit tapi belum diproses") -> Dapat limit tapi belum diproses | D71: =IFERROR(__xludf.DUMMYFUNCTION("""COMPUTED_VALUE"""),"Y21d series") -> Y21d series
A72: =IFERROR(__xludf.DUMMYFUNCTION("""COMPUTED_VALUE"""),45993.845966863424) -> 45993.846 | B72: =IFERROR(__xludf.DUMMYFUNCTION("""COMPUTED_VALUE"""),"MARIA MELAN ANANCE BILI") -> MARIA MELAN ANANCE BILI | C72: =IFERROR(__xludf.DUMMYFUNCTION("""COMPUTED_VALUE"""),"ACC") -> ACC | D72: =IFERROR(__xludf.DUMMYFUNCTION("""COMPUTED_VALUE"""),"V60 Lite series") -> V60 Lite series
A73: =IFERROR(__xludf.DUMMYFUNCTION("""COMPUTED_VALUE"""),45993.8541271412) -> 45993.854 | B73: =IFERROR(__xludf.DUMMYFUNCTION("""COMPUTED_VALUE"""),"NUR FATIMAH MOLBANG") -> NUR FATIMAH MOLBANG | C73: =IFERROR(__xludf.DUMMYFUNCTION("""COMPUTED_VALUE"""),"Belum disetujui") -> Belum disetujui
A74: =IFERROR(__xludf.DUMMYFUNCTION("""COMPUTED_VALUE"""),45993.91202762732) -> 45993.912 | B74: =IFERROR(__xludf.DUMMYFUNCTION("""COMPUTED_VALUE"""),"ESTER LUDJI") -> ESTER LUDJI | C74: =IFERROR(__xludf.DUMMYFUNCTION("""COMPUTED_VALUE"""),"ACC") -> ACC | D74: =IFERROR(__xludf.DUMMYFUNCTION("""COMPUTED_VALUE"""),"Y400 series") -> Y400 series
A75: =IFERROR(__xludf.DUMMYFUNCTION("""COMPUTED_VALUE"""),45993.94131409722) -> 45993.941 | B75: =IFERROR(__xludf.DUMMYFUNCTION("""COMPUTED_VALUE"""),"SANTI MARIA LUKMINI NAHAK") -> SANTI MARIA LUKMINI NAHAK | C75: =IFERROR(__xludf.DUMMYFUNCTION("""COMPUTED_VALUE"""),"Belum disetujui") -> Belum disetujui
A76: =IFERROR(__xludf.DUMMYFUNCTION("""COMPUTED_VALUE"""),45994.42721375) -> 45994.427 | B76: =IFERROR(__xludf.DUMMYFUNCTION("""COMPUTED_VALUE"""),"MARIA MELAN ANANCE BILI") -> MARIA MELAN ANANCE BILI | C76: =IFERROR(__xludf.DUMMYFUNCTION("""COMPUTED_VALUE"""),"Belum disetujui") -> Belum disetujui
A77: =IFERROR(__xludf.DUMMYFUNCTION("""COMPUTED_VALUE"""),45994.428609675924) -> 45994.429 | B77: =IFERROR(__xludf.DUMMYFUNCTION("""COMPUTED_VALUE"""),"MARIA MELAN ANANCE BILI") -> MARIA MELAN ANANCE BILI | C77: =IFERROR(__xludf.DUMMYFUNCTION("""COMPUTED_VALUE"""),"Belum disetujui") -> Belum disetujui
A78: =IFERROR(__xludf.DUMMYFUNCTION("""COMPUTED_VALUE"""),45994.42870438657) -> 45994.429 | B78: =IFERROR(__xludf.DUMMYFUNCTION("""COMPUTED_VALUE"""),"PRETI SISILIA SILA") -> PRETI SISILIA SILA | C78: =IFERROR(__xludf.DUMMYFUNCTION("""COMPUTED_VALUE"""),"Belum disetujui") -> Belum disetujui
A79: =IFERROR(__xludf.DUMMYFUNCTION("""COMPUTED_VALUE"""),45994.43426706018) -> 45994.434 | B79: =IFERROR(__xludf.DUMMYFUNCTION("""COMPUTED_VALUE"""),"YUNITA TAMELAB") -> YUNITA TAMELAB | C79: =IFERROR(__xludf.DUMMYFUNCTION("""COMPUTED_VALUE"""),"Belum disetujui") -> Belum disetujui
A80: =IFERROR(__xludf.DUMMYFUNCTION("""COMPUTED_VALUE"""),45994.46554200232) -> 45994.466 | B80: =IFERROR(__xludf.DUMMYFUNCTION("""COMPUTED_VALUE"""),"NOVANTRY RUTHANIA NAFFIE") -> NOVANTRY RUTHANIA NAFFIE | C80: =IFERROR(__xludf.DUMMYFUNCTION("""COMPUTED_VALUE"""),"Belum disetujui") -> Belum disetujui
A81: =IFERROR(__xludf.DUMMYFUNCTION("""COMPUTED_VALUE"""),45994.46812059028) -> 45994.468 | B81: =IFERROR(__xludf.DUMMYFUNCTION("""COMPUTED_VALUE"""),"FEBRIANTHY ELISABET NA'U") -> FEBRIANTHY ELISABET NA'U | C81: =IFERROR(__xludf.DUMMYFUNCTION("""COMPUTED_VALUE"""),"Belum disetujui") -> Belum disetujui
A82: =IFERROR(__xludf.DUMMYFUNCTION("""COMPUTED_VALUE"""),45994.48669936343) -> 45994.487 | B82: =IFERROR(__xludf.DUMMYFUNCTION("""COMPUTED_VALUE"""),"AZ ZAHRA SITI ZAINAB") -> AZ ZAHRA SITI ZAINAB | C82: =IFERROR(__xludf.DUMMYFUNCTION("""COMPUTED_VALUE"""),"ACC") -> ACC | D82: =IFERROR(__xludf.DUMMYFUNCTION("""COMPUTED_VALUE"""),"Y400 series") -> Y400 series
A83: =IFERROR(__xludf.DUMMYFUNCTION("""COMPUTED_VALUE"""),45994.48809438658) -> 45994.488 | B83: =IFERROR(__xludf.DUMMYFUNCTION("""COMPUTED_VALUE"""),"ROS YANE KANA LUDJI") -> ROS YANE KANA LUDJI | C83: =IFERROR(__xludf.DUMMYFUNCTION("""COMPUTED_VALUE"""),"Belum disetujui") -> Belum disetujui
A84: =IFERROR(__xludf.DUMMYFUNCTION("""COMPUTED_VALUE"""),45994.497347476856) -> 45994.497 | B84: =IFERROR(__xludf.DUMMYFUNCTION("""COMPUTED_VALUE"""),"KESIA NATALIA I. BENU") -> KESIA NATALIA I. BENU | C84: =IFERROR(__xludf.DUMMYFUNCTION("""COMPUTED_VALUE"""),"ACC") -> ACC | D84: =IFERROR(__xludf.DUMMYFUNCTION("""COMPUTED_VALUE"""),"Y400 series") -> Y400 series
A85: =IFERROR(__xludf.DUMMYFUNCTION("""COMPUTED_VALUE"""),45994.50929259259) -> 45994.509 | B85: =IFERROR(__xludf.DUMMYFUNCTION("""COMPUTED_VALUE"""),"NABILA RAHMAWATI") -> NABILA RAHMAWATI | C85: =IFERROR(__xludf.DUMMYFUNCTION("""COMPUTED_VALUE"""),"Belum disetujui") -> Belum disetujui
A86: =IFERROR(__xludf.DUMMYFUNCTION("""COMPUTED_VALUE"""),45994.51020031251) -> 45994.51 | B86: =IFERROR(__xludf.DUMMYFUNCTION("""COMPUTED_VALUE"""),"ASTUTI BELA WAWO") -> ASTUTI BELA WAWO | C86: =IFERROR(__xludf.DUMMYFUNCTION("""COMPUTED_VALUE"""),"Dapat limit tapi belum diproses") -> Dapat limit tapi belum diproses | D86: =IFERROR(__xludf.DUMMYFUNCTION("""COMPUTED_VALUE"""),"Y21d series") -> Y21d series
A87: =IFERROR(__xludf.DUMMYFUNCTION("""COMPUTED_VALUE"""),45994.513593692136) -> 45994.514 | B87: =IFERROR(__xludf.DUMMYFUNCTION("""COMPUTED_VALUE"""),"ALDIANA WELIA PANIE") -> ALDIANA WELIA PANIE | C87: =IFERROR(__xludf.DUMMYFUNCTION("""COMPUTED_VALUE"""),"Belum disetujui") -> Belum disetujui
A88: =IFERROR(__xludf.DUMMYFUNCTION("""COMPUTED_VALUE"""),45994.51465967592) -> 45994.515 | B88: =IFERROR(__xludf.DUMMYFUNCTION("""COMPUTED_VALUE"""),"RESTIANY MARIA LUAN KALI") -> RESTIANY MARIA LUAN KALI | C88: =IFERROR(__xludf.DUMMYFUNCTION("""COMPUTED_VALUE"""),"Belum disetujui") -> Belum disetujui
A89: =IFERROR(__xludf.DUMMYFUNCTION("""COMPUTED_VALUE"""),45994.51734414352) -> 45994.517 | B89: =IFERROR(__xludf.DUMMYFUNCTION("""COMPUTED_VALUE"""),"BERGITHA NIA OLIN") -> BERGITHA NIA OLIN | C89: =IFERROR(__xludf.DUMMYFUNCTION("""COMPUTED_VALUE"""),"Belum disetujui") -> Belum disetujui
A90: =IFERROR(__xludf.DUMMYFUNCTION("""COMPUTED_VALUE"""),45994.53813782408) -> 45994.538 | B90: =IFERROR(__xludf.DUMMYFUNCTION("""COMPUTED_VALUE"""),"ANYARMITHA SOPHIA SUEK") -> ANYARMITHA SOPHIA SUEK | C90: =IFERROR(__xludf.DUMMYFUNCTION("""COMPUTED_VALUE"""),"Belum disetujui") -> Belum disetujui
A91: =IFERROR(__xludf.DUMMYFUNCTION("""COMPUTED_VALUE"""),45994.54844388889) -> 45994.548 | B91: =IFERROR(__xludf.DUMMYFUNCTION("""COMPUTED_VALUE"""),"YASINTHA MBU") -> YASINTHA MBU | C91: =IFERROR(__xludf.DUMMYFUNCTION("""COMPUTED_VALUE"""),"Belum disetujui") -> Belum disetujui
A92: =IFERROR(__xludf.DUMMYFUNCTION("""COMPUTED_VALUE"""),45994.577952210646) -> 45994.578 | B92: =IFERROR(__xludf.DUMMYFUNCTION("""COMPUTED_VALUE"""),"ASTUTI BELA WAWO") -> ASTUTI BELA WAWO | C92: =IFERROR(__xludf.DUMMYFUNCTION("""COMPUTED_VALUE"""),"Belum disetujui") -> Belum disetujui
A93: =IFERROR(__xludf.DUMMYFUNCTION("""COMPUTED_VALUE"""),45994.58770231482) -> 45994.588 | B93: =IFERROR(__xludf.DUMMYFUNCTION("""COMPUTED_VALUE"""),"YUNITA TAMELAB") -> YUNITA TAMELAB | C93: =IFERROR(__xludf.DUMMYFUNCTION("""COMPUTED_VALUE"""),"Belum disetujui") -> Belum disetujui
A94: =IFERROR(__xludf.DUMMYFUNCTION("""COMPUTED_VALUE"""),45994.59161390046) -> 45994.592 | B94: =IFERROR(__xludf.DUMMYFUNCTION("""COMPUTED_VALUE"""),"ANYARMITHA SOPHIA SUEK") -> ANYARMITHA SOPHIA SUEK | C94: =IFERROR(__xludf.DUMMYFUNCTION("""COMPUTED_VALUE"""),"Belum disetujui") -> Belum disetujui
A95: =IFERROR(__xludf.DUMMYFUNCTION("""COMPUTED_VALUE"""),45994.60704673611) -> 45994.607 | B95: =IFERROR(__xludf.DUMMYFUNCTION("""COMPUTED_VALUE"""),"ADRIANA") -> ADRIANA | C95: =IFERROR(__xludf.DUMMYFUNCTION("""COMPUTED_VALUE"""),"Belum disetujui") -> Belum disetujui
A96: =IFERROR(__xludf.DUMMYFUNCTION("""COMPUTED_VALUE"""),45994.60910775463) -> 45994.609 | B96: =IFERROR(__xludf.DUMMYFUNCTION("""COMPUTED_VALUE"""),"ADRIANA") -> ADRIANA | C96: =IFERROR(__xludf.DUMMYFUNCTION("""COMPUTED_VALUE"""),"Belum disetujui") -> Belum disetujui
A97: =IFERROR(__xludf.DUMMYFUNCTION("""COMPUTED_VALUE"""),45994.61069847223) -> 45994.611 | B97: =IFERROR(__xludf.DUMMYFUNCTION("""COMPUTED_VALUE"""),"ADRIANA") -> ADRIANA | C97: =IFERROR(__xludf.DUMMYFUNCTION("""COMPUTED_VALUE"""),"Dapat limit tapi belum diproses") -> Dapat limit tapi belum diproses | D97: =IFERROR(__xludf.DUMMYFUNCTION("""COMPUTED_VALUE"""),"Y21d series") -> Y21d series
A98: =IFERROR(__xludf.DUMMYFUNCTION("""COMPUTED_VALUE"""),45994.61302736111) -> 45994.613 | B98: =IFERROR(__xludf.DUMMYFUNCTION("""COMPUTED_VALUE"""),"ASRI NINGSI RAMBU ATA ENDI") -> ASRI NINGSI RAMBU ATA ENDI | C98: =IFERROR(__xludf.DUMMYFUNCTION("""COMPUTED_VALUE"""),"ACC") -> ACC | D98: =IFERROR(__xludf.DUMMYFUNCTION("""COMPUTED_VALUE"""),"Y21d series") -> Y21d series
A99: =IFERROR(__xludf.DUMMYFUNCTION("""COMPUTED_VALUE"""),45994.62247973379) -> 45994.622 | B99: =IFERROR(__xludf.DUMMYFUNCTION("""COMPUTED_VALUE"""),"SANTI MARIA LUKMINI NAHAK") -> SANTI MARIA LUKMINI NAHAK | C99: =IFERROR(__xludf.DUMMYFUNCTION("""COMPUTED_VALUE"""),"Dapat limit tapi belum diproses") -> Dapat limit tapi belum diproses | D99: =IFERROR(__xludf.DUMMYFUNCTION("""COMPUTED_VALUE"""),"Y400 series") -> Y400 series
A100: =IFERROR(__xludf.DUMMYFUNCTION("""COMPUTED_VALUE"""),45994.625472280095) -> 45994.625 | B100: =IFERROR(__xludf.DUMMYFUNCTION("""COMPUTED_VALUE"""),"NABILA RAHMAWATI") -> NABILA RAHMAWATI | C100: =IFERROR(__xludf.DUMMYFUNCTION("""COMPUTED_VALUE"""),"Dapat limit tapi belum diproses") -> Dapat limit tapi belum diproses | D100: =IFERROR(__xludf.DUMMYFUNCTION("""COMPUTED_VALUE"""),"Y21d series") -> Y21d series
...
